Workbook

Sheet CSO Rates
A1: CSO | B1: AM | C1: AE | D1: 41 | E1: 58 | F1: 58CET | G1: 58CET | H1: 80 | I1: 80 | J1: 80 | K1: 80 | L1: 80 | M1: 80 | N1: 80B | O1: 80B | P1: 80B
A2: Sex | B2: M | C2: M | D2: M | E2: M | F2: M | G2: F | H2: M | I2: M | J2: F | K2: F | L2: U | M2: U | N2: M | O2: F | P2: U
A3: UW | B3: X | C3: X | D3: X | E3: X | F3: X | G3: X | H3: S | I3: N | J3: S | K3: N | L3: S | M3: N | N3: B | O3: B | P3: B
B4: =_xlfn.CONCAT(B1,B2,B3) -> AMMX | C4: =_xlfn.CONCAT(C1,C2,C3) -> AEMX | D4: =_xlfn.CONCAT(D1,D2,D3) -> 41MX | E4: =_xlfn.CONCAT(E1,E2,E3) -> 58MX | F4: =_xlfn.CONCAT(F1,F2,F3) -> 58CETMX | G4: =_xlfn.CONCAT(G1,G2,G3) -> 58CETFX | H4: =_xlfn.CONCAT(H1,H2,H3) -> 80MS | I4: =_xlfn.CONCAT(I1,I2,I3) -> 80MN | ... P4: =_xlfn.CONCAT(P1,P2,P3) -> 80BUB
A5: 0 | B5: 0.11246 | C5: 0.154701 | D5: 0.02258 | E5: 0.00708 | F5: 0.00783 | G5: 0.00695 | H5: 0.00107 | I5: 0.00107 | J5: 0.00087 | K5: 0.00087 | L5: 0.00392 | M5: 0.00392 | N5: 0.00418 | O5: 0.00289 | P5: 0.00392
A6: 1 | B6: 0.02639 | C6: 0.063494 | D6: 0.00577 | E6: 0.00176 | F6: 0.00251 | G6: 0.00242 | H6: 0.00107 | I6: 0.00107 | J6: 0.00087 | K6: 0.00087 | L6: 0.00104 | M6: 0.00104 | N6: 0.00107 | O6: 0.00087 | P6: 0.00104
A7: 2 | B7: 0.01187 | C7: 0.035503 | D7: 0.00414 | E7: 0.00152 | F7: 0.00227 | G7: 0.00216 | H7: 0.00099 | I7: 0.00099 | J7: 0.00081 | K7: 0.00081 | L7: 0.00095 | M7: 0.00095 | N7: 0.00099 | O7: 0.00081 | P7: 0.00095
A8: 3 | B8: 0.00709 | C8: 0.023905 | D8: 0.00338 | E8: 0.00146 | F8: 0.00221 | G8: 0.0021 | H8: 0.00098 | I8: 0.00098 | J8: 0.00079 | K8: 0.00079 | L8: 0.00094 | M8: 0.00094 | N8: 0.00098 | O8: 0.00079 | P8: 0.00094
A9: 4 | B9: 0.00491 | C9: 0.017699 | D9: 0.00299 | E9: 0.0014 | F9: 0.00215 | G9: 0.00204 | H9: 0.00095 | I9: 0.00095 | J9: 0.00077 | K9: 0.00077 | L9: 0.00091 | M9: 0.00091 | N9: 0.00095 | O9: 0.00077 | P9: 0.00091
A10: 5 | B10: 0.00394 | C10: 0.013601 | D10: 0.00276 | E10: 0.00135 | F10: 0.0021 | G10: 0.00199 | H10: 0.0009 | I10: 0.0009 | J10: 0.00076 | K10: 0.00076 | L10: 0.00087 | M10: 0.00087 | N10: 0.0009 | O10: 0.00076 | P10: 0.00087
A11: 6 | B11: 0.00338 | C11: 0.011372 | D11: 0.00261 | E11: 0.0013 | F11: 0.00205 | G11: 0.00194 | H11: 0.00086 | I11: 0.00086 | J11: 0.00073 | K11: 0.00073 | L11: 0.00083 | M11: 0.00083 | N11: 0.00086 | O11: 0.00073 | P11: 0.00083
A12: 7 | B12: 0.00305 | C12: 0.009749 | D12: 0.00247 | E12: 0.00126 | F12: 0.00201 | G12: 0.0019 | H12: 0.0008 | I12: 0.0008 | J12: 0.00072 | K12: 0.00072 | L12: 0.00079 | M12: 0.00079 | N12: 0.0008 | O12: 0.00072 | P12: 0.00079
A13: 8 | B13: 0.00293 | C13: 0.008626 | D13: 0.00231 | E13: 0.00123 | F13: 0.00198 | G13: 0.00187 | H13: 0.00076 | I13: 0.00076 | J13: 0.0007 | K13: 0.0007 | L13: 0.00075 | M13: 0.00075 | N13: 0.00076 | O13: 0.0007 | P13: 0.00075
A14: 9 | B14: 0.00296 | C14: 0.007897 | D14: 0.00212 | E14: 0.00121 | F14: 0.00196 | G14: 0.00186 | H14: 0.00074 | I14: 0.00074 | J14: 0.00069 | K14: 0.00069 | L14: 0.00073 | M14: 0.00073 | N14: 0.00074 | O14: 0.00069 | P14: 0.00073
A15: 10 | B15: 0.00307 | C15: 0.00749 | D15: 0.00197 | E15: 0.00121 | F15: 0.00196 | G15: 0.00186 | H15: 0.00073 | I15: 0.00073 | J15: 0.00068 | K15: 0.00068 | L15: 0.00072 | M15: 0.00072 | N15: 0.00073 | O15: 0.00068 | P15: 0.00072
A16: 11 | B16: 0.00317 | C16: 0.007516 | D16: 0.00191 | E16: 0.00123 | F16: 0.00198 | G16: 0.00187 | H16: 0.00077 | I16: 0.00077 | J16: 0.00069 | K16: 0.00069 | L16: 0.00075 | M16: 0.00075 | N16: 0.00077 | O16: 0.00069 | P16: 0.00075
... A100: 95 | B100: 0.38776 | C100: 1 | D100: 0.39621 | E100: 0.35124 | F100: 0.45661 | G100: 0.34571 | H100: 0.32996 | I100: 0.32996 | J100: 0.31732 | K100: 0.31732 | L100: 0.32489 | M100: 0.32489 | N100: 0.32996 | O100: 0.31732 | P100: 0.32489
A101: 96 | B101: 0.41111 | D101: 0.44719 | E101: 0.40056 | F101: 0.52073 | G101: 0.37609 | H101: 0.38455 | I101: 0.38455 | J101: 0.37574 | K101: 0.37574 | L101: 0.38097 | M101: 0.38097 | N101: 0.38455 | O101: 0.37574 | P101: 0.38097
A102: 97 | B102: 0.4434 | D102: 0.54826 | E102: 0.48842 | F102: 0.63495 | G102: 0.41165 | H102: 0.4802 | I102: 0.4802 | J102: 0.47497 | K102: 0.47497 | L102: 0.47769 | M102: 0.47769 | N102: 0.4802 | O102: 0.47497 | P102: 0.47769
A103: 98 | B103: 0.45763 | D103: 0.72467 | E103: 0.66815 | F103: 0.8686 | G103: 0.45662 | H103: 0.65798 | I103: 0.65798 | J103: 0.65585 | K103: 0.65585 | L103: 0.65738 | M103: 0.65738 | N103: 0.65798 | O103: 0.65585 | P103: 0.65738
A104: 99 | B104: 0.5 | D104: 1 | E104: 1 | F104: 1 | G104: 0.52075 | H104: 1 | I104: 1 | J104: 1 | K104: 1 | L104: 1 | M104: 1 | N104: 1 | O104: 1 | P104: 1
A105: 100 | B105: 0.5625 | G105: 0.635
A106: 101 | B106: 0.57143 | G106: 0.86877
A107: 102 | B107: 0.66667 | G107: 1
A108: 103 | B108: 1
A109: 104
A110: 105
A111: 106
A112: 107
A113: 108
A114: 109
A115: 110
A116: 111
A117: 112
A118: 113
A119: 114
A120: 115
... A126: 121

Sheet Inputs
D1: Output
A2: Mortality Table | B2: 41 | D2: Cash Value | E2: {=_xlfn.let( _xlpm.valdate, B12, _xlpm.daterange, Projection_Monthly!$B$2:$B$1050, _xlpm.cvrange, Projection_Monthly!$L$2:$L$1050, _xlpm.exactmatch, _xlfn.xlookup(_xlpm.valdate, _xlpm.daterange, _xlpm.cvrange, "", 0), IF(_xlpm.exactmatch<>"", _xlpm.exactmatch, _xlfn.let( _xlpm.datebefore, _xlfn.xlookup(_xlpm.valdate, _xlpm.daterange, _xlpm.daterange, "", -1), _xlpm.dateafter, _xlfn.xlookup(_xlpm.valdate, _xlpm.daterange, _xlpm.daterange, "", 1), _xlpm.cvbefore, _xlfn.xlookup(_xlpm.datebefore, _xlpm.daterange, _xlpm.cvrange), _xlpm.cvafter, _xlfn.xlookup(_xlpm.dateafter, _xlpm.daterange, _xlpm.cvrange), _xlpm.daysbetween, _xlpm.dateafter - _xlpm.datebefore, _xlpm.daysfrombefore, _xlpm.valdate - _xlpm.datebefore, _xlpm.fraction, _xlpm.daysfrombefore / _xlpm.daysbetween, _xlpm.cvbefore + _xlpm.fraction * (_xlpm.cvafter - _xlpm.cvbefore) ) ) )} -> #NAME? | G2: Legend
A3: Underwriting Class | B3: X | C3: Ben_info | D3: PUA Cash Value | E3: {=_xlfn.let( _xlpm.valdate, B13, _xlpm.daterange, Projection_Monthly!$B$2:$B$1050, _xlpm.cvrange, Projection_Monthly!$M$2:$M$1050, _xlpm.exactmatch, _xlfn.xlookup(_xlpm.valdate, _xlpm.daterange, _xlpm.cvrange, "", 0), IF(_xlpm.exactmatch<>"", _xlpm.exactmatch, _xlfn.let( _xlpm.datebefore, _xlfn.xlookup(_xlpm.valdate, _xlpm.daterange, _xlpm.daterange, "", -1), _xlpm.dateafter, _xlfn.xlookup(_xlpm.valdate, _xlpm.daterange, _xlpm.daterange, "", 1), _xlpm.cvbefore, _xlfn.xlookup(_xlpm.datebefore, _xlpm.daterange, _xlpm.cvrange), _xlpm.cvafter, _xlfn.xlookup(_xlpm.dateafter, _xlpm.daterange, _xlpm.cvrange), _xlpm.daysbetween, _xlpm.dateafter - _xlpm.datebefore, _xlpm.daysfrombefore, _xlpm.valdate - _xlpm.datebefore, _xlpm.fraction, _xlpm.daysfrombefore / _xlpm.daysbetween, _xlpm.cvbefore + _xlpm.fraction * (_xlpm.cvafter - _xlpm.cvbefore) ) ) )+$B$19} -> #NAME? | H3: Link with Data | K3: Matched Policies
A4: Plan Code | B4: 34 | C4: Policy_info | D4: ETI | E4: =ETI!E6 | H4: Formulae | K4: Policy Number | L4: 05451200 | M4: 13657260 | N4: 13353710 | O4: 13535530 | P4: 07340050
A5: Policy Number | B5: 07340050 | C5: Policy_info | D5: RPU | E5: =RPU!B17 | H5: Dropdown Selection | K5: Gender | L5: Male | M5: Female | N5: Female | O5: Female | P5: Female
A6: Gender | B6: M | C6: Ben_info | D6: APL | E6: =APL!F10 | K6: Units | L6: 10 | M6: 5 | N6: 2 | O6: 10 | P6: 50
A7: Issue Age | B7: =ROUND((B11-B14)/365.25,0) -> 16 | C7: Age nearest birthday | D7: Loan Outstanding | E7: =IF(B32="D",VLOOKUP("Valuation",Loan!$C$28:$G$40,5,0),IF(B32="A",VLOOKUP("Valuation",Loan!$L$28:$P$40,5,0),"Not Found")) -> 413.94772 | K7: PUA Units | P7: 159.997
A8: Premium Paying Term (PPT) | B8: 30 | C8: Enter Premium Paying Term (years) User input | K8: Issue Date | L8: 29132 | M8: 30832 | N8: 28900 | O8: 29373 | P8: 21706
A9: Units | B9: 50 | C9: Ben_info | K9: Valuation Date | L9: 46155 | M9: 46172 | N9: 46172 | O9: 46172 | P9: 46172
A10: PUA Units | B10: 159.997 | C10: Ben_info | K10: DOB | L10: 13072 | M10: 30354 | N10: 28730 | O10: 28150 | P10: 15687
A11: Issue Date | B11: 21706 | C11: Ben_info | K11: Mortality | L11: 41CSO250 | M11: 58CSO300 | N11: 58CSO300 | O11: 58CSO300 | P11: 41CSO250
A12: Valuation Date | B12: 46178 | C12: Input Value | K12: Age Basis | L12: Age Nearest | M12: Age Nearest | N12: Age Nearest | O12: Age Nearest | P12: Age Nearest
A13: Last Anniversary | B13: =IF(DATE(YEAR($B$12),MONTH($B$11),MIN(DAY($B$11), DAY(EOMONTH(DATE(YEAR($B$12),MONTH($B$11),1),0)))) <=$B$12, DATE(YEAR($B$12),MONTH($B$11),MIN(DAY($B$11), DAY(EOMONTH(DATE(YEAR($B$12),MONTH($B$11),1),0)))), DATE(YEAR($B$12)-1,MONTH($B$11),MIN(DAY($B$11), DAY(EOMONTH(DATE(YEAR($B$12)-1,MONTH($B$11),1),0))))) -> 46178
A14: DOB | B14: 15687 | C14: Name_Add
A15: Current age | B15: =ROUND(YEAR(B13)-YEAR(B14)+(MONTH(B13)-MONTH(B14))/12+(DAY(B13)-DAY(B14)-1)/360,0) -> 83 | D15: Age at Valuation Date
A16: Duration(x) | B16: =INT((B12-B11)/365.25) -> 67 | D16: Policy Duration (complete years)
A17: Duration(x+1) | B17: =B16+1 -> 68 | D17: Duration for next anniversary
A18: Base SA | B18: =B9*1000 -> 50000
A19: Declared Dividend (After Conv Date) | B19: 0 | C19: New field from Div data | D19: 2426.37
A20: Declared Dividend Rate (p.a.) | B20: 0
A21: Expense Loading Factor | B21: 0.03
A22: Dividend Option | B22: PUA
A23: Accumulation Interest Rate (p.a.) | B23: 0.025
A24: Annual Base Premium | B24: 77 | C24: Ben_info
A25: Modal Premium | B25: =B24*B27 -> 77
A26: Premium Mode | B26: Annual
A27: Modal Factor | B27: {=_xlfn.SWITCH(B26,"Annual",1,"Semi-Annual",0.5,"Quarterly",0.25,"Monthly",1/12,1)} -> 1 | C27: Policy_info
A28: Contract Status | B28: A | C28: Policy_info
A29: Premium Paid-Up Duration | B29: =MIN(B8,B16) -> 30 | D29: MIN(PPT, Duration)
A30: Is Currently Paying Premium | B30: =EDATE(B11,B8*12)>B12 -> FALSE | D30: TRUE if PPT End Date > Valuation Date
A31: Loan Intrest Rate | B31: 0.05 | C31: c_ln_loan_curr_int_rate
A32: Loan Interest Type | B32: A | C32: c_ln_loan_int_method ( A-Arrear, D- Advance)
A33: Loan Start Date | B33: 45213 | C33: c_ln_loan_curr_bal_date
A34: Starting Loan Amount | B34: 373.37 | C34: c_ln_curr_loan_balance
A35: Loan Repayment Date
A36: Repayment Amount | C36: c_ln_loan_repaid_to_date

Sheet MORTALITY
A1: Age | B1: =_xlfn.CONCAT(Inputs!B2,Inputs!B6,Inputs!B3) -> 41MX | D1: Age | E1: q_x (1958 CET ANB MALE)
A2: 0 | B2: =INDEX('CSO Rates'!$A$5:$P$126,MATCH(A2,'CSO Rates'!$A$5:$A$126,0),MATCH($B$1,'CSO Rates'!$A$4:$P$4,0)) -> 0.02258 | D2: 0 | E2: 0.00376
A3: =+A2+1 -> 1 | B3: =INDEX('CSO Rates'!$A$5:$P$126,MATCH(A3,'CSO Rates'!$A$5:$A$126,0),MATCH($B$1,'CSO Rates'!$A$4:$P$4,0)) -> 0.00577 | D3: 1 | E3: 0.00162
A4: =+A3+1 -> 2 | B4: =INDEX('CSO Rates'!$A$5:$P$126,MATCH(A4,'CSO Rates'!$A$5:$A$126,0),MATCH($B$1,'CSO Rates'!$A$4:$P$4,0)) -> 0.00414 | D4: 2 | E4: 0.00156
A5: =+A4+1 -> 3 | B5: =INDEX('CSO Rates'!$A$5:$P$126,MATCH(A5,'CSO Rates'!$A$5:$A$126,0),MATCH($B$1,'CSO Rates'!$A$4:$P$4,0)) -> 0.00338 | D5: 3 | E5: 0.00154
A6: =+A5+1 -> 4 | B6: =INDEX('CSO Rates'!$A$5:$P$126,MATCH(A6,'CSO Rates'!$A$5:$A$126,0),MATCH($B$1,'CSO Rates'!$A$4:$P$4,0)) -> 0.00299 | D6: 4 | E6: 0.00152
A7: =+A6+1 -> 5 | B7: =INDEX('CSO Rates'!$A$5:$P$126,MATCH(A7,'CSO Rates'!$A$5:$A$126,0),MATCH($B$1,'CSO Rates'!$A$4:$P$4,0)) -> 0.00276 | D7: 5 | E7: 0.00151
A8: =+A7+1 -> 6 | B8: =INDEX('CSO Rates'!$A$5:$P$126,MATCH(A8,'CSO Rates'!$A$5:$A$126,0),MATCH($B$1,'CSO Rates'!$A$4:$P$4,0)) -> 0.00261 | D8: 6 | E8: 0.00148
A9: =+A8+1 -> 7 | B9: =INDEX('CSO Rates'!$A$5:$P$126,MATCH(A9,'CSO Rates'!$A$5:$A$126,0),MATCH($B$1,'CSO Rates'!$A$4:$P$4,0)) -> 0.00247 | D9: 7 | E9: 0.00147
A10: =+A9+1 -> 8 | B10: =INDEX('CSO Rates'!$A$5:$P$126,MATCH(A10,'CSO Rates'!$A$5:$A$126,0),MATCH($B$1,'CSO Rates'!$A$4:$P$4,0)) -> 0.00231 | D10: 8 | E10: 0.00145
A11: =+A10+1 -> 9 | B11: =INDEX('CSO Rates'!$A$5:$P$126,MATCH(A11,'CSO Rates'!$A$5:$A$126,0),MATCH($B$1,'CSO Rates'!$A$4:$P$4,0)) -> 0.00212 | D11: 9 | E11: 0.00144
A12: =+A11+1 -> 10 | B12: =INDEX('CSO Rates'!$A$5:$P$126,MATCH(A12,'CSO Rates'!$A$5:$A$126,0),MATCH($B$1,'CSO Rates'!$A$4:$P$4,0)) -> 0.00197 | D12: 10 | E12: 0.00143
A13: =+A12+1 -> 11 | B13: =INDEX('CSO Rates'!$A$5:$P$126,MATCH(A13,'CSO Rates'!$A$5:$A$126,0),MATCH($B$1,'CSO Rates'!$A$4:$P$4,0)) -> 0.00191 | D13: 11 | E13: 0.00144
A14: =+A13+1 -> 12 | B14: =INDEX('CSO Rates'!$A$5:$P$126,MATCH(A14,'CSO Rates'!$A$5:$A$126,0),MATCH($B$1,'CSO Rates'!$A$4:$P$4,0)) -> 0.00192 | D14: 12 | E14: 0.00147
... A101: =+A100+1 -> 99 | B101: =INDEX('CSO Rates'!$A$5:$P$126,MATCH(A101,'CSO Rates'!$A$5:$A$126,0),MATCH($B$1,'CSO Rates'!$A$4:$P$4,0)) -> 1 | D101: 99 | E101: 1
D102: 100 | E102: 0
D103: 101 | E103: 0
D104: 102 | E104: 0
D105: 103 | E105: 0
D106: 104 | E106: 0
D107: 105 | E107: 0
D108: 106 | E108: 0
D109: 107 | E109: 0
D110: 108 | E110: 0
D111: 109 | E111: 0
D112: 110 | E112: 0
D113: 111 | E113: 0
... D122: 120 | E122: 0

Sheet Projection (Annual)
A1: Policy Number | B1: Plan Name | C1: Date | D1: Year | E1: Age | F1: Duration | G1: CV Factor (x+1) | H1: CV Factor (x) | I1: Days to next anniversary | J1: CV
A2: =Inputs!$B$5 -> 07340050 | B2: =Inputs!$B$4 -> 34 | C2: =Inputs!$B$12 -> 46178 | D2: 0 | E2: =Inputs!$B$7 -> 16 | F2: =Inputs!$B$16 -> 67 | G2: =IFERROR(INDEX(CV_RATES!$K:$K,MATCH(F2+1,CV_RATES!$C:$C,0)),0) -> 904.65633 | H2: =IFERROR(INDEX(CV_RATES!$K:$K,MATCH(F2,CV_RATES!$C:$C,0)),0) -> 899.32366 | I2: 68 | J2: =(H2*Inputs!$B$9)+(G2-H2)*Inputs!$B$9*I2/365 -> 45015.857
A3: =Inputs!$B$5 -> 07340050 | B3: =Inputs!$B$4 -> 34 | C3: =DATE(YEAR(C2)+1,MONTH(C2),DAY(C2)) -> 46543 | D3: =IF(E3<>"",D2+1) -> 1 | E3: =IF(E2<=100,E2+1,"") -> 17 | F3: =IF(D3<>"",F2+1,"") -> 68 | G3: =IFERROR(INDEX(CV_RATES!$K:$K,MATCH(F3+1,CV_RATES!$C:$C,0)),0) -> 909.75312 | H3: =IFERROR(INDEX(CV_RATES!$K:$K,MATCH(F3,CV_RATES!$C:$C,0)),0) -> 904.65633 | I3: 365 | J3: =(H3*Inputs!$B$9)+(G3-H3)*Inputs!$B$9*I3/365 -> 45487.656
A4: =Inputs!$B$5 -> 07340050 | B4: =Inputs!$B$4 -> 34 | C4: =DATE(YEAR(C3)+1,MONTH(C3),DAY(C3)) -> 46909 | D4: =IF(E4<>"",D3+1) -> 2 | E4: =IF(E3<=100,E3+1,"") -> 18 | F4: =IF(D4<>"",F3+1,"") -> 69 | G4: =IFERROR(INDEX(CV_RATES!$K:$K,MATCH(F4+1,CV_RATES!$C:$C,0)),0) -> 914.62118 | H4: =IFERROR(INDEX(CV_RATES!$K:$K,MATCH(F4,CV_RATES!$C:$C,0)),0) -> 909.75312 | I4: 365 | J4: =(H4*Inputs!$B$9)+(G4-H4)*Inputs!$B$9*I4/365 -> 45731.059
A5: =Inputs!$B$5 -> 07340050 | B5: =Inputs!$B$4 -> 34 | C5: =DATE(YEAR(C4)+1,MONTH(C4),DAY(C4)) -> 47274 | D5: =IF(E5<>"",D4+1) -> 3 | E5: =IF(E4<=100,E4+1,"") -> 19 | F5: =IF(D5<>"",F4+1,"") -> 70 | G5: =IFERROR(INDEX(CV_RATES!$K:$K,MATCH(F5+1,CV_RATES!$C:$C,0)),0) -> 919.27206 | H5: =IFERROR(INDEX(CV_RATES!$K:$K,MATCH(F5,CV_RATES!$C:$C,0)),0) -> 914.62118 | I5: 365 | J5: =(H5*Inputs!$B$9)+(G5-H5)*Inputs!$B$9*I5/365 -> 45963.603
A6: =Inputs!$B$5 -> 07340050 | B6: =Inputs!$B$4 -> 34 | C6: =DATE(YEAR(C5)+1,MONTH(C5),DAY(C5)) -> 47639 | D6: =IF(E6<>"",D5+1) -> 4 | E6: =IF(E5<=100,E5+1,"") -> 20 | F6: =IF(D6<>"",F5+1,"") -> 71 | G6: =IFERROR(INDEX(CV_RATES!$K:$K,MATCH(F6+1,CV_RATES!$C:$C,0)),0) -> 923.71713 | H6: =IFERROR(INDEX(CV_RATES!$K:$K,MATCH(F6,CV_RATES!$C:$C,0)),0) -> 919.27206 | I6: 365 | J6: =(H6*Inputs!$B$9)+(G6-H6)*Inputs!$B$9*I6/365 -> 46185.856
A7: =Inputs!$B$5 -> 07340050 | B7: =Inputs!$B$4 -> 34 | C7: =DATE(YEAR(C6)+1,MONTH(C6),DAY(C6)) -> 48004 | D7: =IF(E7<>"",D6+1) -> 5 | E7: =IF(E6<=100,E6+1,"") -> 21 | F7: =IF(D7<>"",F6+1,"") -> 72 | G7: =IFERROR(INDEX(CV_RATES!$K:$K,MATCH(F7+1,CV_RATES!$C:$C,0)),0) -> 927.98155 | H7: =IFERROR(INDEX(CV_RATES!$K:$K,MATCH(F7,CV_RATES!$C:$C,0)),0) -> 923.71713 | I7: 365 | J7: =(H7*Inputs!$B$9)+(G7-H7)*Inputs!$B$9*I7/365 -> 46399.078
A8: =Inputs!$B$5 -> 07340050 | B8: =Inputs!$B$4 -> 34 | C8: =DATE(YEAR(C7)+1,MONTH(C7),DAY(C7)) -> 48370 | D8: =IF(E8<>"",D7+1) -> 6 | E8: =IF(E7<=100,E7+1,"") -> 22 | F8: =IF(D8<>"",F7+1,"") -> 73 | G8: =IFERROR(INDEX(CV_RATES!$K:$K,MATCH(F8+1,CV_RATES!$C:$C,0)),0) -> 932.1026 | H8: =IFERROR(INDEX(CV_RATES!$K:$K,MATCH(F8,CV_RATES!$C:$C,0)),0) -> 927.98155 | I8: 365 | J8: =(H8*Inputs!$B$9)+(G8-H8)*Inputs!$B$9*I8/365 -> 46605.13
A9: =Inputs!$B$5 -> 07340050 | B9: =Inputs!$B$4 -> 34 | C9: =DATE(YEAR(C8)+1,MONTH(C8),DAY(C8)) -> 48735 | D9: =IF(E9<>"",D8+1) -> 7 | E9: =IF(E8<=100,E8+1,"") -> 23 | F9: =IF(D9<>"",F8+1,"") -> 74 | G9: =IFERROR(INDEX(CV_RATES!$K:$K,MATCH(F9+1,CV_RATES!$C:$C,0)),0) -> 936.13526 | H9: =IFERROR(INDEX(CV_RATES!$K:$K,MATCH(F9,CV_RATES!$C:$C,0)),0) -> 932.1026 | I9: 365 | J9: =(H9*Inputs!$B$9)+(G9-H9)*Inputs!$B$9*I9/365 -> 46806.763
A10: =Inputs!$B$5 -> 07340050 | B10: =Inputs!$B$4 -> 34 | C10: =DATE(YEAR(C9)+1,MONTH(C9),DAY(C9)) -> 49100 | D10: =IF(E10<>"",D9+1) -> 8 | E10: =IF(E9<=100,E9+1,"") -> 24 | F10: =IF(D10<>"",F9+1,"") -> 75 | G10: =IFERROR(INDEX(CV_RATES!$K:$K,MATCH(F10+1,CV_RATES!$C:$C,0)),0) -> 940.17778 | H10: =IFERROR(INDEX(CV_RATES!$K:$K,MATCH(F10,CV_RATES!$C:$C,0)),0) -> 936.13526 | I10: 365 | J10: =(H10*Inputs!$B$9)+(G10-H10)*Inputs!$B$9*I10/365 -> 47008.889
A11: =Inputs!$B$5 -> 07340050 | B11: =Inputs!$B$4 -> 34 | C11: =DATE(YEAR(C10)+1,MONTH(C10),DAY(C10)) -> 49465 | D11: =IF(E11<>"",D10+1) -> 9 | E11: =IF(E10<=100,E10+1,"") -> 25 | F11: =IF(D11<>"",F10+1,"") -> 76 | G11: =IFERROR(INDEX(CV_RATES!$K:$K,MATCH(F11+1,CV_RATES!$C:$C,0)),0) -> 944.41214 | H11: =IFERROR(INDEX(CV_RATES!$K:$K,MATCH(F11,CV_RATES!$C:$C,0)),0) -> 940.17778 | I11: 365 | J11: =(H11*Inputs!$B$9)+(G11-H11)*Inputs!$B$9*I11/365 -> 47220.607
A12: =Inputs!$B$5 -> 07340050 | B12: =Inputs!$B$4 -> 34 | C12: =DATE(YEAR(C11)+1,MONTH(C11),DAY(C11)) -> 49831 | D12: =IF(E12<>"",D11+1) -> 10 | E12: =IF(E11<=100,E11+1,"") -> 26 | F12: =IF(D12<>"",F11+1,"") -> 77 | G12: =IFERROR(INDEX(CV_RATES!$K:$K,MATCH(F12+1,CV_RATES!$C:$C,0)),0) -> 949.16127 | H12: =IFERROR(INDEX(CV_RATES!$K:$K,MATCH(F12,CV_RATES!$C:$C,0)),0) -> 944.41214 | I12: 365 | J12: =(H12*Inputs!$B$9)+(G12-H12)*Inputs!$B$9*I12/365 -> 47458.064
A13: =Inputs!$B$5 -> 07340050 | B13: =Inputs!$B$4 -> 34 | C13: =DATE(YEAR(C12)+1,MONTH(C12),DAY(C12)) -> 50196 | D13: =IF(E13<>"",D12+1) -> 11 | E13: =IF(E12<=100,E12+1,"") -> 27 | F13: =IF(D13<>"",F12+1,"") -> 78 | G13: =IFERROR(INDEX(CV_RATES!$K:$K,MATCH(F13+1,CV_RATES!$C:$C,0)),0) -> 955.10078 | H13: =IFERROR(INDEX(CV_RATES!$K:$K,MATCH(F13,CV_RATES!$C:$C,0)),0) -> 949.16127 | I13: 365 | J13: =(H13*Inputs!$B$9)+(G13-H13)*Inputs!$B$9*I13/365 -> 47755.039
A14: =Inputs!$B$5 -> 07340050 | B14: =Inputs!$B$4 -> 34 | C14: =DATE(YEAR(C13)+1,MONTH(C13),DAY(C13)) -> 50561 | D14: =IF(E14<>"",D13+1) -> 12 | E14: =IF(E13<=100,E13+1,"") -> 28 | F14: =IF(D14<>"",F13+1,"") -> 79 | G14: =IFERROR(INDEX(CV_RATES!$K:$K,MATCH(F14+1,CV_RATES!$C:$C,0)),0) -> 961.97302 | H14: =IFERROR(INDEX(CV_RATES!$K:$K,MATCH(F14,CV_RATES!$C:$C,0)),0) -> 955.10078 | I14: 365 | J14: =(H14*Inputs!$B$9)+(G14-H14)*Inputs!$B$9*I14/365 -> 48098.651
... A44: =Inputs!$B$5 -> 07340050 | B44: =Inputs!$B$4 -> 34 | C44: =DATE(YEAR(C43)+1,MONTH(C43),DAY(C43)) -> 61519 | D44: =IF(E44<>"",D43+1) -> 42 | E44: =IF(E43<=100,E43+1,"") -> 58 | F44: =IF(D44<>"",F43+1,"") -> 109 | G44: =IFERROR(INDEX(CV_RATES!$K:$K,MATCH(F44+1,CV_RATES!$C:$C,0)),0) -> 0 | H44: =IFERROR(INDEX(CV_RATES!$K:$K,MATCH(F44,CV_RATES!$C:$C,0)),0) -> 0 | I44: 365 | J44: =(H44*Inputs!$B$9)+(G44-H44)*Inputs!$B$9*I44/365 -> 0
A45: =Inputs!$B$5 -> 07340050 | B45: =Inputs!$B$4 -> 34 | C45: =DATE(YEAR(C44)+1,MONTH(C44),DAY(C44)) -> 61884 | D45: =IF(E45<>"",D44+1) -> 43 | E45: =IF(E44<=100,E44+1,"") -> 59 | F45: =IF(D45<>"",F44+1,"") -> 110 | G45: =IFERROR(INDEX(CV_RATES!$K:$K,MATCH(F45+1,CV_RATES!$C:$C,0)),0) -> 0 | H45: =IFERROR(INDEX(CV_RATES!$K:$K,MATCH(F45,CV_RATES!$C:$C,0)),0) -> 0 | I45: 365
A46: =Inputs!$B$5 -> 07340050 | B46: =Inputs!$B$4 -> 34 | C46: =DATE(YEAR(C45)+1,MONTH(C45),DAY(C45)) -> 62249 | D46: =IF(E46<>"",D45+1) -> 44 | E46: =IF(E45<=100,E45+1,"") -> 60 | F46: =IF(D46<>"",F45+1,"") -> 111 | G46: =IFERROR(INDEX(CV_RATES!$K:$K,MATCH(F46+1,CV_RATES!$C:$C,0)),0) -> 0 | H46: =IFERROR(INDEX(CV_RATES!$K:$K,MATCH(F46,CV_RATES!$C:$C,0)),0) -> 0 | I46: 365
A47: =Inputs!$B$5 -> 07340050 | B47: =Inputs!$B$4 -> 34 | C47: =DATE(YEAR(C46)+1,MONTH(C46),DAY(C46)) -> 62614 | D47: =IF(E47<>"",D46+1) -> 45 | E47: =IF(E46<=100,E46+1,"") -> 61 | F47: =IF(D47<>"",F46+1,"") -> 112 | G47: =IFERROR(INDEX(CV_RATES!$K:$K,MATCH(F47+1,CV_RATES!$C:$C,0)),0) -> 0 | H47: =IFERROR(INDEX(CV_RATES!$K:$K,MATCH(F47,CV_RATES!$C:$C,0)),0) -> 0 | I47: 365
A48: =Inputs!$B$5 -> 07340050 | B48: =Inputs!$B$4 -> 34 | C48: =DATE(YEAR(C47)+1,MONTH(C47),DAY(C47)) -> 62980 | D48: =IF(E48<>"",D47+1) -> 46 | E48: =IF(E47<=100,E47+1,"") -> 62 | F48: =IF(D48<>"",F47+1,"") -> 113 | G48: =IFERROR(INDEX(CV_RATES!$K:$K,MATCH(F48+1,CV_RATES!$C:$C,0)),0) -> 0 | H48: =IFERROR(INDEX(CV_RATES!$K:$K,MATCH(F48,CV_RATES!$C:$C,0)),0) -> 0 | I48: 365
A49: =Inputs!$B$5 -> 07340050 | B49: =Inputs!$B$4 -> 34 | C49: =DATE(YEAR(C48)+1,MONTH(C48),DAY(C48)) -> 63345 | D49: =IF(E49<>"",D48+1) -> 47 | E49: =IF(E48<=100,E48+1,"") -> 63 | F49: =IF(D49<>"",F48+1,"") -> 114 | G49: =IFERROR(INDEX(CV_RATES!$K:$K,MATCH(F49+1,CV_RATES!$C:$C,0)),0) -> 0 | H49: =IFERROR(INDEX(CV_RATES!$K:$K,MATCH(F49,CV_RATES!$C:$C,0)),0) -> 0 | I49: 365
A50: =Inputs!$B$5 -> 07340050 | B50: =Inputs!$B$4 -> 34 | C50: =DATE(YEAR(C49)+1,MONTH(C49),DAY(C49)) -> 63710 | D50: =IF(E50<>"",D49+1) -> 48 | E50: =IF(E49<=100,E49+1,"") -> 64 | F50: =IF(D50<>"",F49+1,"") -> 115 | G50: =IFERROR(INDEX(CV_RATES!$K:$K,MATCH(F50+1,CV_RATES!$C:$C,0)),0) -> 0 | H50: =IFERROR(INDEX(CV_RATES!$K:$K,MATCH(F50,CV_RATES!$C:$C,0)),0) -> 0 | I50: 365
A51: =Inputs!$B$5 -> 07340050 | B51: =Inputs!$B$4 -> 34 | C51: =DATE(YEAR(C50)+1,MONTH(C50),DAY(C50)) -> 64075 | D51: =IF(E51<>"",D50+1) -> 49 | E51: =IF(E50<=100,E50+1,"") -> 65 | F51: =IF(D51<>"",F50+1,"") -> 116 | G51: =IFERROR(INDEX(CV_RATES!$K:$K,MATCH(F51+1,CV_RATES!$C:$C,0)),0) -> 0 | H51: =IFERROR(INDEX(CV_RATES!$K:$K,MATCH(F51,CV_RATES!$C:$C,0)),0) -> 0 | I51: 365
A52: =Inputs!$B$5 -> 07340050 | B52: =Inputs!$B$4 -> 34 | C52: =DATE(YEAR(C51)+1,MONTH(C51),DAY(C51)) -> 64441 | D52: =IF(E52<>"",D51+1) -> 50 | E52: =IF(E51<=100,E51+1,"") -> 66 | F52: =IF(D52<>"",F51+1,"") -> 117 | G52: =IFERROR(INDEX(CV_RATES!$K:$K,MATCH(F52+1,CV_RATES!$C:$C,0)),0) -> 0 | H52: =IFERROR(INDEX(CV_RATES!$K:$K,MATCH(F52,CV_RATES!$C:$C,0)),0) -> 0 | I52: 365
A53: =Inputs!$B$5 -> 07340050 | B53: =Inputs!$B$4 -> 34 | C53: =DATE(YEAR(C52)+1,MONTH(C52),DAY(C52)) -> 64806 | D53: =IF(E53<>"",D52+1) -> 51 | E53: =IF(E52<=100,E52+1,"") -> 67 | F53: =IF(D53<>"",F52+1,"") -> 118 | G53: =IFERROR(INDEX(CV_RATES!$K:$K,MATCH(F53+1,CV_RATES!$C:$C,0)),0) -> 0 | H53: =IFERROR(INDEX(CV_RATES!$K:$K,MATCH(F53,CV_RATES!$C:$C,0)),0) -> 0 | I53: 365
A54: =Inputs!$B$5 -> 07340050 | B54: =Inputs!$B$4 -> 34 | C54: =DATE(YEAR(C53)+1,MONTH(C53),DAY(C53)) -> 65171 | D54: =IF(E54<>"",D53+1) -> 52 | E54: =IF(E53<=100,E53+1,"") -> 68 | F54: =IF(D54<>"",F53+1,"") -> 119 | G54: =IFERROR(INDEX(CV_RATES!$K:$K,MATCH(F54+1,CV_RATES!$C:$C,0)),0) -> 0 | H54: =IFERROR(INDEX(CV_RATES!$K:$K,MATCH(F54,CV_RATES!$C:$C,0)),0) -> 0 | I54: 365
A55: =Inputs!$B$5 -> 07340050 | B55: =Inputs!$B$4 -> 34 | C55: =DATE(YEAR(C54)+1,MONTH(C54),DAY(C54)) -> 65536 | D55: =IF(E55<>"",D54+1) -> 53 | E55: =IF(E54<=100,E54+1,"") -> 69 | F55: =IF(D55<>"",F54+1,"") -> 120 | G55: =IFERROR(INDEX(CV_RATES!$K:$K,MATCH(F55+1,CV_RATES!$C:$C,0)),0) -> 0 | H55: =IFERROR(INDEX(CV_RATES!$K:$K,MATCH(F55,CV_RATES!$C:$C,0)),0) -> 0 | I55: 365
A56: =Inputs!$B$5 -> 07340050 | B56: =Inputs!$B$4 -> 34 | C56: =DATE(YEAR(C55)+1,MONTH(C55),DAY(C55)) -> 65902 | D56: =IF(E56<>"",D55+1) -> 54 | E56: =IF(E55<=100,E55+1,"") -> 70 | F56: =IF(D56<>"",F55+1,"") -> 121 | G56: =IFERROR(INDEX(CV_RATES!$K:$K,MATCH(F56+1,CV_RATES!$C:$C,0)),0) -> 0 | H56: =IFERROR(INDEX(CV_RATES!$K:$K,MATCH(F56,CV_RATES!$C:$C,0)),0) -> 0 | I56: 365
... A100: =Inputs!$B$5 -> 07340050 | B100: =Inputs!$B$4 -> 34 | C100: =DATE(YEAR(C99)+1,MONTH(C99),DAY(C99)) -> 81972 | D100: =IF(E100<>"",D99+1) -> FALSE | E100: =IF(E99<=100,E99+1,"") | F100: =IF(D100<>"",F99+1,"") -> 165 | G100: =IFERROR(INDEX(CV_RATES!$K:$K,MATCH(F100+1,CV_RATES!$C:$C,0)),0) -> 0 | H100: =IFERROR(INDEX(CV_RATES!$K:$K,MATCH(F100,CV_RATES!$C:$C,0)),0) -> 0 | I100: 365

Sheet Commutation
A1: Age | B1: qx | C1: lx | D1: dx | E1: v^x | F1: Dx | G1: Cx | H1: Nx | I1: Mx | J1: ax_due | K1: Ax | L1: NLP_per_1000 | M1: LPP_NLP_per_1000
A2: 0 | B2: =IF(A2="","",IFERROR(INDEX(MORTALITY!$B:$B,MATCH(A2,MORTALITY!$A:$A,0)),0)) -> 0.02258 | C2: 10000000 | D2: =IF(A2="","",IFERROR(C2*B2,0)) -> 225800 | E2: =IF(A2="","",IFERROR((1/(1+Inputs!$B$23))^A2,0)) -> 1 | F2: =IF(A2="","",IFERROR(C2*E2,0)) -> 10000000 | G2: =IF(A2="","",IFERROR(D2*(1/(1+Inputs!$B$23))^(A2+1),0)) -> 220292.68 | H2: =IF(A2="","",IFERROR(IF(B2=1,F2,F2+H3),0)) -> 3.0665805e+08 | I2: =IF(A2="","",IFERROR(IF(B2=1,G2,G2+I3),0)) -> 2520535.3 | J2: =IF(A2="","",IFERROR(H2/F2,0)) -> 30.665805 | K2: =IF(A2="","",IFERROR(I2/F2,0)) -> 0.25205353 | L2: =IF(A2="","",IFERROR(1000*I2/H2,0)) -> 8.2193676 | M2: =IF(A2="","",IFERROR(1000*I2/(H2-INDEX(H:H,MATCH(A2+Inputs!$B$8,$A:$A,0))),0)) -> 12.409866
A3: =IF(OR(A2="",A2>=MAX(MORTALITY!$A:$A)),"",A2+1) -> 1 | B3: =IF(A3="","",IFERROR(INDEX(MORTALITY!$B:$B,MATCH(A3,MORTALITY!$A:$A,0)),0)) -> 0.00577 | C3: =IF(A3="","",IFERROR(C2*(1-B2),0)) -> 9774200 | D3: =IF(A3="","",IFERROR(C3*B3,0)) -> 56397.134 | E3: =IF(A3="","",IFERROR((1/(1+Inputs!$B$23))^A3,0)) -> 0.97560976 | F3: =IF(A3="","",IFERROR(C3*E3,0)) -> 9535804.9 | G3: =IF(A3="","",IFERROR(D3*(1/(1+Inputs!$B$23))^(A3+1),0)) -> 53679.604 | H3: =IF(A3="","",IFERROR(IF(B3=1,F3,F3+H4),0)) -> 2.9665805e+08 | I3: =IF(A3="","",IFERROR(IF(B3=1,G3,G3+I4),0)) -> 2300242.6 | J3: =IF(A3="","",IFERROR(H3/F3,0)) -> 31.109912 | K3: =IF(A3="","",IFERROR(I3/F3,0)) -> 0.24122165 | L3: =IF(A3="","",IFERROR(1000*I3/H3,0)) -> 7.7538518 | M3: =IF(A3="","",IFERROR(1000*I3/(H3-INDEX(H:H,MATCH(A3+Inputs!$B$8,$A:$A,0))),0)) -> 11.651763
A4: =IF(OR(A3="",A3>=MAX(MORTALITY!$A:$A)),"",A3+1) -> 2 | B4: =IF(A4="","",IFERROR(INDEX(MORTALITY!$B:$B,MATCH(A4,MORTALITY!$A:$A,0)),0)) -> 0.00414 | C4: =IF(A4="","",IFERROR(C3*(1-B3),0)) -> 9717802.9 | D4: =IF(A4="","",IFERROR(C4*B4,0)) -> 40231.704 | E4: =IF(A4="","",IFERROR((1/(1+Inputs!$B$23))^A4,0)) -> 0.9518144 | F4: =IF(A4="","",IFERROR(C4*E4,0)) -> 9249544.7 | G4: =IF(A4="","",IFERROR(D4*(1/(1+Inputs!$B$23))^(A4+1),0)) -> 37359.137 | H4: =IF(A4="","",IFERROR(IF(B4=1,F4,F4+H5),0)) -> 2.8712225e+08 | I4: =IF(A4="","",IFERROR(IF(B4=1,G4,G4+I5),0)) -> 2246563 | J4: =IF(A4="","",IFERROR(H4/F4,0)) -> 31.041771 | K4: =IF(A4="","",IFERROR(I4/F4,0)) -> 0.24288363 | L4: =IF(A4="","",IFERROR(1000*I4/H4,0)) -> 7.8244128 | M4: =IF(A4="","",IFERROR(1000*I4/(H4-INDEX(H:H,MATCH(A4+Inputs!$B$8,$A:$A,0))),0)) -> 11.696678
A5: =IF(OR(A4="",A4>=MAX(MORTALITY!$A:$A)),"",A4+1) -> 3 | B5: =IF(A5="","",IFERROR(INDEX(MORTALITY!$B:$B,MATCH(A5,MORTALITY!$A:$A,0)),0)) -> 0.00338 | C5: =IF(A5="","",IFERROR(C4*(1-B4),0)) -> 9677571.2 | D5: =IF(A5="","",IFERROR(C5*B5,0)) -> 32710.191 | E5: =IF(A5="","",IFERROR((1/(1+Inputs!$B$23))^A5,0)) -> 0.92859941 | F5: =IF(A5="","",IFERROR(C5*E5,0)) -> 8986586.9 | G5: =IF(A5="","",IFERROR(D5*(1/(1+Inputs!$B$23))^(A5+1),0)) -> 29633.818 | H5: =IF(A5="","",IFERROR(IF(B5=1,F5,F5+H6),0)) -> 2.778727e+08 | I5: =IF(A5="","",IFERROR(IF(B5=1,G5,G5+I6),0)) -> 2209203.9 | J5: =IF(A5="","",IFERROR(H5/F5,0)) -> 30.920828 | K5: =IF(A5="","",IFERROR(I5/F5,0)) -> 0.24583347 | L5: =IF(A5="","",IFERROR(1000*I5/H5,0)) -> 7.9504169 | M5: =IF(A5="","",IFERROR(1000*I5/(H5-INDEX(H:H,MATCH(A5+Inputs!$B$8,$A:$A,0))),0)) -> 11.820881
A6: =IF(OR(A5="",A5>=MAX(MORTALITY!$A:$A)),"",A5+1) -> 4 | B6: =IF(A6="","",IFERROR(INDEX(MORTALITY!$B:$B,MATCH(A6,MORTALITY!$A:$A,0)),0)) -> 0.00299 | C6: =IF(A6="","",IFERROR(C5*(1-B5),0)) -> 9644861 | D6: =IF(A6="","",IFERROR(C6*B6,0)) -> 28838.134 | E6: =IF(A6="","",IFERROR((1/(1+Inputs!$B$23))^A6,0)) -> 0.90595064 | F6: =IF(A6="","",IFERROR(C6*E6,0)) -> 8737768 | G6: =IF(A6="","",IFERROR(D6*(1/(1+Inputs!$B$23))^(A6+1),0)) -> 25488.709 | H6: =IF(A6="","",IFERROR(IF(B6=1,F6,F6+H7),0)) -> 2.6888612e+08 | I6: =IF(A6="","",IFERROR(IF(B6=1,G6,G6+I7),0)) -> 2179570 | J6: =IF(A6="","",IFERROR(H6/F6,0)) -> 30.772861 | K6: =IF(A6="","",IFERROR(I6/F6,0)) -> 0.24944242 | L6: =IF(A6="","",IFERROR(1000*I6/H6,0)) -> 8.1059225 | M6: =IF(A6="","",IFERROR(1000*I6/(H6-INDEX(H:H,MATCH(A6+Inputs!$B$8,$A:$A,0))),0)) -> 11.98491
A7: =IF(OR(A6="",A6>=MAX(MORTALITY!$A:$A)),"",A6+1) -> 5 | B7: =IF(A7="","",IFERROR(INDEX(MORTALITY!$B:$B,MATCH(A7,MORTALITY!$A:$A,0)),0)) -> 0.00276 | C7: =IF(A7="","",IFERROR(C6*(1-B6),0)) -> 9616022.8 | D7: =IF(A7="","",IFERROR(C7*B7,0)) -> 26540.223 | E7: =IF(A7="","",IFERROR((1/(1+Inputs!$B$23))^A7,0)) -> 0.88385429 | F7: =IF(A7="","",IFERROR(C7*E7,0)) -> 8499163 | G7: =IF(A7="","",IFERROR(D7*(1/(1+Inputs!$B$23))^(A7+1),0)) -> 22885.551 | H7: =IF(A7="","",IFERROR(IF(B7=1,F7,F7+H8),0)) -> 2.6014835e+08 | I7: =IF(A7="","",IFERROR(IF(B7=1,G7,G7+I8),0)) -> 2154081.3 | J7: =IF(A7="","",IFERROR(H7/F7,0)) -> 30.608702 | K7: =IF(A7="","",IFERROR(I7/F7,0)) -> 0.25344629 | L7: =IF(A7="","",IFERROR(1000*I7/H7,0)) -> 8.2802037 | M7: =IF(A7="","",IFERROR(1000*I7/(H7-INDEX(H:H,MATCH(A7+Inputs!$B$8,$A:$A,0))),0)) -> 12.172322
A8: =IF(OR(A7="",A7>=MAX(MORTALITY!$A:$A)),"",A7+1) -> 6 | B8: =IF(A8="","",IFERROR(INDEX(MORTALITY!$B:$B,MATCH(A8,MORTALITY!$A:$A,0)),0)) -> 0.00261 | C8: =IF(A8="","",IFERROR(C7*(1-B7),0)) -> 9589482.6 | D8: =IF(A8="","",IFERROR(C8*B8,0)) -> 25028.55 | E8: =IF(A8="","",IFERROR((1/(1+Inputs!$B$23))^A8,0)) -> 0.86229687 | F8: =IF(A8="","",IFERROR(C8*E8,0)) -> 8268980.8 | G8: =IF(A8="","",IFERROR(D8*(1/(1+Inputs!$B$23))^(A8+1),0)) -> 21055.649 | H8: =IF(A8="","",IFERROR(IF(B8=1,F8,F8+H9),0)) -> 2.5164919e+08 | I8: =IF(A8="","",IFERROR(IF(B8=1,G8,G8+I9),0)) -> 2131195.8 | J8: =IF(A8="","",IFERROR(H8/F8,0)) -> 30.432915 | K8: =IF(A8="","",IFERROR(I8/F8,0)) -> 0.25773379 | L8: =IF(A8="","",IFERROR(1000*I8/H8,0)) -> 8.4689158 | M8: =IF(A8="","",IFERROR(1000*I8/(H8-INDEX(H:H,MATCH(A8+Inputs!$B$8,$A:$A,0))),0)) -> 12.376278
A9: =IF(OR(A8="",A8>=MAX(MORTALITY!$A:$A)),"",A8+1) -> 7 | B9: =IF(A9="","",IFERROR(INDEX(MORTALITY!$B:$B,MATCH(A9,MORTALITY!$A:$A,0)),0)) -> 0.00247 | C9: =IF(A9="","",IFERROR(C8*(1-B8),0)) -> 9564454.1 | D9: =IF(A9="","",IFERROR(C9*B9,0)) -> 23624.202 | E9: =IF(A9="","",IFERROR((1/(1+Inputs!$B$23))^A9,0)) -> 0.84126524 | F9: =IF(A9="","",IFERROR(C9*E9,0)) -> 8046242.7 | G9: =IF(A9="","",IFERROR(D9*(1/(1+Inputs!$B$23))^(A9+1),0)) -> 19389.482 | H9: =IF(A9="","",IFERROR(IF(B9=1,F9,F9+H10),0)) -> 2.4338021e+08 | I9: =IF(A9="","",IFERROR(IF(B9=1,G9,G9+I10),0)) -> 2110140.1 | J9: =IF(A9="","",IFERROR(H9/F9,0)) -> 30.247684 | K9: =IF(A9="","",IFERROR(I9/F9,0)) -> 0.26225161 | L9: =IF(A9="","",IFERROR(1000*I9/H9,0)) -> 8.6701387 | M9: =IF(A9="","",IFERROR(1000*I9/(H9-INDEX(H:H,MATCH(A9+Inputs!$B$8,$A:$A,0))),0)) -> 12.593566
A10: =IF(OR(A9="",A9>=MAX(MORTALITY!$A:$A)),"",A9+1) -> 8 | B10: =IF(A10="","",IFERROR(INDEX(MORTALITY!$B:$B,MATCH(A10,MORTALITY!$A:$A,0)),0)) -> 0.00231 | C10: =IF(A10="","",IFERROR(C9*(1-B9),0)) -> 9540829.9 | D10: =IF(A10="","",IFERROR(C10*B10,0)) -> 22039.317 | E10: =IF(A10="","",IFERROR((1/(1+Inputs!$B$23))^A10,0)) -> 0.82074657 | F10: =IF(A10="","",IFERROR(C10*E10,0)) -> 7830603.4 | G10: =IF(A10="","",IFERROR(D10*(1/(1+Inputs!$B$23))^(A10+1),0)) -> 17647.506 | H10: =IF(A10="","",IFERROR(IF(B10=1,F10,F10+H11),0)) -> 2.3533396e+08 | I10: =IF(A10="","",IFERROR(IF(B10=1,G10,G10+I11),0)) -> 2090750.6 | J10: =IF(A10="","",IFERROR(H10/F10,0)) -> 30.053107 | K10: =IF(A10="","",IFERROR(I10/F10,0)) -> 0.26699739 | L10: =IF(A10="","",IFERROR(1000*I10/H10,0)) -> 8.8841858 | M10: =IF(A10="","",IFERROR(1000*I10/(H10-INDEX(H:H,MATCH(A10+Inputs!$B$8,$A:$A,0))),0)) -> 12.824248
A11: =IF(OR(A10="",A10>=MAX(MORTALITY!$A:$A)),"",A10+1) -> 9 | B11: =IF(A11="","",IFERROR(INDEX(MORTALITY!$B:$B,MATCH(A11,MORTALITY!$A:$A,0)),0)) -> 0.00212 | C11: =IF(A11="","",IFERROR(C10*(1-B10),0)) -> 9518790.5 | D11: =IF(A11="","",IFERROR(C11*B11,0)) -> 20179.836 | E11: =IF(A11="","",IFERROR((1/(1+Inputs!$B$23))^A11,0)) -> 0.80072836 | F11: =IF(A11="","",IFERROR(C11*E11,0)) -> 7621965.6 | G11: =IF(A11="","",IFERROR(D11*(1/(1+Inputs!$B$23))^(A11+1),0)) -> 15764.456 | H11: =IF(A11="","",IFERROR(IF(B11=1,F11,F11+H12),0)) -> 2.2750336e+08 | I11: =IF(A11="","",IFERROR(IF(B11=1,G11,G11+I12),0)) -> 2073103.1 | J11: =IF(A11="","",IFERROR(H11/F11,0)) -> 29.848385 | K11: =IF(A11="","",IFERROR(I11/F11,0)) -> 0.27199062 | L11: =IF(A11="","",IFERROR(1000*I11/H11,0)) -> 9.1124067 | M11: =IF(A11="","",IFERROR(1000*I11/(H11-INDEX(H:H,MATCH(A11+Inputs!$B$8,$A:$A,0))),0)) -> 13.069852
A12: =IF(OR(A11="",A11>=MAX(MORTALITY!$A:$A)),"",A11+1) -> 10 | B12: =IF(A12="","",IFERROR(INDEX(MORTALITY!$B:$B,MATCH(A12,MORTALITY!$A:$A,0)),0)) -> 0.00197 | C12: =IF(A12="","",IFERROR(C11*(1-B11),0)) -> 9498610.7 | D12: =IF(A12="","",IFERROR(C12*B12,0)) -> 18712.263 | E12: =IF(A12="","",IFERROR((1/(1+Inputs!$B$23))^A12,0)) -> 0.7811984 | F12: =IF(A12="","",IFERROR(C12*E12,0)) -> 7420299.5 | G12: =IF(A12="","",IFERROR(D12*(1/(1+Inputs!$B$23))^(A12+1),0)) -> 14261.454 | H12: =IF(A12="","",IFERROR(IF(B12=1,F12,F12+H13),0)) -> 2.1988139e+08 | I12: =IF(A12="","",IFERROR(IF(B12=1,G12,G12+I13),0)) -> 2057338.7 | J12: =IF(A12="","",IFERROR(H12/F12,0)) -> 29.632415 | K12: =IF(A12="","",IFERROR(I12/F12,0)) -> 0.27725817 | L12: =IF(A12="","",IFERROR(1000*I12/H12,0)) -> 9.3565838 | M12: =IF(A12="","",IFERROR(1000*I12/(H12-INDEX(H:H,MATCH(A12+Inputs!$B$8,$A:$A,0))),0)) -> 13.332467
A13: =IF(OR(A12="",A12>=MAX(MORTALITY!$A:$A)),"",A12+1) -> 11 | B13: =IF(A13="","",IFERROR(INDEX(MORTALITY!$B:$B,MATCH(A13,MORTALITY!$A:$A,0)),0)) -> 0.00191 | C13: =IF(A13="","",IFERROR(C12*(1-B12),0)) -> 9479898.4 | D13: =IF(A13="","",IFERROR(C13*B13,0)) -> 18106.606 | E13: =IF(A13="","",IFERROR((1/(1+Inputs!$B$23))^A13,0)) -> 0.76214478 | F13: =IF(A13="","",IFERROR(C13*E13,0)) -> 7225055.1 | G13: =IF(A13="","",IFERROR(D13*(1/(1+Inputs!$B$23))^(A13+1),0)) -> 13463.273 | H13: =IF(A13="","",IFERROR(IF(B13=1,F13,F13+H14),0)) -> 2.1246109e+08 | I13: =IF(A13="","",IFERROR(IF(B13=1,G13,G13+I14),0)) -> 2043077.2 | J13: =IF(A13="","",IFERROR(H13/F13,0)) -> 29.406155 | K13: =IF(A13="","",IFERROR(I13/F13,0)) -> 0.2827767 | L13: =IF(A13="","",IFERROR(1000*I13/H13,0)) -> 9.6162417 | M13: =IF(A13="","",IFERROR(1000*I13/(H13-INDEX(H:H,MATCH(A13+Inputs!$B$8,$A:$A,0))),0)) -> 13.610925
A14: =IF(OR(A13="",A13>=MAX(MORTALITY!$A:$A)),"",A13+1) -> 12 | B14: =IF(A14="","",IFERROR(INDEX(MORTALITY!$B:$B,MATCH(A14,MORTALITY!$A:$A,0)),0)) -> 0.00192 | C14: =IF(A14="","",IFERROR(C13*(1-B13),0)) -> 9461791.8 | D14: =IF(A14="","",IFERROR(C14*B14,0)) -> 18166.64 | E14: =IF(A14="","",IFERROR((1/(1+Inputs!$B$23))^A14,0)) -> 0.74355589 | F14: =IF(A14="","",IFERROR(C14*E14,0)) -> 7035371 | G14: =IF(A14="","",IFERROR(D14*(1/(1+Inputs!$B$23))^(A14+1),0)) -> 13178.451 | H14: =IF(A14="","",IFERROR(IF(B14=1,F14,F14+H15),0)) -> 2.0523604e+08 | I14: =IF(A14="","",IFERROR(IF(B14=1,G14,G14+I15),0)) -> 2029614 | J14: =IF(A14="","",IFERROR(H14/F14,0)) -> 29.172028 | K14: =IF(A14="","",IFERROR(I14/F14,0)) -> 0.28848712 | L14: =IF(A14="","",IFERROR(1000*I14/H14,0)) -> 9.8891694 | M14: =IF(A14="","",IFERROR(1000*I14/(H14-INDEX(H:H,MATCH(A14+Inputs!$B$8,$A:$A,0))),0)) -> 13.901621
... A110: =IF(OR(A109="",A109>=MAX(MORTALITY!$A:$A)),"",A109+1) | B110: =IF(A110="","",IFERROR(INDEX(MORTALITY!$B:$B,MATCH(A110,MORTALITY!$A:$A,0)),0)) | C110: =IF(A110="","",IFERROR(C109*(1-B109),0)) | D110: =IF(A110="","",IFERROR(C110*B110,0)) | E110: =IF(A110="","",IFERROR((1/(1+Inputs!$B$23))^A110,0)) | F110: =IF(A110="","",IFERROR(C110*E110,0)) | G110: =IF(A110="","",IFERROR(D110*(1/(1+Inputs!$B$23))^(A110+1),0)) | H110: =IF(A110="","",IFERROR(IF(B110=1,F110,F110+H111),0)) | I110: =IF(A110="","",IFERROR(IF(B110=1,G110,G110+I111),0)) | J110: =IF(A110="","",IFERROR(H110/F110,0)) | K110: =IF(A110="","",IFERROR(I110/F110,0)) | L110: =IF(A110="","",IFERROR(1000*I110/H110,0)) | M110: =IF(A110="","",IFERROR(1000*I110/(H110-INDEX(H:H,MATCH(A110+Inputs!$B$8,$A:$A,0))),0))

Sheet CV_RATES
A1: Code | B1: Issue Age | C1: Duration | D1: Attained Age | E1: qx | F1: px | G1: Interest Rate | H1: Beta (NLP/1000) | I1: CV (BOY) | J1: CV (EOY) | K1: CV FACTOR
A2: =IF(D2>100,"",Inputs!$B$4) -> 34 | B2: =IF(D2>100,"",Inputs!$B$7) -> 16 | C2: 0 | D2: =IFERROR(IF(Inputs!$B$7+C2>=100,"",Inputs!$B$7+C2),"") -> 16 | E2: =IF(D2="","",INDEX(MORTALITY!$B:$B,MATCH(D2,MORTALITY!$A:$A,0))) -> 0.00219 | F2: =IF(D2="","",1-E2) -> 0.99781 | G2: =IF(D2="","",Inputs!$B$23) -> 0.025 | H2: =IF(D2="","",INDEX(Commutation!$L:$L,MATCH(Inputs!$B$7,Commutation!$A:$A,0))) -> 11.090171 | I2: 0 | J2: =IF(D2>99,"",IF(E2=1,1000,MIN(1000,MAX(0,(INDEX(Commutation!$K:$K,MATCH(D3,Commutation!$A:$A,0))-(INDEX(Commutation!$K:$K,MATCH(Inputs!$B$7,Commutation!$A:$A,0))/((INDEX(Commutation!$H:$H,MATCH(Inputs!$B$7,Commutation!$A:$A,0))-INDEX(Commutation!$H:$H,MATCH(Inputs!$B$8,Commutation!$A:$A,0)))/INDEX(Commutation!$F:$F,MATCH(Inputs!$B$7,Commutation!$A:$A,0))))*MAX(0,(INDEX(Commutation!$H:$H,MATCH(D3,Commutation!$A:$A,0))-INDEX(Commutation!$H:$H,MATCH(Inputs!$B$8,Commutation!$A:$A,0)))/INDEX(Commutation!$F:$F,MATCH(D3,Commutation!$A:$A,0))))*1000)))) -> 25.003668 | K2: =J2 -> 25.003668 | M2: =IF(A2="","",IF(E2=1,1000,IFERROR(((I2+IF(C2<=Inputs!$B$8,$H$2,0))*(1+G2)-E2*1000)/F2,0))) -> 9.1975681
A3: =IF(D3>100,"",Inputs!$B$4) -> 34 | B3: =IF(D3>100,"",Inputs!$B$7) -> 16 | C3: =IFERROR(IF(Inputs!$B$7+C2+1>=100,"",C2+1),"") -> 1 | D3: =IFERROR(IF(Inputs!$B$7+C3>=100,"",Inputs!$B$7+C3),"") -> 17 | E3: =IF(D3="","",INDEX(MORTALITY!$B:$B,MATCH(D3,MORTALITY!$A:$A,0))) -> 0.00225 | F3: =IF(D3="","",1-E3) -> 0.99775 | G3: =IF(D3="","",Inputs!$B$23) -> 0.025 | H3: =IF(D3="","",INDEX(Commutation!$L:$L,MATCH(Inputs!$B$7,Commutation!$A:$A,0))) -> 11.090171 | I3: =IF(D3="","",J2) -> 25.003668 | J3: =IF(D3>99,"",IF(E3=1,1000,MIN(1000,MAX(0,(INDEX(Commutation!$K:$K,MATCH(D4,Commutation!$A:$A,0))-(INDEX(Commutation!$K:$K,MATCH(Inputs!$B$7,Commutation!$A:$A,0))/((INDEX(Commutation!$H:$H,MATCH(Inputs!$B$7,Commutation!$A:$A,0))-INDEX(Commutation!$H:$H,MATCH(Inputs!$B$8,Commutation!$A:$A,0)))/INDEX(Commutation!$F:$F,MATCH(Inputs!$B$7,Commutation!$A:$A,0))))*MAX(0,(INDEX(Commutation!$H:$H,MATCH(D4,Commutation!$A:$A,0))-INDEX(Commutation!$H:$H,MATCH(Inputs!$B$8,Commutation!$A:$A,0)))/INDEX(Commutation!$F:$F,MATCH(D4,Commutation!$A:$A,0))))*1000)))) -> 50.63159 | K3: =J3 -> 50.63159 | M3: =IF(A3="","",IF(E3=1,1000,IFERROR(((I3+IF(C3<=Inputs!$B$8,$H$2,0))*(1+G3)-E3*1000)/F3,0))) -> 34.82454
A4: =IF(D4>100,"",Inputs!$B$4) -> 34 | B4: =IF(D4>100,"",Inputs!$B$7) -> 16 | C4: =IFERROR(IF(Inputs!$B$7+C3+1>=100,"",C3+1),"") -> 2 | D4: =IFERROR(IF(Inputs!$B$7+C4>=100,"",Inputs!$B$7+C4),"") -> 18 | E4: =IF(D4="","",INDEX(MORTALITY!$B:$B,MATCH(D4,MORTALITY!$A:$A,0))) -> 0.0023 | F4: =IF(D4="","",1-E4) -> 0.9977 | G4: =IF(D4="","",Inputs!$B$23) -> 0.025 | H4: =IF(D4="","",INDEX(Commutation!$L:$L,MATCH(Inputs!$B$7,Commutation!$A:$A,0))) -> 11.090171 | I4: =IF(D4="","",J3) -> 50.63159 | J4: =IF(D4>99,"",IF(E4=1,1000,MIN(1000,MAX(0,(INDEX(Commutation!$K:$K,MATCH(D5,Commutation!$A:$A,0))-(INDEX(Commutation!$K:$K,MATCH(Inputs!$B$7,Commutation!$A:$A,0))/((INDEX(Commutation!$H:$H,MATCH(Inputs!$B$7,Commutation!$A:$A,0))-INDEX(Commutation!$H:$H,MATCH(Inputs!$B$8,Commutation!$A:$A,0)))/INDEX(Commutation!$F:$F,MATCH(Inputs!$B$7,Commutation!$A:$A,0))))*MAX(0,(INDEX(Commutation!$H:$H,MATCH(D5,Commutation!$A:$A,0))-INDEX(Commutation!$H:$H,MATCH(Inputs!$B$8,Commutation!$A:$A,0)))/INDEX(Commutation!$F:$F,MATCH(D5,Commutation!$A:$A,0))))*1000)))) -> 76.91319 | K4: =IF(Inputs!$B$7+3-1>MAX(MORTALITY!$A:$A),"",IFERROR(J4,0)) -> 76.91319 | M4: =IF(A4="","",IF(E4=1,1000,IFERROR(((I4+IF(C4<=Inputs!$B$8,$H$2,0))*(1+G4)-E4*1000)/F4,0))) -> 61.105347
A5: =IF(D5>100,"",Inputs!$B$4) -> 34 | B5: =IF(D5>100,"",Inputs!$B$7) -> 16 | C5: =IFERROR(IF(Inputs!$B$7+C4+1>=100,"",C4+1),"") -> 3 | D5: =IFERROR(IF(Inputs!$B$7+C5>=100,"",Inputs!$B$7+C5),"") -> 19 | E5: =IF(D5="","",INDEX(MORTALITY!$B:$B,MATCH(D5,MORTALITY!$A:$A,0))) -> 0.00237 | F5: =IF(D5="","",1-E5) -> 0.99763 | G5: =IF(D5="","",Inputs!$B$23) -> 0.025 | H5: =IF(D5="","",INDEX(Commutation!$L:$L,MATCH(Inputs!$B$7,Commutation!$A:$A,0))) -> 11.090171 | I5: =IF(D5="","",J4) -> 76.91319 | J5: =IF(D5>99,"",IF(E5=1,1000,MIN(1000,MAX(0,(INDEX(Commutation!$K:$K,MATCH(D6,Commutation!$A:$A,0))-(INDEX(Commutation!$K:$K,MATCH(Inputs!$B$7,Commutation!$A:$A,0))/((INDEX(Commutation!$H:$H,MATCH(Inputs!$B$7,Commutation!$A:$A,0))-INDEX(Commutation!$H:$H,MATCH(Inputs!$B$8,Commutation!$A:$A,0)))/INDEX(Commutation!$F:$F,MATCH(Inputs!$B$7,Commutation!$A:$A,0))))*MAX(0,(INDEX(Commutation!$H:$H,MATCH(D6,Commutation!$A:$A,0))-INDEX(Commutation!$H:$H,MATCH(Inputs!$B$8,Commutation!$A:$A,0)))/INDEX(Commutation!$F:$F,MATCH(D6,Commutation!$A:$A,0))))*1000)))) -> 103.85106 | K5: =IF(Inputs!$B$7+4-1>MAX(MORTALITY!$A:$A),"",IFERROR(J5,0)) -> 103.85106 | M5: =IF(A5="","",IF(E5=1,1000,IFERROR(((I5+IF(C5<=Inputs!$B$8,$H$2,0))*(1+G5)-E5*1000)/F5,0))) -> 88.042105
A6: =IF(D6>100,"",Inputs!$B$4) -> 34 | B6: =IF(D6>100,"",Inputs!$B$7) -> 16 | C6: =IFERROR(IF(Inputs!$B$7+C5+1>=100,"",C5+1),"") -> 4 | D6: =IFERROR(IF(Inputs!$B$7+C6>=100,"",Inputs!$B$7+C6),"") -> 20 | E6: =IF(D6="","",INDEX(MORTALITY!$B:$B,MATCH(D6,MORTALITY!$A:$A,0))) -> 0.00243 | F6: =IF(D6="","",1-E6) -> 0.99757 | G6: =IF(D6="","",Inputs!$B$23) -> 0.025 | H6: =IF(D6="","",INDEX(Commutation!$L:$L,MATCH(Inputs!$B$7,Commutation!$A:$A,0))) -> 11.090171 | I6: =IF(D6="","",J5) -> 103.85106 | J6: =IF(D6>99,"",IF(E6=1,1000,MIN(1000,MAX(0,(INDEX(Commutation!$K:$K,MATCH(D7,Commutation!$A:$A,0))-(INDEX(Commutation!$K:$K,MATCH(Inputs!$B$7,Commutation!$A:$A,0))/((INDEX(Commutation!$H:$H,MATCH(Inputs!$B$7,Commutation!$A:$A,0))-INDEX(Commutation!$H:$H,MATCH(Inputs!$B$8,Commutation!$A:$A,0)))/INDEX(Commutation!$F:$F,MATCH(Inputs!$B$7,Commutation!$A:$A,0))))*MAX(0,(INDEX(Commutation!$H:$H,MATCH(D7,Commutation!$A:$A,0))-INDEX(Commutation!$H:$H,MATCH(Inputs!$B$8,Commutation!$A:$A,0)))/INDEX(Commutation!$F:$F,MATCH(D7,Commutation!$A:$A,0))))*1000)))) -> 131.47573 | K6: =IF(Inputs!$B$7+5-1>MAX(MORTALITY!$A:$A),"",IFERROR(J6,0)) -> 131.47573 | M6: =IF(A6="","",IF(E6=1,1000,IFERROR(((I6+IF(C6<=Inputs!$B$8,$H$2,0))*(1+G6)-E6*1000)/F6,0))) -> 115.66583
A7: =IF(D7>100,"",Inputs!$B$4) -> 34 | B7: =IF(D7>100,"",Inputs!$B$7) -> 16 | C7: =IFERROR(IF(Inputs!$B$7+C6+1>=100,"",C6+1),"") -> 5 | D7: =IFERROR(IF(Inputs!$B$7+C7>=100,"",Inputs!$B$7+C7),"") -> 21 | E7: =IF(D7="","",INDEX(MORTALITY!$B:$B,MATCH(D7,MORTALITY!$A:$A,0))) -> 0.00251 | F7: =IF(D7="","",1-E7) -> 0.99749 | G7: =IF(D7="","",Inputs!$B$23) -> 0.025 | H7: =IF(D7="","",INDEX(Commutation!$L:$L,MATCH(Inputs!$B$7,Commutation!$A:$A,0))) -> 11.090171 | I7: =IF(D7="","",J6) -> 131.47573 | J7: =IF(D7>99,"",IF(E7=1,1000,MIN(1000,MAX(0,(INDEX(Commutation!$K:$K,MATCH(D8,Commutation!$A:$A,0))-(INDEX(Commutation!$K:$K,MATCH(Inputs!$B$7,Commutation!$A:$A,0))/((INDEX(Commutation!$H:$H,MATCH(Inputs!$B$7,Commutation!$A:$A,0))-INDEX(Commutation!$H:$H,MATCH(Inputs!$B$8,Commutation!$A:$A,0)))/INDEX(Commutation!$F:$F,MATCH(Inputs!$B$7,Commutation!$A:$A,0))))*MAX(0,(INDEX(Commutation!$H:$H,MATCH(D8,Commutation!$A:$A,0))-INDEX(Commutation!$H:$H,MATCH(Inputs!$B$8,Commutation!$A:$A,0)))/INDEX(Commutation!$F:$F,MATCH(D8,Commutation!$A:$A,0))))*1000)))) -> 159.79261 | K7: =IF(Inputs!$B$7+6-1>MAX(MORTALITY!$A:$A),"",IFERROR(J7,0)) -> 159.79261 | M7: =IF(A7="","",IF(E7=1,1000,IFERROR(((I7+IF(C7<=Inputs!$B$8,$H$2,0))*(1+G7)-E7*1000)/F7,0))) -> 143.98144
A8: =IF(D8>100,"",Inputs!$B$4) -> 34 | B8: =IF(D8>100,"",Inputs!$B$7) -> 16 | C8: =IFERROR(IF(Inputs!$B$7+C7+1>=100,"",C7+1),"") -> 6 | D8: =IFERROR(IF(Inputs!$B$7+C8>=100,"",Inputs!$B$7+C8),"") -> 22 | E8: =IF(D8="","",INDEX(MORTALITY!$B:$B,MATCH(D8,MORTALITY!$A:$A,0))) -> 0.00259 | F8: =IF(D8="","",1-E8) -> 0.99741 | G8: =IF(D8="","",Inputs!$B$23) -> 0.025 | H8: =IF(D8="","",INDEX(Commutation!$L:$L,MATCH(Inputs!$B$7,Commutation!$A:$A,0))) -> 11.090171 | I8: =IF(D8="","",J7) -> 159.79261 | J8: =IF(D8>99,"",IF(E8=1,1000,MIN(1000,MAX(0,(INDEX(Commutation!$K:$K,MATCH(D9,Commutation!$A:$A,0))-(INDEX(Commutation!$K:$K,MATCH(Inputs!$B$7,Commutation!$A:$A,0))/((INDEX(Commutation!$H:$H,MATCH(Inputs!$B$7,Commutation!$A:$A,0))-INDEX(Commutation!$H:$H,MATCH(Inputs!$B$8,Commutation!$A:$A,0)))/INDEX(Commutation!$F:$F,MATCH(Inputs!$B$7,Commutation!$A:$A,0))))*MAX(0,(INDEX(Commutation!$H:$H,MATCH(D9,Commutation!$A:$A,0))-INDEX(Commutation!$H:$H,MATCH(Inputs!$B$8,Commutation!$A:$A,0)))/INDEX(Commutation!$F:$F,MATCH(D9,Commutation!$A:$A,0))))*1000)))) -> 188.82539 | K8: =IF(Inputs!$B$7+7-1>MAX(MORTALITY!$A:$A),"",IFERROR(J8,0)) -> 188.82539 | M8: =IF(A8="","",IF(E8=1,1000,IFERROR(((I8+IF(C8<=Inputs!$B$8,$H$2,0))*(1+G8)-E8*1000)/F8,0))) -> 173.01295
A9: =IF(D9>100,"",Inputs!$B$4) -> 34 | B9: =IF(D9>100,"",Inputs!$B$7) -> 16 | C9: =IFERROR(IF(Inputs!$B$7+C8+1>=100,"",C8+1),"") -> 7 | D9: =IFERROR(IF(Inputs!$B$7+C9>=100,"",Inputs!$B$7+C9),"") -> 23 | E9: =IF(D9="","",INDEX(MORTALITY!$B:$B,MATCH(D9,MORTALITY!$A:$A,0))) -> 0.00268 | F9: =IF(D9="","",1-E9) -> 0.99732 | G9: =IF(D9="","",Inputs!$B$23) -> 0.025 | H9: =IF(D9="","",INDEX(Commutation!$L:$L,MATCH(Inputs!$B$7,Commutation!$A:$A,0))) -> 11.090171 | I9: =IF(D9="","",J8) -> 188.82539 | J9: =IF(D9>99,"",IF(E9=1,1000,MIN(1000,MAX(0,(INDEX(Commutation!$K:$K,MATCH(D10,Commutation!$A:$A,0))-(INDEX(Commutation!$K:$K,MATCH(Inputs!$B$7,Commutation!$A:$A,0))/((INDEX(Commutation!$H:$H,MATCH(Inputs!$B$7,Commutation!$A:$A,0))-INDEX(Commutation!$H:$H,MATCH(Inputs!$B$8,Commutation!$A:$A,0)))/INDEX(Commutation!$F:$F,MATCH(Inputs!$B$7,Commutation!$A:$A,0))))*MAX(0,(INDEX(Commutation!$H:$H,MATCH(D10,Commutation!$A:$A,0))-INDEX(Commutation!$H:$H,MATCH(Inputs!$B$8,Commutation!$A:$A,0)))/INDEX(Commutation!$F:$F,MATCH(D10,Commutation!$A:$A,0))))*1000)))) -> 218.59076 | K9: =IF(Inputs!$B$7+8-1>MAX(MORTALITY!$A:$A),"",IFERROR(J9,0)) -> 218.59076 | M9: =IF(A9="","",IF(E9=1,1000,IFERROR(((I9+IF(C9<=Inputs!$B$8,$H$2,0))*(1+G9)-E9*1000)/F9,0))) -> 202.77689
A10: =IF(D10>100,"",Inputs!$B$4) -> 34 | B10: =IF(D10>100,"",Inputs!$B$7) -> 16 | C10: =IFERROR(IF(Inputs!$B$7+C9+1>=100,"",C9+1),"") -> 8 | D10: =IFERROR(IF(Inputs!$B$7+C10>=100,"",Inputs!$B$7+C10),"") -> 24 | E10: =IF(D10="","",INDEX(MORTALITY!$B:$B,MATCH(D10,MORTALITY!$A:$A,0))) -> 0.00277 | F10: =IF(D10="","",1-E10) -> 0.99723 | G10: =IF(D10="","",Inputs!$B$23) -> 0.025 | H10: =IF(D10="","",INDEX(Commutation!$L:$L,MATCH(Inputs!$B$7,Commutation!$A:$A,0))) -> 11.090171 | I10: =IF(D10="","",J9) -> 218.59076 | J10: =IF(D10>99,"",IF(E10=1,1000,MIN(1000,MAX(0,(INDEX(Commutation!$K:$K,MATCH(D11,Commutation!$A:$A,0))-(INDEX(Commutation!$K:$K,MATCH(Inputs!$B$7,Commutation!$A:$A,0))/((INDEX(Commutation!$H:$H,MATCH(Inputs!$B$7,Commutation!$A:$A,0))-INDEX(Commutation!$H:$H,MATCH(Inputs!$B$8,Commutation!$A:$A,0)))/INDEX(Commutation!$F:$F,MATCH(Inputs!$B$7,Commutation!$A:$A,0))))*MAX(0,(INDEX(Commutation!$H:$H,MATCH(D11,Commutation!$A:$A,0))-INDEX(Commutation!$H:$H,MATCH(Inputs!$B$8,Commutation!$A:$A,0)))/INDEX(Commutation!$F:$F,MATCH(D11,Commutation!$A:$A,0))))*1000)))) -> 249.11449 | K10: =IF(Inputs!$B$7+9-1>MAX(MORTALITY!$A:$A),"",IFERROR(J10,0)) -> 249.11449 | M10: =IF(A10="","",IF(E10=1,1000,IFERROR(((I10+IF(C10<=Inputs!$B$8,$H$2,0))*(1+G10)-E10*1000)/F10,0))) -> 233.29919
A11: =IF(D11>100,"",Inputs!$B$4) -> 34 | B11: =IF(D11>100,"",Inputs!$B$7) -> 16 | C11: =IFERROR(IF(Inputs!$B$7+C10+1>=100,"",C10+1),"") -> 9 | D11: =IFERROR(IF(Inputs!$B$7+C11>=100,"",Inputs!$B$7+C11),"") -> 25 | E11: =IF(D11="","",INDEX(MORTALITY!$B:$B,MATCH(D11,MORTALITY!$A:$A,0))) -> 0.00288 | F11: =IF(D11="","",1-E11) -> 0.99712 | G11: =IF(D11="","",Inputs!$B$23) -> 0.025 | H11: =IF(D11="","",INDEX(Commutation!$L:$L,MATCH(Inputs!$B$7,Commutation!$A:$A,0))) -> 11.090171 | I11: =IF(D11="","",J10) -> 249.11449 | J11: =IF(D11>99,"",IF(E11=1,1000,MIN(1000,MAX(0,(INDEX(Commutation!$K:$K,MATCH(D12,Commutation!$A:$A,0))-(INDEX(Commutation!$K:$K,MATCH(Inputs!$B$7,Commutation!$A:$A,0))/((INDEX(Commutation!$H:$H,MATCH(Inputs!$B$7,Commutation!$A:$A,0))-INDEX(Commutation!$H:$H,MATCH(Inputs!$B$8,Commutation!$A:$A,0)))/INDEX(Commutation!$F:$F,MATCH(Inputs!$B$7,Commutation!$A:$A,0))))*MAX(0,(INDEX(Commutation!$H:$H,MATCH(D12,Commutation!$A:$A,0))-INDEX(Commutation!$H:$H,MATCH(Inputs!$B$8,Commutation!$A:$A,0)))/INDEX(Commutation!$F:$F,MATCH(D12,Commutation!$A:$A,0))))*1000)))) -> 280.40884 | K11: =IF(Inputs!$B$7+10-1>MAX(MORTALITY!$A:$A),"",IFERROR(J11,0)) -> 280.40884 | M11: =IF(A11="","",IF(E11=1,1000,IFERROR(((I11+IF(C11<=Inputs!$B$8,$H$2,0))*(1+G11)-E11*1000)/F11,0))) -> 264.5918
A12: =IF(D12>100,"",Inputs!$B$4) -> 34 | B12: =IF(D12>100,"",Inputs!$B$7) -> 16 | C12: =IFERROR(IF(Inputs!$B$7+C11+1>=100,"",C11+1),"") -> 10 | D12: =IFERROR(IF(Inputs!$B$7+C12>=100,"",Inputs!$B$7+C12),"") -> 26 | E12: =IF(D12="","",INDEX(MORTALITY!$B:$B,MATCH(D12,MORTALITY!$A:$A,0))) -> 0.00299 | F12: =IF(D12="","",1-E12) -> 0.99701 | G12: =IF(D12="","",Inputs!$B$23) -> 0.025 | H12: =IF(D12="","",INDEX(Commutation!$L:$L,MATCH(Inputs!$B$7,Commutation!$A:$A,0))) -> 11.090171 | I12: =IF(D12="","",J11) -> 280.40884 | J12: =IF(D12>99,"",IF(E12=1,1000,MIN(1000,MAX(0,(INDEX(Commutation!$K:$K,MATCH(D13,Commutation!$A:$A,0))-(INDEX(Commutation!$K:$K,MATCH(Inputs!$B$7,Commutation!$A:$A,0))/((INDEX(Commutation!$H:$H,MATCH(Inputs!$B$7,Commutation!$A:$A,0))-INDEX(Commutation!$H:$H,MATCH(Inputs!$B$8,Commutation!$A:$A,0)))/INDEX(Commutation!$F:$F,MATCH(Inputs!$B$7,Commutation!$A:$A,0))))*MAX(0,(INDEX(Commutation!$H:$H,MATCH(D13,Commutation!$A:$A,0))-INDEX(Commutation!$H:$H,MATCH(Inputs!$B$8,Commutation!$A:$A,0)))/INDEX(Commutation!$F:$F,MATCH(D13,Commutation!$A:$A,0))))*1000)))) -> 312.50235 | K12: =IF(Inputs!$B$7+11-1>MAX(MORTALITY!$A:$A),"",IFERROR(J12,0)) -> 312.50235 | M12: =IF(A12="","",IF(E12=1,1000,IFERROR(((I12+IF(C12<=Inputs!$B$8,$H$2,0))*(1+G12)-E12*1000)/F12,0))) -> 296.68357
A13: =IF(D13>100,"",Inputs!$B$4) -> 34 | B13: =IF(D13>100,"",Inputs!$B$7) -> 16 | C13: =IFERROR(IF(Inputs!$B$7+C12+1>=100,"",C12+1),"") -> 11 | D13: =IFERROR(IF(Inputs!$B$7+C13>=100,"",Inputs!$B$7+C13),"") -> 27 | E13: =IF(D13="","",INDEX(MORTALITY!$B:$B,MATCH(D13,MORTALITY!$A:$A,0))) -> 0.00311 | F13: =IF(D13="","",1-E13) -> 0.99689 | G13: =IF(D13="","",Inputs!$B$23) -> 0.025 | H13: =IF(D13="","",INDEX(Commutation!$L:$L,MATCH(Inputs!$B$7,Commutation!$A:$A,0))) -> 11.090171 | I13: =IF(D13="","",J12) -> 312.50235 | J13: =IF(D13>99,"",IF(E13=1,1000,MIN(1000,MAX(0,(INDEX(Commutation!$K:$K,MATCH(D14,Commutation!$A:$A,0))-(INDEX(Commutation!$K:$K,MATCH(Inputs!$B$7,Commutation!$A:$A,0))/((INDEX(Commutation!$H:$H,MATCH(Inputs!$B$7,Commutation!$A:$A,0))-INDEX(Commutation!$H:$H,MATCH(Inputs!$B$8,Commutation!$A:$A,0)))/INDEX(Commutation!$F:$F,MATCH(Inputs!$B$7,Commutation!$A:$A,0))))*MAX(0,(INDEX(Commutation!$H:$H,MATCH(D14,Commutation!$A:$A,0))-INDEX(Commutation!$H:$H,MATCH(Inputs!$B$8,Commutation!$A:$A,0)))/INDEX(Commutation!$F:$F,MATCH(D14,Commutation!$A:$A,0))))*1000)))) -> 345.41807 | K13: =IF(Inputs!$B$7+12-1>MAX(MORTALITY!$A:$A),"",IFERROR(J13,0)) -> 345.41807 | M13: =IF(A13="","",IF(E13=1,1000,IFERROR(((I13+IF(C13<=Inputs!$B$8,$H$2,0))*(1+G13)-E13*1000)/F13,0))) -> 329.59738
A14: =IF(D14>100,"",Inputs!$B$4) -> 34 | B14: =IF(D14>100,"",Inputs!$B$7) -> 16 | C14: =IFERROR(IF(Inputs!$B$7+C13+1>=100,"",C13+1),"") -> 12 | D14: =IFERROR(IF(Inputs!$B$7+C14>=100,"",Inputs!$B$7+C14),"") -> 28 | E14: =IF(D14="","",INDEX(MORTALITY!$B:$B,MATCH(D14,MORTALITY!$A:$A,0))) -> 0.00325 | F14: =IF(D14="","",1-E14) -> 0.99675 | G14: =IF(D14="","",Inputs!$B$23) -> 0.025 | H14: =IF(D14="","",INDEX(Commutation!$L:$L,MATCH(Inputs!$B$7,Commutation!$A:$A,0))) -> 11.090171 | I14: =IF(D14="","",J13) -> 345.41807 | J14: =IF(D14>99,"",IF(E14=1,1000,MIN(1000,MAX(0,(INDEX(Commutation!$K:$K,MATCH(D15,Commutation!$A:$A,0))-(INDEX(Commutation!$K:$K,MATCH(Inputs!$B$7,Commutation!$A:$A,0))/((INDEX(Commutation!$H:$H,MATCH(Inputs!$B$7,Commutation!$A:$A,0))-INDEX(Commutation!$H:$H,MATCH(Inputs!$B$8,Commutation!$A:$A,0)))/INDEX(Commutation!$F:$F,MATCH(Inputs!$B$7,Commutation!$A:$A,0))))*MAX(0,(INDEX(Commutation!$H:$H,MATCH(D15,Commutation!$A:$A,0))-INDEX(Commutation!$H:$H,MATCH(Inputs!$B$8,Commutation!$A:$A,0)))/INDEX(Commutation!$F:$F,MATCH(D15,Commutation!$A:$A,0))))*1000)))) -> 379.17475 | K14: =IF(Inputs!$B$7+13-1>MAX(MORTALITY!$A:$A),"",IFERROR(J14,0)) -> 379.17475 | M14: =IF(A14="","",IF(E14=1,1000,IFERROR(((I14+IF(C14<=Inputs!$B$8,$H$2,0))*(1+G14)-E14*1000)/F14,0))) -> 363.35184
A15: =IF(D15>100,"",Inputs!$B$4) -> 34 | B15: =IF(D15>100,"",Inputs!$B$7) -> 16 | C15: =IFERROR(IF(Inputs!$B$7+C14+1>=100,"",C14+1),"") -> 13 | D15: =IFERROR(IF(Inputs!$B$7+C15>=100,"",Inputs!$B$7+C15),"") -> 29 | E15: =IF(D15="","",INDEX(MORTALITY!$B:$B,MATCH(D15,MORTALITY!$A:$A,0))) -> 0.0034 | F15: =IF(D15="","",1-E15) -> 0.9966 | G15: =IF(D15="","",Inputs!$B$23) -> 0.025 | H15: =IF(D15="","",INDEX(Commutation!$L:$L,MATCH(Inputs!$B$7,Commutation!$A:$A,0))) -> 11.090171 | I15: =IF(D15="","",J14) -> 379.17475 | J15: =IF(D15>99,"",IF(E15=1,1000,MIN(1000,MAX(0,(INDEX(Commutation!$K:$K,MATCH(D16,Commutation!$A:$A,0))-(INDEX(Commutation!$K:$K,MATCH(Inputs!$B$7,Commutation!$A:$A,0))/((INDEX(Commutation!$H:$H,MATCH(Inputs!$B$7,Commutation!$A:$A,0))-INDEX(Commutation!$H:$H,MATCH(Inputs!$B$8,Commutation!$A:$A,0)))/INDEX(Commutation!$F:$F,MATCH(Inputs!$B$7,Commutation!$A:$A,0))))*MAX(0,(INDEX(Commutation!$H:$H,MATCH(D16,Commutation!$A:$A,0))-INDEX(Commutation!$H:$H,MATCH(Inputs!$B$8,Commutation!$A:$A,0)))/INDEX(Commutation!$F:$F,MATCH(D16,Commutation!$A:$A,0))))*1000)))) -> 413.79994 | K15: =IF(Inputs!$B$7+14-1>MAX(MORTALITY!$A:$A),"",IFERROR(J15,0)) -> 413.79994 | M15: =IF(A15="","",IF(E15=1,1000,IFERROR(((I15+IF(C15<=Inputs!$B$8,$H$2,0))*(1+G15)-E15*1000)/F15,0))) -> 397.97465
A16: =IF(D16>100,"",Inputs!$B$4) -> 34 | B16: =IF(D16>100,"",Inputs!$B$7) -> 16 | C16: =IFERROR(IF(Inputs!$B$7+C15+1>=100,"",C15+1),"") -> 14 | D16: =IFERROR(IF(Inputs!$B$7+C16>=100,"",Inputs!$B$7+C16),"") -> 30 | E16: =IF(D16="","",INDEX(MORTALITY!$B:$B,MATCH(D16,MORTALITY!$A:$A,0))) -> 0.00356 | F16: =IF(D16="","",1-E16) -> 0.99644 | G16: =IF(D16="","",Inputs!$B$23) -> 0.025 | H16: =IF(D16="","",INDEX(Commutation!$L:$L,MATCH(Inputs!$B$7,Commutation!$A:$A,0))) -> 11.090171 | I16: =IF(D16="","",J15) -> 413.79994 | J16: =IF(D16>99,"",IF(E16=1,1000,MIN(1000,MAX(0,(INDEX(Commutation!$K:$K,MATCH(D17,Commutation!$A:$A,0))-(INDEX(Commutation!$K:$K,MATCH(Inputs!$B$7,Commutation!$A:$A,0))/((INDEX(Commutation!$H:$H,MATCH(Inputs!$B$7,Commutation!$A:$A,0))-INDEX(Commutation!$H:$H,MATCH(Inputs!$B$8,Commutation!$A:$A,0)))/INDEX(Commutation!$F:$F,MATCH(Inputs!$B$7,Commutation!$A:$A,0))))*MAX(0,(INDEX(Commutation!$H:$H,MATCH(D17,Commutation!$A:$A,0))-INDEX(Commutation!$H:$H,MATCH(Inputs!$B$8,Commutation!$A:$A,0)))/INDEX(Commutation!$F:$F,MATCH(D17,Commutation!$A:$A,0))))*1000)))) -> 422.08757 | K16: =IF(Inputs!$B$7+15-1>MAX(MORTALITY!$A:$A),"",IFERROR(J16,0)) -> 422.08757 | M16: =IF(A16="","",IF(E16=1,1000,IFERROR(((I16+IF(C16<=Inputs!$B$8,$H$2,0))*(1+G16)-E16*1000)/F16,0))) -> 433.49561
A17: =IF(D17>100,"",Inputs!$B$4) -> 34 | B17: =IF(D17>100,"",Inputs!$B$7) -> 16 | C17: =IFERROR(IF(Inputs!$B$7+C16+1>=100,"",C16+1),"") -> 15 | D17: =IFERROR(IF(Inputs!$B$7+C17>=100,"",Inputs!$B$7+C17),"") -> 31 | E17: =IF(D17="","",INDEX(MORTALITY!$B:$B,MATCH(D17,MORTALITY!$A:$A,0))) -> 0.00373 | F17: =IF(D17="","",1-E17) -> 0.99627 | G17: =IF(D17="","",Inputs!$B$23) -> 0.025 | H17: =IF(D17="","",INDEX(Commutation!$L:$L,MATCH(Inputs!$B$7,Commutation!$A:$A,0))) -> 11.090171 | I17: =IF(D17="","",J16) -> 422.08757 | J17: =IF(D17>99,"",IF(E17=1,1000,MIN(1000,MAX(0,(INDEX(Commutation!$K:$K,MATCH(D18,Commutation!$A:$A,0))-(INDEX(Commutation!$K:$K,MATCH(Inputs!$B$7,Commutation!$A:$A,0))/((INDEX(Commutation!$H:$H,MATCH(Inputs!$B$7,Commutation!$A:$A,0))-INDEX(Commutation!$H:$H,MATCH(Inputs!$B$8,Commutation!$A:$A,0)))/INDEX(Commutation!$F:$F,MATCH(Inputs!$B$7,Commutation!$A:$A,0))))*MAX(0,(INDEX(Commutation!$H:$H,MATCH(D18,Commutation!$A:$A,0))-INDEX(Commutation!$H:$H,MATCH(Inputs!$B$8,Commutation!$A:$A,0)))/INDEX(Commutation!$F:$F,MATCH(D18,Commutation!$A:$A,0))))*1000)))) -> 430.51559 | K17: =IF(Inputs!$B$7+16-1>MAX(MORTALITY!$A:$A),"",IFERROR(J17,0)) -> 430.51559 | M17: =IF(A17="","",IF(E17=1,1000,IFERROR(((I17+IF(C17<=Inputs!$B$8,$H$2,0))*(1+G17)-E17*1000)/F17,0))) -> 441.92557
A18: =IF(D18>100,"",Inputs!$B$4) -> 34 | B18: =IF(D18>100,"",Inputs!$B$7) -> 16 | C18: =IFERROR(IF(Inputs!$B$7+C17+1>=100,"",C17+1),"") -> 16 | D18: =IFERROR(IF(Inputs!$B$7+C18>=100,"",Inputs!$B$7+C18),"") -> 32 | E18: =IF(D18="","",INDEX(MORTALITY!$B:$B,MATCH(D18,MORTALITY!$A:$A,0))) -> 0.00392 | F18: =IF(D18="","",1-E18) -> 0.99608 | G18: =IF(D18="","",Inputs!$B$23) -> 0.025 | H18: =IF(D18="","",INDEX(Commutation!$L:$L,MATCH(Inputs!$B$7,Commutation!$A:$A,0))) -> 11.090171 | I18: =IF(D18="","",J17) -> 430.51559 | J18: =IF(D18>99,"",IF(E18=1,1000,MIN(1000,MAX(0,(INDEX(Commutation!$K:$K,MATCH(D19,Commutation!$A:$A,0))-(INDEX(Commutation!$K:$K,MATCH(Inputs!$B$7,Commutation!$A:$A,0))/((INDEX(Commutation!$H:$H,MATCH(Inputs!$B$7,Commutation!$A:$A,0))-INDEX(Commutation!$H:$H,MATCH(Inputs!$B$8,Commutation!$A:$A,0)))/INDEX(Commutation!$F:$F,MATCH(Inputs!$B$7,Commutation!$A:$A,0))))*MAX(0,(INDEX(Commutation!$H:$H,MATCH(D19,Commutation!$A:$A,0))-INDEX(Commutation!$H:$H,MATCH(Inputs!$B$8,Commutation!$A:$A,0)))/INDEX(Commutation!$F:$F,MATCH(D19,Commutation!$A:$A,0))))*1000)))) -> 439.07967 | K18: =IF(Inputs!$B$7+17-1>MAX(MORTALITY!$A:$A),"",IFERROR(J18,0)) -> 439.07967 | M18: =IF(A18="","",IF(E18=1,1000,IFERROR(((I18+IF(C18<=Inputs!$B$8,$H$2,0))*(1+G18)-E18*1000)/F18,0))) -> 450.49183
A19: =IF(D19>100,"",Inputs!$B$4) -> 34 | B19: =IF(D19>100,"",Inputs!$B$7) -> 16 | C19: =IFERROR(IF(Inputs!$B$7+C18+1>=100,"",C18+1),"") -> 17 | D19: =IFERROR(IF(Inputs!$B$7+C19>=100,"",Inputs!$B$7+C19),"") -> 33 | E19: =IF(D19="","",INDEX(MORTALITY!$B:$B,MATCH(D19,MORTALITY!$A:$A,0))) -> 0.00412 | F19: =IF(D19="","",1-E19) -> 0.99588 | G19: =IF(D19="","",Inputs!$B$23) -> 0.025 | H19: =IF(D19="","",INDEX(Commutation!$L:$L,MATCH(Inputs!$B$7,Commutation!$A:$A,0))) -> 11.090171 | I19: =IF(D19="","",J18) -> 439.07967 | J19: =IF(D19>99,"",IF(E19=1,1000,MIN(1000,MAX(0,(INDEX(Commutation!$K:$K,MATCH(D20,Commutation!$A:$A,0))-(INDEX(Commutation!$K:$K,MATCH(Inputs!$B$7,Commutation!$A:$A,0))/((INDEX(Commutation!$H:$H,MATCH(Inputs!$B$7,Commutation!$A:$A,0))-INDEX(Commutation!$H:$H,MATCH(Inputs!$B$8,Commutation!$A:$A,0)))/INDEX(Commutation!$F:$F,MATCH(Inputs!$B$7,Commutation!$A:$A,0))))*MAX(0,(INDEX(Commutation!$H:$H,MATCH(D20,Commutation!$A:$A,0))-INDEX(Commutation!$H:$H,MATCH(Inputs!$B$8,Commutation!$A:$A,0)))/INDEX(Commutation!$F:$F,MATCH(D20,Commutation!$A:$A,0))))*1000)))) -> 447.78152 | K19: =IF(Inputs!$B$7+18-1>MAX(MORTALITY!$A:$A),"",IFERROR(J19,0)) -> 447.78152 | M19: =IF(A19="","",IF(E19=1,1000,IFERROR(((I19+IF(C19<=Inputs!$B$8,$H$2,0))*(1+G19)-E19*1000)/F19,0))) -> 459.19597
A20: =IF(D20>100,"",Inputs!$B$4) -> 34 | B20: =IF(D20>100,"",Inputs!$B$7) -> 16 | C20: =IFERROR(IF(Inputs!$B$7+C19+1>=100,"",C19+1),"") -> 18 | D20: =IFERROR(IF(Inputs!$B$7+C20>=100,"",Inputs!$B$7+C20),"") -> 34 | E20: =IF(D20="","",INDEX(MORTALITY!$B:$B,MATCH(D20,MORTALITY!$A:$A,0))) -> 0.00435 | F20: =IF(D20="","",1-E20) -> 0.99565 | G20: =IF(D20="","",Inputs!$B$23) -> 0.025 | H20: =IF(D20="","",INDEX(Commutation!$L:$L,MATCH(Inputs!$B$7,Commutation!$A:$A,0))) -> 11.090171 | I20: =IF(D20="","",J19) -> 447.78152 | J20: =IF(D20>99,"",IF(E20=1,1000,MIN(1000,MAX(0,(INDEX(Commutation!$K:$K,MATCH(D21,Commutation!$A:$A,0))-(INDEX(Commutation!$K:$K,MATCH(Inputs!$B$7,Commutation!$A:$A,0))/((INDEX(Commutation!$H:$H,MATCH(Inputs!$B$7,Commutation!$A:$A,0))-INDEX(Commutation!$H:$H,MATCH(Inputs!$B$8,Commutation!$A:$A,0)))/INDEX(Commutation!$F:$F,MATCH(Inputs!$B$7,Commutation!$A:$A,0))))*MAX(0,(INDEX(Commutation!$H:$H,MATCH(D21,Commutation!$A:$A,0))-INDEX(Commutation!$H:$H,MATCH(Inputs!$B$8,Commutation!$A:$A,0)))/INDEX(Commutation!$F:$F,MATCH(D21,Commutation!$A:$A,0))))*1000)))) -> 456.61232 | K20: =IF(Inputs!$B$7+19-1>MAX(MORTALITY!$A:$A),"",IFERROR(J20,0)) -> 456.61232 | M20: =IF(A20="","",IF(E20=1,1000,IFERROR(((I20+IF(C20<=Inputs!$B$8,$H$2,0))*(1+G20)-E20*1000)/F20,0))) -> 468.02941
A21: =IF(D21>100,"",Inputs!$B$4) -> 34 | B21: =IF(D21>100,"",Inputs!$B$7) -> 16 | C21: =IFERROR(IF(Inputs!$B$7+C20+1>=100,"",C20+1),"") -> 19 | D21: =IFERROR(IF(Inputs!$B$7+C21>=100,"",Inputs!$B$7+C21),"") -> 35 | E21: =IF(D21="","",INDEX(MORTALITY!$B:$B,MATCH(D21,MORTALITY!$A:$A,0))) -> 0.00459 | F21: =IF(D21="","",1-E21) -> 0.99541 | G21: =IF(D21="","",Inputs!$B$23) -> 0.025 | H21: =IF(D21="","",INDEX(Commutation!$L:$L,MATCH(Inputs!$B$7,Commutation!$A:$A,0))) -> 11.090171 | I21: =IF(D21="","",J20) -> 456.61232 | J21: =IF(D21>99,"",IF(E21=1,1000,MIN(1000,MAX(0,(INDEX(Commutation!$K:$K,MATCH(D22,Commutation!$A:$A,0))-(INDEX(Commutation!$K:$K,MATCH(Inputs!$B$7,Commutation!$A:$A,0))/((INDEX(Commutation!$H:$H,MATCH(Inputs!$B$7,Commutation!$A:$A,0))-INDEX(Commutation!$H:$H,MATCH(Inputs!$B$8,Commutation!$A:$A,0)))/INDEX(Commutation!$F:$F,MATCH(Inputs!$B$7,Commutation!$A:$A,0))))*MAX(0,(INDEX(Commutation!$H:$H,MATCH(D22,Commutation!$A:$A,0))-INDEX(Commutation!$H:$H,MATCH(Inputs!$B$8,Commutation!$A:$A,0)))/INDEX(Commutation!$F:$F,MATCH(D22,Commutation!$A:$A,0))))*1000)))) -> 465.57462 | K21: =IF(Inputs!$B$7+20-1>MAX(MORTALITY!$A:$A),"",IFERROR(J21,0)) -> 465.57462 | M21: =IF(A21="","",IF(E21=1,1000,IFERROR(((I21+IF(C21<=Inputs!$B$8,$H$2,0))*(1+G21)-E21*1000)/F21,0))) -> 476.99446
A22: =IF(D22>100,"",Inputs!$B$4) -> 34 | B22: =IF(D22>100,"",Inputs!$B$7) -> 16 | C22: =IFERROR(IF(Inputs!$B$7+C21+1>=100,"",C21+1),"") -> 20 | D22: =IFERROR(IF(Inputs!$B$7+C22>=100,"",Inputs!$B$7+C22),"") -> 36 | E22: =IF(D22="","",INDEX(MORTALITY!$B:$B,MATCH(D22,MORTALITY!$A:$A,0))) -> 0.00486 | F22: =IF(D22="","",1-E22) -> 0.99514 | G22: =IF(D22="","",Inputs!$B$23) -> 0.025 | H22: =IF(D22="","",INDEX(Commutation!$L:$L,MATCH(Inputs!$B$7,Commutation!$A:$A,0))) -> 11.090171 | I22: =IF(D22="","",J21) -> 465.57462 | J22: =IF(D22>99,"",IF(E22=1,1000,MIN(1000,MAX(0,(INDEX(Commutation!$K:$K,MATCH(D23,Commutation!$A:$A,0))-(INDEX(Commutation!$K:$K,MATCH(Inputs!$B$7,Commutation!$A:$A,0))/((INDEX(Commutation!$H:$H,MATCH(Inputs!$B$7,Commutation!$A:$A,0))-INDEX(Commutation!$H:$H,MATCH(Inputs!$B$8,Commutation!$A:$A,0)))/INDEX(Commutation!$F:$F,MATCH(Inputs!$B$7,Commutation!$A:$A,0))))*MAX(0,(INDEX(Commutation!$H:$H,MATCH(D23,Commutation!$A:$A,0))-INDEX(Commutation!$H:$H,MATCH(Inputs!$B$8,Commutation!$A:$A,0)))/INDEX(Commutation!$F:$F,MATCH(D23,Commutation!$A:$A,0))))*1000)))) -> 474.66083 | K22: =IF(Inputs!$B$7+21-1>MAX(MORTALITY!$A:$A),"",IFERROR(J22,0)) -> 474.66083 | M22: =IF(A22="","",IF(E22=1,1000,IFERROR(((I22+IF(C22<=Inputs!$B$8,$H$2,0))*(1+G22)-E22*1000)/F22,0))) -> 486.08377
A23: =IF(D23>100,"",Inputs!$B$4) -> 34 | B23: =IF(D23>100,"",Inputs!$B$7) -> 16 | C23: =IFERROR(IF(Inputs!$B$7+C22+1>=100,"",C22+1),"") -> 21 | D23: =IFERROR(IF(Inputs!$B$7+C23>=100,"",Inputs!$B$7+C23),"") -> 37 | E23: =IF(D23="","",INDEX(MORTALITY!$B:$B,MATCH(D23,MORTALITY!$A:$A,0))) -> 0.00515 | F23: =IF(D23="","",1-E23) -> 0.99485 | G23: =IF(D23="","",Inputs!$B$23) -> 0.025 | H23: =IF(D23="","",INDEX(Commutation!$L:$L,MATCH(Inputs!$B$7,Commutation!$A:$A,0))) -> 11.090171 | I23: =IF(D23="","",J22) -> 474.66083 | J23: =IF(D23>99,"",IF(E23=1,1000,MIN(1000,MAX(0,(INDEX(Commutation!$K:$K,MATCH(D24,Commutation!$A:$A,0))-(INDEX(Commutation!$K:$K,MATCH(Inputs!$B$7,Commutation!$A:$A,0))/((INDEX(Commutation!$H:$H,MATCH(Inputs!$B$7,Commutation!$A:$A,0))-INDEX(Commutation!$H:$H,MATCH(Inputs!$B$8,Commutation!$A:$A,0)))/INDEX(Commutation!$F:$F,MATCH(Inputs!$B$7,Commutation!$A:$A,0))))*MAX(0,(INDEX(Commutation!$H:$H,MATCH(D24,Commutation!$A:$A,0))-INDEX(Commutation!$H:$H,MATCH(Inputs!$B$8,Commutation!$A:$A,0)))/INDEX(Commutation!$F:$F,MATCH(D24,Commutation!$A:$A,0))))*1000)))) -> 483.86928 | K23: =IF(Inputs!$B$7+22-1>MAX(MORTALITY!$A:$A),"",IFERROR(J23,0)) -> 483.86928 | M23: =IF(A23="","",IF(E23=1,1000,IFERROR(((I23+IF(C23<=Inputs!$B$8,$H$2,0))*(1+G23)-E23*1000)/F23,0))) -> 495.29555
A24: =IF(D24>100,"",Inputs!$B$4) -> 34 | B24: =IF(D24>100,"",Inputs!$B$7) -> 16 | C24: =IFERROR(IF(Inputs!$B$7+C23+1>=100,"",C23+1),"") -> 22 | D24: =IFERROR(IF(Inputs!$B$7+C24>=100,"",Inputs!$B$7+C24),"") -> 38 | E24: =IF(D24="","",INDEX(MORTALITY!$B:$B,MATCH(D24,MORTALITY!$A:$A,0))) -> 0.00546 | F24: =IF(D24="","",1-E24) -> 0.99454 | G24: =IF(D24="","",Inputs!$B$23) -> 0.025 | H24: =IF(D24="","",INDEX(Commutation!$L:$L,MATCH(Inputs!$B$7,Commutation!$A:$A,0))) -> 11.090171 | I24: =IF(D24="","",J23) -> 483.86928 | J24: =IF(D24>99,"",IF(E24=1,1000,MIN(1000,MAX(0,(INDEX(Commutation!$K:$K,MATCH(D25,Commutation!$A:$A,0))-(INDEX(Commutation!$K:$K,MATCH(Inputs!$B$7,Commutation!$A:$A,0))/((INDEX(Commutation!$H:$H,MATCH(Inputs!$B$7,Commutation!$A:$A,0))-INDEX(Commutation!$H:$H,MATCH(Inputs!$B$8,Commutation!$A:$A,0)))/INDEX(Commutation!$F:$F,MATCH(Inputs!$B$7,Commutation!$A:$A,0))))*MAX(0,(INDEX(Commutation!$H:$H,MATCH(D25,Commutation!$A:$A,0))-INDEX(Commutation!$H:$H,MATCH(Inputs!$B$8,Commutation!$A:$A,0)))/INDEX(Commutation!$F:$F,MATCH(D25,Commutation!$A:$A,0))))*1000)))) -> 493.19888 | K24: =IF(Inputs!$B$7+23-1>MAX(MORTALITY!$A:$A),"",IFERROR(J24,0)) -> 493.19888 | M24: =IF(A24="","",IF(E24=1,1000,IFERROR(((I24+IF(C24<=Inputs!$B$8,$H$2,0))*(1+G24)-E24*1000)/F24,0))) -> 504.62871
A25: =IF(D25>100,"",Inputs!$B$4) -> 34 | B25: =IF(D25>100,"",Inputs!$B$7) -> 16 | C25: =IFERROR(IF(Inputs!$B$7+C24+1>=100,"",C24+1),"") -> 23 | D25: =IFERROR(IF(Inputs!$B$7+C25>=100,"",Inputs!$B$7+C25),"") -> 39 | E25: =IF(D25="","",INDEX(MORTALITY!$B:$B,MATCH(D25,MORTALITY!$A:$A,0))) -> 0.00581 | F25: =IF(D25="","",1-E25) -> 0.99419 | G25: =IF(D25="","",Inputs!$B$23) -> 0.025 | H25: =IF(D25="","",INDEX(Commutation!$L:$L,MATCH(Inputs!$B$7,Commutation!$A:$A,0))) -> 11.090171 | I25: =IF(D25="","",J24) -> 493.19888 | J25: =IF(D25>99,"",IF(E25=1,1000,MIN(1000,MAX(0,(INDEX(Commutation!$K:$K,MATCH(D26,Commutation!$A:$A,0))-(INDEX(Commutation!$K:$K,MATCH(Inputs!$B$7,Commutation!$A:$A,0))/((INDEX(Commutation!$H:$H,MATCH(Inputs!$B$7,Commutation!$A:$A,0))-INDEX(Commutation!$H:$H,MATCH(Inputs!$B$8,Commutation!$A:$A,0)))/INDEX(Commutation!$F:$F,MATCH(Inputs!$B$7,Commutation!$A:$A,0))))*MAX(0,(INDEX(Commutation!$H:$H,MATCH(D26,Commutation!$A:$A,0))-INDEX(Commutation!$H:$H,MATCH(Inputs!$B$8,Commutation!$A:$A,0)))/INDEX(Commutation!$F:$F,MATCH(D26,Commutation!$A:$A,0))))*1000)))) -> 502.63918 | K25: =IF(Inputs!$B$7+24-1>MAX(MORTALITY!$A:$A),"",IFERROR(J25,0)) -> 502.63918 | M25: =IF(A25="","",IF(E25=1,1000,IFERROR(((I25+IF(C25<=Inputs!$B$8,$H$2,0))*(1+G25)-E25*1000)/F25,0))) -> 514.07304
A26: =IF(D26>100,"",Inputs!$B$4) -> 34 | B26: =IF(D26>100,"",Inputs!$B$7) -> 16 | C26: =IFERROR(IF(Inputs!$B$7+C25+1>=100,"",C25+1),"") -> 24 | D26: =IFERROR(IF(Inputs!$B$7+C26>=100,"",Inputs!$B$7+C26),"") -> 40 | E26: =IF(D26="","",INDEX(MORTALITY!$B:$B,MATCH(D26,MORTALITY!$A:$A,0))) -> 0.00618 | F26: =IF(D26="","",1-E26) -> 0.99382 | G26: =IF(D26="","",Inputs!$B$23) -> 0.025 | H26: =IF(D26="","",INDEX(Commutation!$L:$L,MATCH(Inputs!$B$7,Commutation!$A:$A,0))) -> 11.090171 | I26: =IF(D26="","",J25) -> 502.63918 | J26: =IF(D26>99,"",IF(E26=1,1000,MIN(1000,MAX(0,(INDEX(Commutation!$K:$K,MATCH(D27,Commutation!$A:$A,0))-(INDEX(Commutation!$K:$K,MATCH(Inputs!$B$7,Commutation!$A:$A,0))/((INDEX(Commutation!$H:$H,MATCH(Inputs!$B$7,Commutation!$A:$A,0))-INDEX(Commutation!$H:$H,MATCH(Inputs!$B$8,Commutation!$A:$A,0)))/INDEX(Commutation!$F:$F,MATCH(Inputs!$B$7,Commutation!$A:$A,0))))*MAX(0,(INDEX(Commutation!$H:$H,MATCH(D27,Commutation!$A:$A,0))-INDEX(Commutation!$H:$H,MATCH(Inputs!$B$8,Commutation!$A:$A,0)))/INDEX(Commutation!$F:$F,MATCH(D27,Commutation!$A:$A,0))))*1000)))) -> 512.1905 | K26: =IF(Inputs!$B$7+25-1>MAX(MORTALITY!$A:$A),"",IFERROR(J26,0)) -> 512.1905 | M26: =IF(A26="","",IF(E26=1,1000,IFERROR(((I26+IF(C26<=Inputs!$B$8,$H$2,0))*(1+G26)-E26*1000)/F26,0))) -> 523.62861
A27: =IF(D27>100,"",Inputs!$B$4) -> 34 | B27: =IF(D27>100,"",Inputs!$B$7) -> 16 | C27: =IFERROR(IF(Inputs!$B$7+C26+1>=100,"",C26+1),"") -> 25 | D27: =IFERROR(IF(Inputs!$B$7+C27>=100,"",Inputs!$B$7+C27),"") -> 41 | E27: =IF(D27="","",INDEX(MORTALITY!$B:$B,MATCH(D27,MORTALITY!$A:$A,0))) -> 0.00659 | F27: =IF(D27="","",1-E27) -> 0.99341 | G27: =IF(D27="","",Inputs!$B$23) -> 0.025 | H27: =IF(D27="","",INDEX(Commutation!$L:$L,MATCH(Inputs!$B$7,Commutation!$A:$A,0))) -> 11.090171 | I27: =IF(D27="","",J26) -> 512.1905 | J27: =IF(D27>99,"",IF(E27=1,1000,MIN(1000,MAX(0,(INDEX(Commutation!$K:$K,MATCH(D28,Commutation!$A:$A,0))-(INDEX(Commutation!$K:$K,MATCH(Inputs!$B$7,Commutation!$A:$A,0))/((INDEX(Commutation!$H:$H,MATCH(Inputs!$B$7,Commutation!$A:$A,0))-INDEX(Commutation!$H:$H,MATCH(Inputs!$B$8,Commutation!$A:$A,0)))/INDEX(Commutation!$F:$F,MATCH(Inputs!$B$7,Commutation!$A:$A,0))))*MAX(0,(INDEX(Commutation!$H:$H,MATCH(D28,Commutation!$A:$A,0))-INDEX(Commutation!$H:$H,MATCH(Inputs!$B$8,Commutation!$A:$A,0)))/INDEX(Commutation!$F:$F,MATCH(D28,Commutation!$A:$A,0))))*1000)))) -> 521.84422 | K27: =IF(Inputs!$B$7+26-1>MAX(MORTALITY!$A:$A),"",IFERROR(J27,0)) -> 521.84422 | M27: =IF(A27="","",IF(E27=1,1000,IFERROR(((I27+IF(C27<=Inputs!$B$8,$H$2,0))*(1+G27)-E27*1000)/F27,0))) -> 533.28705
A28: =IF(D28>100,"",Inputs!$B$4) -> 34 | B28: =IF(D28>100,"",Inputs!$B$7) -> 16 | C28: =IFERROR(IF(Inputs!$B$7+C27+1>=100,"",C27+1),"") -> 26 | D28: =IFERROR(IF(Inputs!$B$7+C28>=100,"",Inputs!$B$7+C28),"") -> 42 | E28: =IF(D28="","",INDEX(MORTALITY!$B:$B,MATCH(D28,MORTALITY!$A:$A,0))) -> 0.00703 | F28: =IF(D28="","",1-E28) -> 0.99297 | G28: =IF(D28="","",Inputs!$B$23) -> 0.025 | H28: =IF(D28="","",INDEX(Commutation!$L:$L,MATCH(Inputs!$B$7,Commutation!$A:$A,0))) -> 11.090171 | I28: =IF(D28="","",J27) -> 521.84422 | J28: =IF(D28>99,"",IF(E28=1,1000,MIN(1000,MAX(0,(INDEX(Commutation!$K:$K,MATCH(D29,Commutation!$A:$A,0))-(INDEX(Commutation!$K:$K,MATCH(Inputs!$B$7,Commutation!$A:$A,0))/((INDEX(Commutation!$H:$H,MATCH(Inputs!$B$7,Commutation!$A:$A,0))-INDEX(Commutation!$H:$H,MATCH(Inputs!$B$8,Commutation!$A:$A,0)))/INDEX(Commutation!$F:$F,MATCH(Inputs!$B$7,Commutation!$A:$A,0))))*MAX(0,(INDEX(Commutation!$H:$H,MATCH(D29,Commutation!$A:$A,0))-INDEX(Commutation!$H:$H,MATCH(Inputs!$B$8,Commutation!$A:$A,0)))/INDEX(Commutation!$F:$F,MATCH(D29,Commutation!$A:$A,0))))*1000)))) -> 531.59745 | K28: =IF(Inputs!$B$7+27-1>MAX(MORTALITY!$A:$A),"",IFERROR(J28,0)) -> 531.59745 | M28: =IF(A28="","",IF(E28=1,1000,IFERROR(((I28+IF(C28<=Inputs!$B$8,$H$2,0))*(1+G28)-E28*1000)/F28,0))) -> 543.04536
A29: =IF(D29>100,"",Inputs!$B$4) -> 34 | B29: =IF(D29>100,"",Inputs!$B$7) -> 16 | C29: =IFERROR(IF(Inputs!$B$7+C28+1>=100,"",C28+1),"") -> 27 | D29: =IFERROR(IF(Inputs!$B$7+C29>=100,"",Inputs!$B$7+C29),"") -> 43 | E29: =IF(D29="","",INDEX(MORTALITY!$B:$B,MATCH(D29,MORTALITY!$A:$A,0))) -> 0.00751 | F29: =IF(D29="","",1-E29) -> 0.99249 | G29: =IF(D29="","",Inputs!$B$23) -> 0.025 | H29: =IF(D29="","",INDEX(Commutation!$L:$L,MATCH(Inputs!$B$7,Commutation!$A:$A,0))) -> 11.090171 | I29: =IF(D29="","",J28) -> 531.59745 | J29: =IF(D29>99,"",IF(E29=1,1000,MIN(1000,MAX(0,(INDEX(Commutation!$K:$K,MATCH(D30,Commutation!$A:$A,0))-(INDEX(Commutation!$K:$K,MATCH(Inputs!$B$7,Commutation!$A:$A,0))/((INDEX(Commutation!$H:$H,MATCH(Inputs!$B$7,Commutation!$A:$A,0))-INDEX(Commutation!$H:$H,MATCH(Inputs!$B$8,Commutation!$A:$A,0)))/INDEX(Commutation!$F:$F,MATCH(Inputs!$B$7,Commutation!$A:$A,0))))*MAX(0,(INDEX(Commutation!$H:$H,MATCH(D30,Commutation!$A:$A,0))-INDEX(Commutation!$H:$H,MATCH(Inputs!$B$8,Commutation!$A:$A,0)))/INDEX(Commutation!$F:$F,MATCH(D30,Commutation!$A:$A,0))))*1000)))) -> 541.44363 | K29: =IF(Inputs!$B$7+28-1>MAX(MORTALITY!$A:$A),"",IFERROR(J29,0)) -> 541.44363 | M29: =IF(A29="","",IF(E29=1,1000,IFERROR(((I29+IF(C29<=Inputs!$B$8,$H$2,0))*(1+G29)-E29*1000)/F29,0))) -> 552.89707
A30: =IF(D30>100,"",Inputs!$B$4) -> 34 | B30: =IF(D30>100,"",Inputs!$B$7) -> 16 | C30: =IFERROR(IF(Inputs!$B$7+C29+1>=100,"",C29+1),"") -> 28 | D30: =IFERROR(IF(Inputs!$B$7+C30>=100,"",Inputs!$B$7+C30),"") -> 44 | E30: =IF(D30="","",INDEX(MORTALITY!$B:$B,MATCH(D30,MORTALITY!$A:$A,0))) -> 0.00804 | F30: =IF(D30="","",1-E30) -> 0.99196 | G30: =IF(D30="","",Inputs!$B$23) -> 0.025 | H30: =IF(D30="","",INDEX(Commutation!$L:$L,MATCH(Inputs!$B$7,Commutation!$A:$A,0))) -> 11.090171 | I30: =IF(D30="","",J29) -> 541.44363 | J30: =IF(D30>99,"",IF(E30=1,1000,MIN(1000,MAX(0,(INDEX(Commutation!$K:$K,MATCH(D31,Commutation!$A:$A,0))-(INDEX(Commutation!$K:$K,MATCH(Inputs!$B$7,Commutation!$A:$A,0))/((INDEX(Commutation!$H:$H,MATCH(Inputs!$B$7,Commutation!$A:$A,0))-INDEX(Commutation!$H:$H,MATCH(Inputs!$B$8,Commutation!$A:$A,0)))/INDEX(Commutation!$F:$F,MATCH(Inputs!$B$7,Commutation!$A:$A,0))))*MAX(0,(INDEX(Commutation!$H:$H,MATCH(D31,Commutation!$A:$A,0))-INDEX(Commutation!$H:$H,MATCH(Inputs!$B$8,Commutation!$A:$A,0)))/INDEX(Commutation!$F:$F,MATCH(D31,Commutation!$A:$A,0))))*1000)))) -> 551.37276 | K30: =IF(Inputs!$B$7+29-1>MAX(MORTALITY!$A:$A),"",IFERROR(J30,0)) -> 551.37276 | M30: =IF(A30="","",IF(E30=1,1000,IFERROR(((I30+IF(C30<=Inputs!$B$8,$H$2,0))*(1+G30)-E30*1000)/F30,0))) -> 562.83232
A31: =IF(D31>100,"",Inputs!$B$4) -> 34 | B31: =IF(D31>100,"",Inputs!$B$7) -> 16 | C31: =IFERROR(IF(Inputs!$B$7+C30+1>=100,"",C30+1),"") -> 29 | D31: =IFERROR(IF(Inputs!$B$7+C31>=100,"",Inputs!$B$7+C31),"") -> 45 | E31: =IF(D31="","",INDEX(MORTALITY!$B:$B,MATCH(D31,MORTALITY!$A:$A,0))) -> 0.00861 | F31: =IF(D31="","",1-E31) -> 0.99139 | G31: =IF(D31="","",Inputs!$B$23) -> 0.025 | H31: =IF(D31="","",INDEX(Commutation!$L:$L,MATCH(Inputs!$B$7,Commutation!$A:$A,0))) -> 11.090171 | I31: =IF(D31="","",J30) -> 551.37276 | J31: =IF(D31>99,"",IF(E31=1,1000,MIN(1000,MAX(0,(INDEX(Commutation!$K:$K,MATCH(D32,Commutation!$A:$A,0))-(INDEX(Commutation!$K:$K,MATCH(Inputs!$B$7,Commutation!$A:$A,0))/((INDEX(Commutation!$H:$H,MATCH(Inputs!$B$7,Commutation!$A:$A,0))-INDEX(Commutation!$H:$H,MATCH(Inputs!$B$8,Commutation!$A:$A,0)))/INDEX(Commutation!$F:$F,MATCH(Inputs!$B$7,Commutation!$A:$A,0))))*MAX(0,(INDEX(Commutation!$H:$H,MATCH(D32,Commutation!$A:$A,0))-INDEX(Commutation!$H:$H,MATCH(Inputs!$B$8,Commutation!$A:$A,0)))/INDEX(Commutation!$F:$F,MATCH(D32,Commutation!$A:$A,0))))*1000)))) -> 561.38056 | K31: =IF(Inputs!$B$7+30-1>MAX(MORTALITY!$A:$A),"",IFERROR(J31,0)) -> 561.38056 | M31: =IF(A31="","",IF(E31=1,1000,IFERROR(((I31+IF(C31<=Inputs!$B$8,$H$2,0))*(1+G31)-E31*1000)/F31,0))) -> 572.84671
A32: =IF(D32>100,"",Inputs!$B$4) -> 34 | B32: =IF(D32>100,"",Inputs!$B$7) -> 16 | C32: =IFERROR(IF(Inputs!$B$7+C31+1>=100,"",C31+1),"") -> 30 | D32: =IFERROR(IF(Inputs!$B$7+C32>=100,"",Inputs!$B$7+C32),"") -> 46 | E32: =IF(D32="","",INDEX(MORTALITY!$B:$B,MATCH(D32,MORTALITY!$A:$A,0))) -> 0.00923 | F32: =IF(D32="","",1-E32) -> 0.99077 | G32: =IF(D32="","",Inputs!$B$23) -> 0.025 | H32: =IF(D32="","",INDEX(Commutation!$L:$L,MATCH(Inputs!$B$7,Commutation!$A:$A,0))) -> 11.090171 | I32: =IF(D32="","",J31) -> 561.38056 | J32: =IF(D32>99,"",IF(E32=1,1000,MIN(1000,MAX(0,(INDEX(Commutation!$K:$K,MATCH(D33,Commutation!$A:$A,0))-(INDEX(Commutation!$K:$K,MATCH(Inputs!$B$7,Commutation!$A:$A,0))/((INDEX(Commutation!$H:$H,MATCH(Inputs!$B$7,Commutation!$A:$A,0))-INDEX(Commutation!$H:$H,MATCH(Inputs!$B$8,Commutation!$A:$A,0)))/INDEX(Commutation!$F:$F,MATCH(Inputs!$B$7,Commutation!$A:$A,0))))*MAX(0,(INDEX(Commutation!$H:$H,MATCH(D33,Commutation!$A:$A,0))-INDEX(Commutation!$H:$H,MATCH(Inputs!$B$8,Commutation!$A:$A,0)))/INDEX(Commutation!$F:$F,MATCH(D33,Commutation!$A:$A,0))))*1000)))) -> 571.45965 | K32: =IF(Inputs!$B$7+31-1>MAX(MORTALITY!$A:$A),"",IFERROR(J32,0)) -> 571.45965 | M32: =IF(A32="","",IF(E32=1,1000,IFERROR(((I32+IF(C32<=Inputs!$B$8,$H$2,0))*(1+G32)-E32*1000)/F32,0))) -> 582.93298
A33: =IF(D33>100,"",Inputs!$B$4) -> 34 | B33: =IF(D33>100,"",Inputs!$B$7) -> 16 | C33: =IFERROR(IF(Inputs!$B$7+C32+1>=100,"",C32+1),"") -> 31 | D33: =IFERROR(IF(Inputs!$B$7+C33>=100,"",Inputs!$B$7+C33),"") -> 47 | E33: =IF(D33="","",INDEX(MORTALITY!$B:$B,MATCH(D33,MORTALITY!$A:$A,0))) -> 0.00991 | F33: =IF(D33="","",1-E33) -> 0.99009 | G33: =IF(D33="","",Inputs!$B$23) -> 0.025 | H33: =IF(D33="","",INDEX(Commutation!$L:$L,MATCH(Inputs!$B$7,Commutation!$A:$A,0))) -> 11.090171 | I33: =IF(D33="","",J32) -> 571.45965 | J33: =IF(D33>99,"",IF(E33=1,1000,MIN(1000,MAX(0,(INDEX(Commutation!$K:$K,MATCH(D34,Commutation!$A:$A,0))-(INDEX(Commutation!$K:$K,MATCH(Inputs!$B$7,Commutation!$A:$A,0))/((INDEX(Commutation!$H:$H,MATCH(Inputs!$B$7,Commutation!$A:$A,0))-INDEX(Commutation!$H:$H,MATCH(Inputs!$B$8,Commutation!$A:$A,0)))/INDEX(Commutation!$F:$F,MATCH(Inputs!$B$7,Commutation!$A:$A,0))))*MAX(0,(INDEX(Commutation!$H:$H,MATCH(D34,Commutation!$A:$A,0))-INDEX(Commutation!$H:$H,MATCH(Inputs!$B$8,Commutation!$A:$A,0)))/INDEX(Commutation!$F:$F,MATCH(D34,Commutation!$A:$A,0))))*1000)))) -> 581.5998 | K33: =IF(Inputs!$B$7+32-1>MAX(MORTALITY!$A:$A),"",IFERROR(J33,0)) -> 581.5998 | M33: =IF(A33="","",IF(E33=1,1000,IFERROR(((I33+IF(C33<=Inputs!$B$8,$H$2,0))*(1+G33)-E33*1000)/F33,0))) -> 581.5998
A34: =IF(D34>100,"",Inputs!$B$4) -> 34 | B34: =IF(D34>100,"",Inputs!$B$7) -> 16 | C34: =IFERROR(IF(Inputs!$B$7+C33+1>=100,"",C33+1),"") -> 32 | D34: =IFERROR(IF(Inputs!$B$7+C34>=100,"",Inputs!$B$7+C34),"") -> 48 | E34: =IF(D34="","",INDEX(MORTALITY!$B:$B,MATCH(D34,MORTALITY!$A:$A,0))) -> 0.01064 | F34: =IF(D34="","",1-E34) -> 0.98936 | G34: =IF(D34="","",Inputs!$B$23) -> 0.025 | H34: =IF(D34="","",INDEX(Commutation!$L:$L,MATCH(Inputs!$B$7,Commutation!$A:$A,0))) -> 11.090171 | I34: =IF(D34="","",J33) -> 581.5998 | J34: =IF(D34>99,"",IF(E34=1,1000,MIN(1000,MAX(0,(INDEX(Commutation!$K:$K,MATCH(D35,Commutation!$A:$A,0))-(INDEX(Commutation!$K:$K,MATCH(Inputs!$B$7,Commutation!$A:$A,0))/((INDEX(Commutation!$H:$H,MATCH(Inputs!$B$7,Commutation!$A:$A,0))-INDEX(Commutation!$H:$H,MATCH(Inputs!$B$8,Commutation!$A:$A,0)))/INDEX(Commutation!$F:$F,MATCH(Inputs!$B$7,Commutation!$A:$A,0))))*MAX(0,(INDEX(Commutation!$H:$H,MATCH(D35,Commutation!$A:$A,0))-INDEX(Commutation!$H:$H,MATCH(Inputs!$B$8,Commutation!$A:$A,0)))/INDEX(Commutation!$F:$F,MATCH(D35,Commutation!$A:$A,0))))*1000)))) -> 591.79651 | K34: =IF(Inputs!$B$7+33-1>MAX(MORTALITY!$A:$A),"",IFERROR(J34,0)) -> 591.79651 | M34: =IF(A34="","",IF(E34=1,1000,IFERROR(((I34+IF(C34<=Inputs!$B$8,$H$2,0))*(1+G34)-E34*1000)/F34,0))) -> 591.79651
A35: =IF(D35>100,"",Inputs!$B$4) -> 34 | B35: =IF(D35>100,"",Inputs!$B$7) -> 16 | C35: =IFERROR(IF(Inputs!$B$7+C34+1>=100,"",C34+1),"") -> 33 | D35: =IFERROR(IF(Inputs!$B$7+C35>=100,"",Inputs!$B$7+C35),"") -> 49 | E35: =IF(D35="","",INDEX(MORTALITY!$B:$B,MATCH(D35,MORTALITY!$A:$A,0))) -> 0.01145 | F35: =IF(D35="","",1-E35) -> 0.98855 | G35: =IF(D35="","",Inputs!$B$23) -> 0.025 | H35: =IF(D35="","",INDEX(Commutation!$L:$L,MATCH(Inputs!$B$7,Commutation!$A:$A,0))) -> 11.090171 | I35: =IF(D35="","",J34) -> 591.79651 | J35: =IF(D35>99,"",IF(E35=1,1000,MIN(1000,MAX(0,(INDEX(Commutation!$K:$K,MATCH(D36,Commutation!$A:$A,0))-(INDEX(Commutation!$K:$K,MATCH(Inputs!$B$7,Commutation!$A:$A,0))/((INDEX(Commutation!$H:$H,MATCH(Inputs!$B$7,Commutation!$A:$A,0))-INDEX(Commutation!$H:$H,MATCH(Inputs!$B$8,Commutation!$A:$A,0)))/INDEX(Commutation!$F:$F,MATCH(Inputs!$B$7,Commutation!$A:$A,0))))*MAX(0,(INDEX(Commutation!$H:$H,MATCH(D36,Commutation!$A:$A,0))-INDEX(Commutation!$H:$H,MATCH(Inputs!$B$8,Commutation!$A:$A,0)))/INDEX(Commutation!$F:$F,MATCH(D36,Commutation!$A:$A,0))))*1000)))) -> 602.03472 | K35: =IF(Inputs!$B$7+34-1>MAX(MORTALITY!$A:$A),"",IFERROR(J35,0)) -> 602.03472 | M35: =IF(A35="","",IF(E35=1,1000,IFERROR(((I35+IF(C35<=Inputs!$B$8,$H$2,0))*(1+G35)-E35*1000)/F35,0))) -> 602.03472
A36: =IF(D36>100,"",Inputs!$B$4) -> 34 | B36: =IF(D36>100,"",Inputs!$B$7) -> 16 | C36: =IFERROR(IF(Inputs!$B$7+C35+1>=100,"",C35+1),"") -> 34 | D36: =IFERROR(IF(Inputs!$B$7+C36>=100,"",Inputs!$B$7+C36),"") -> 50 | E36: =IF(D36="","",INDEX(MORTALITY!$B:$B,MATCH(D36,MORTALITY!$A:$A,0))) -> 0.01232 | F36: =IF(D36="","",1-E36) -> 0.98768 | G36: =IF(D36="","",Inputs!$B$23) -> 0.025 | H36: =IF(D36="","",INDEX(Commutation!$L:$L,MATCH(Inputs!$B$7,Commutation!$A:$A,0))) -> 11.090171 | I36: =IF(D36="","",J35) -> 602.03472 | J36: =IF(D36>99,"",IF(E36=1,1000,MIN(1000,MAX(0,(INDEX(Commutation!$K:$K,MATCH(D37,Commutation!$A:$A,0))-(INDEX(Commutation!$K:$K,MATCH(Inputs!$B$7,Commutation!$A:$A,0))/((INDEX(Commutation!$H:$H,MATCH(Inputs!$B$7,Commutation!$A:$A,0))-INDEX(Commutation!$H:$H,MATCH(Inputs!$B$8,Commutation!$A:$A,0)))/INDEX(Commutation!$F:$F,MATCH(Inputs!$B$7,Commutation!$A:$A,0))))*MAX(0,(INDEX(Commutation!$H:$H,MATCH(D37,Commutation!$A:$A,0))-INDEX(Commutation!$H:$H,MATCH(Inputs!$B$8,Commutation!$A:$A,0)))/INDEX(Commutation!$F:$F,MATCH(D37,Commutation!$A:$A,0))))*1000)))) -> 612.30923 | K36: =IF(Inputs!$B$7+35-1>MAX(MORTALITY!$A:$A),"",IFERROR(J36,0)) -> 612.30923 | M36: =IF(A36="","",IF(E36=1,1000,IFERROR(((I36+IF(C36<=Inputs!$B$8,$H$2,0))*(1+G36)-E36*1000)/F36,0))) -> 612.30923
A37: =IF(D37>100,"",Inputs!$B$4) -> 34 | B37: =IF(D37>100,"",Inputs!$B$7) -> 16 | C37: =IFERROR(IF(Inputs!$B$7+C36+1>=100,"",C36+1),"") -> 35 | D37: =IFERROR(IF(Inputs!$B$7+C37>=100,"",Inputs!$B$7+C37),"") -> 51 | E37: =IF(D37="","",INDEX(MORTALITY!$B:$B,MATCH(D37,MORTALITY!$A:$A,0))) -> 0.01327 | F37: =IF(D37="","",1-E37) -> 0.98673 | G37: =IF(D37="","",Inputs!$B$23) -> 0.025 | H37: =IF(D37="","",INDEX(Commutation!$L:$L,MATCH(Inputs!$B$7,Commutation!$A:$A,0))) -> 11.090171 | I37: =IF(D37="","",J36) -> 612.30923 | J37: =IF(D37>99,"",IF(E37=1,1000,MIN(1000,MAX(0,(INDEX(Commutation!$K:$K,MATCH(D38,Commutation!$A:$A,0))-(INDEX(Commutation!$K:$K,MATCH(Inputs!$B$7,Commutation!$A:$A,0))/((INDEX(Commutation!$H:$H,MATCH(Inputs!$B$7,Commutation!$A:$A,0))-INDEX(Commutation!$H:$H,MATCH(Inputs!$B$8,Commutation!$A:$A,0)))/INDEX(Commutation!$F:$F,MATCH(Inputs!$B$7,Commutation!$A:$A,0))))*MAX(0,(INDEX(Commutation!$H:$H,MATCH(D38,Commutation!$A:$A,0))-INDEX(Commutation!$H:$H,MATCH(Inputs!$B$8,Commutation!$A:$A,0)))/INDEX(Commutation!$F:$F,MATCH(D38,Commutation!$A:$A,0))))*1000)))) -> 622.60899 | K37: =IF(Inputs!$B$7+36-1>MAX(MORTALITY!$A:$A),"",IFERROR(J37,0)) -> 622.60899 | M37: =IF(A37="","",IF(E37=1,1000,IFERROR(((I37+IF(C37<=Inputs!$B$8,$H$2,0))*(1+G37)-E37*1000)/F37,0))) -> 622.60899
A38: =IF(D38>100,"",Inputs!$B$4) -> 34 | B38: =IF(D38>100,"",Inputs!$B$7) -> 16 | C38: =IFERROR(IF(Inputs!$B$7+C37+1>=100,"",C37+1),"") -> 36 | D38: =IFERROR(IF(Inputs!$B$7+C38>=100,"",Inputs!$B$7+C38),"") -> 52 | E38: =IF(D38="","",INDEX(MORTALITY!$B:$B,MATCH(D38,MORTALITY!$A:$A,0))) -> 0.0143 | F38: =IF(D38="","",1-E38) -> 0.9857 | G38: =IF(D38="","",Inputs!$B$23) -> 0.025 | H38: =IF(D38="","",INDEX(Commutation!$L:$L,MATCH(Inputs!$B$7,Commutation!$A:$A,0))) -> 11.090171 | I38: =IF(D38="","",J37) -> 622.60899 | J38: =IF(D38>99,"",IF(E38=1,1000,MIN(1000,MAX(0,(INDEX(Commutation!$K:$K,MATCH(D39,Commutation!$A:$A,0))-(INDEX(Commutation!$K:$K,MATCH(Inputs!$B$7,Commutation!$A:$A,0))/((INDEX(Commutation!$H:$H,MATCH(Inputs!$B$7,Commutation!$A:$A,0))-INDEX(Commutation!$H:$H,MATCH(Inputs!$B$8,Commutation!$A:$A,0)))/INDEX(Commutation!$F:$F,MATCH(Inputs!$B$7,Commutation!$A:$A,0))))*MAX(0,(INDEX(Commutation!$H:$H,MATCH(D39,Commutation!$A:$A,0))-INDEX(Commutation!$H:$H,MATCH(Inputs!$B$8,Commutation!$A:$A,0)))/INDEX(Commutation!$F:$F,MATCH(D39,Commutation!$A:$A,0))))*1000)))) -> 632.92504 | K38: =IF(Inputs!$B$7+37-1>MAX(MORTALITY!$A:$A),"",IFERROR(J38,0)) -> 632.92504 | M38: =IF(A38="","",IF(E38=1,1000,IFERROR(((I38+IF(C38<=Inputs!$B$8,$H$2,0))*(1+G38)-E38*1000)/F38,0))) -> 632.92504
A39: =IF(D39>100,"",Inputs!$B$4) -> 34 | B39: =IF(D39>100,"",Inputs!$B$7) -> 16 | C39: =IFERROR(IF(Inputs!$B$7+C38+1>=100,"",C38+1),"") -> 37 | D39: =IFERROR(IF(Inputs!$B$7+C39>=100,"",Inputs!$B$7+C39),"") -> 53 | E39: =IF(D39="","",INDEX(MORTALITY!$B:$B,MATCH(D39,MORTALITY!$A:$A,0))) -> 0.01543 | F39: =IF(D39="","",1-E39) -> 0.98457 | G39: =IF(D39="","",Inputs!$B$23) -> 0.025 | H39: =IF(D39="","",INDEX(Commutation!$L:$L,MATCH(Inputs!$B$7,Commutation!$A:$A,0))) -> 11.090171 | I39: =IF(D39="","",J38) -> 632.92504 | J39: =IF(D39>99,"",IF(E39=1,1000,MIN(1000,MAX(0,(INDEX(Commutation!$K:$K,MATCH(D40,Commutation!$A:$A,0))-(INDEX(Commutation!$K:$K,MATCH(Inputs!$B$7,Commutation!$A:$A,0))/((INDEX(Commutation!$H:$H,MATCH(Inputs!$B$7,Commutation!$A:$A,0))-INDEX(Commutation!$H:$H,MATCH(Inputs!$B$8,Commutation!$A:$A,0)))/INDEX(Commutation!$F:$F,MATCH(Inputs!$B$7,Commutation!$A:$A,0))))*MAX(0,(INDEX(Commutation!$H:$H,MATCH(D40,Commutation!$A:$A,0))-INDEX(Commutation!$H:$H,MATCH(Inputs!$B$8,Commutation!$A:$A,0)))/INDEX(Commutation!$F:$F,MATCH(D40,Commutation!$A:$A,0))))*1000)))) -> 643.24341 | K39: =IF(Inputs!$B$7+38-1>MAX(MORTALITY!$A:$A),"",IFERROR(J39,0)) -> 643.24341 | M39: =IF(A39="","",IF(E39=1,1000,IFERROR(((I39+IF(C39<=Inputs!$B$8,$H$2,0))*(1+G39)-E39*1000)/F39,0))) -> 643.24341
A40: =IF(D40>100,"",Inputs!$B$4) -> 34 | B40: =IF(D40>100,"",Inputs!$B$7) -> 16 | C40: =IFERROR(IF(Inputs!$B$7+C39+1>=100,"",C39+1),"") -> 38 | D40: =IFERROR(IF(Inputs!$B$7+C40>=100,"",Inputs!$B$7+C40),"") -> 54 | E40: =IF(D40="","",INDEX(MORTALITY!$B:$B,MATCH(D40,MORTALITY!$A:$A,0))) -> 0.01665 | F40: =IF(D40="","",1-E40) -> 0.98335 | G40: =IF(D40="","",Inputs!$B$23) -> 0.025 | H40: =IF(D40="","",INDEX(Commutation!$L:$L,MATCH(Inputs!$B$7,Commutation!$A:$A,0))) -> 11.090171 | I40: =IF(D40="","",J39) -> 643.24341 | J40: =IF(D40>99,"",IF(E40=1,1000,MIN(1000,MAX(0,(INDEX(Commutation!$K:$K,MATCH(D41,Commutation!$A:$A,0))-(INDEX(Commutation!$K:$K,MATCH(Inputs!$B$7,Commutation!$A:$A,0))/((INDEX(Commutation!$H:$H,MATCH(Inputs!$B$7,Commutation!$A:$A,0))-INDEX(Commutation!$H:$H,MATCH(Inputs!$B$8,Commutation!$A:$A,0)))/INDEX(Commutation!$F:$F,MATCH(Inputs!$B$7,Commutation!$A:$A,0))))*MAX(0,(INDEX(Commutation!$H:$H,MATCH(D41,Commutation!$A:$A,0))-INDEX(Commutation!$H:$H,MATCH(Inputs!$B$8,Commutation!$A:$A,0)))/INDEX(Commutation!$F:$F,MATCH(D41,Commutation!$A:$A,0))))*1000)))) -> 653.55621 | K40: =IF(Inputs!$B$7+39-1>MAX(MORTALITY!$A:$A),"",IFERROR(J40,0)) -> 653.55621 | M40: =IF(A40="","",IF(E40=1,1000,IFERROR(((I40+IF(C40<=Inputs!$B$8,$H$2,0))*(1+G40)-E40*1000)/F40,0))) -> 653.55621
A41: =IF(D41>100,"",Inputs!$B$4) -> 34 | B41: =IF(D41>100,"",Inputs!$B$7) -> 16 | C41: =IFERROR(IF(Inputs!$B$7+C40+1>=100,"",C40+1),"") -> 39 | D41: =IFERROR(IF(Inputs!$B$7+C41>=100,"",Inputs!$B$7+C41),"") -> 55 | E41: =IF(D41="","",INDEX(MORTALITY!$B:$B,MATCH(D41,MORTALITY!$A:$A,0))) -> 0.01798 | F41: =IF(D41="","",1-E41) -> 0.98202 | G41: =IF(D41="","",Inputs!$B$23) -> 0.025 | H41: =IF(D41="","",INDEX(Commutation!$L:$L,MATCH(Inputs!$B$7,Commutation!$A:$A,0))) -> 11.090171 | I41: =IF(D41="","",J40) -> 653.55621 | J41: =IF(D41>99,"",IF(E41=1,1000,MIN(1000,MAX(0,(INDEX(Commutation!$K:$K,MATCH(D42,Commutation!$A:$A,0))-(INDEX(Commutation!$K:$K,MATCH(Inputs!$B$7,Commutation!$A:$A,0))/((INDEX(Commutation!$H:$H,MATCH(Inputs!$B$7,Commutation!$A:$A,0))-INDEX(Commutation!$H:$H,MATCH(Inputs!$B$8,Commutation!$A:$A,0)))/INDEX(Commutation!$F:$F,MATCH(Inputs!$B$7,Commutation!$A:$A,0))))*MAX(0,(INDEX(Commutation!$H:$H,MATCH(D42,Commutation!$A:$A,0))-INDEX(Commutation!$H:$H,MATCH(Inputs!$B$8,Commutation!$A:$A,0)))/INDEX(Commutation!$F:$F,MATCH(D42,Commutation!$A:$A,0))))*1000)))) -> 663.85116 | K41: =IF(Inputs!$B$7+40-1>MAX(MORTALITY!$A:$A),"",IFERROR(J41,0)) -> 663.85116 | M41: =IF(A41="","",IF(E41=1,1000,IFERROR(((I41+IF(C41<=Inputs!$B$8,$H$2,0))*(1+G41)-E41*1000)/F41,0))) -> 663.85116
A42: =IF(D42>100,"",Inputs!$B$4) -> 34 | B42: =IF(D42>100,"",Inputs!$B$7) -> 16 | C42: =IFERROR(IF(Inputs!$B$7+C41+1>=100,"",C41+1),"") -> 40 | D42: =IFERROR(IF(Inputs!$B$7+C42>=100,"",Inputs!$B$7+C42),"") -> 56 | E42: =IF(D42="","",INDEX(MORTALITY!$B:$B,MATCH(D42,MORTALITY!$A:$A,0))) -> 0.01943 | F42: =IF(D42="","",1-E42) -> 0.98057 | G42: =IF(D42="","",Inputs!$B$23) -> 0.025 | H42: =IF(D42="","",INDEX(Commutation!$L:$L,MATCH(Inputs!$B$7,Commutation!$A:$A,0))) -> 11.090171 | I42: =IF(D42="","",J41) -> 663.85116 | J42: =IF(D42>99,"",IF(E42=1,1000,MIN(1000,MAX(0,(INDEX(Commutation!$K:$K,MATCH(D43,Commutation!$A:$A,0))-(INDEX(Commutation!$K:$K,MATCH(Inputs!$B$7,Commutation!$A:$A,0))/((INDEX(Commutation!$H:$H,MATCH(Inputs!$B$7,Commutation!$A:$A,0))-INDEX(Commutation!$H:$H,MATCH(Inputs!$B$8,Commutation!$A:$A,0)))/INDEX(Commutation!$F:$F,MATCH(Inputs!$B$7,Commutation!$A:$A,0))))*MAX(0,(INDEX(Commutation!$H:$H,MATCH(D43,Commutation!$A:$A,0))-INDEX(Commutation!$H:$H,MATCH(Inputs!$B$8,Commutation!$A:$A,0)))/INDEX(Commutation!$F:$F,MATCH(D43,Commutation!$A:$A,0))))*1000)))) -> 674.1155 | K42: =IF(Inputs!$B$7+41-1>MAX(MORTALITY!$A:$A),"",IFERROR(J42,0)) -> 674.1155 | M42: =IF(A42="","",IF(E42=1,1000,IFERROR(((I42+IF(C42<=Inputs!$B$8,$H$2,0))*(1+G42)-E42*1000)/F42,0))) -> 674.1155
A43: =IF(D43>100,"",Inputs!$B$4) -> 34 | B43: =IF(D43>100,"",Inputs!$B$7) -> 16 | C43: =IFERROR(IF(Inputs!$B$7+C42+1>=100,"",C42+1),"") -> 41 | D43: =IFERROR(IF(Inputs!$B$7+C43>=100,"",Inputs!$B$7+C43),"") -> 57 | E43: =IF(D43="","",INDEX(MORTALITY!$B:$B,MATCH(D43,MORTALITY!$A:$A,0))) -> 0.021 | F43: =IF(D43="","",1-E43) -> 0.979 | G43: =IF(D43="","",Inputs!$B$23) -> 0.025 | H43: =IF(D43="","",INDEX(Commutation!$L:$L,MATCH(Inputs!$B$7,Commutation!$A:$A,0))) -> 11.090171 | I43: =IF(D43="","",J42) -> 674.1155 | J43: =IF(D43>99,"",IF(E43=1,1000,MIN(1000,MAX(0,(INDEX(Commutation!$K:$K,MATCH(D44,Commutation!$A:$A,0))-(INDEX(Commutation!$K:$K,MATCH(Inputs!$B$7,Commutation!$A:$A,0))/((INDEX(Commutation!$H:$H,MATCH(Inputs!$B$7,Commutation!$A:$A,0))-INDEX(Commutation!$H:$H,MATCH(Inputs!$B$8,Commutation!$A:$A,0)))/INDEX(Commutation!$F:$F,MATCH(Inputs!$B$7,Commutation!$A:$A,0))))*MAX(0,(INDEX(Commutation!$H:$H,MATCH(D44,Commutation!$A:$A,0))-INDEX(Commutation!$H:$H,MATCH(Inputs!$B$8,Commutation!$A:$A,0)))/INDEX(Commutation!$F:$F,MATCH(D44,Commutation!$A:$A,0))))*1000)))) -> 684.33952 | K43: =IF(Inputs!$B$7+42-1>MAX(MORTALITY!$A:$A),"",IFERROR(J43,0)) -> 684.33952 | M43: =IF(A43="","",IF(E43=1,1000,IFERROR(((I43+IF(C43<=Inputs!$B$8,$H$2,0))*(1+G43)-E43*1000)/F43,0))) -> 684.33952
A44: =IF(D44>100,"",Inputs!$B$4) -> 34 | B44: =IF(D44>100,"",Inputs!$B$7) -> 16 | C44: =IFERROR(IF(Inputs!$B$7+C43+1>=100,"",C43+1),"") -> 42 | D44: =IFERROR(IF(Inputs!$B$7+C44>=100,"",Inputs!$B$7+C44),"") -> 58 | E44: =IF(D44="","",INDEX(MORTALITY!$B:$B,MATCH(D44,MORTALITY!$A:$A,0))) -> 0.02271 | F44: =IF(D44="","",1-E44) -> 0.97729 | G44: =IF(D44="","",Inputs!$B$23) -> 0.025 | H44: =IF(D44="","",INDEX(Commutation!$L:$L,MATCH(Inputs!$B$7,Commutation!$A:$A,0))) -> 11.090171 | I44: =IF(D44="","",J43) -> 684.33952 | J44: =IF(D44>99,"",IF(E44=1,1000,MIN(1000,MAX(0,(INDEX(Commutation!$K:$K,MATCH(D45,Commutation!$A:$A,0))-(INDEX(Commutation!$K:$K,MATCH(Inputs!$B$7,Commutation!$A:$A,0))/((INDEX(Commutation!$H:$H,MATCH(Inputs!$B$7,Commutation!$A:$A,0))-INDEX(Commutation!$H:$H,MATCH(Inputs!$B$8,Commutation!$A:$A,0)))/INDEX(Commutation!$F:$F,MATCH(Inputs!$B$7,Commutation!$A:$A,0))))*MAX(0,(INDEX(Commutation!$H:$H,MATCH(D45,Commutation!$A:$A,0))-INDEX(Commutation!$H:$H,MATCH(Inputs!$B$8,Commutation!$A:$A,0)))/INDEX(Commutation!$F:$F,MATCH(D45,Commutation!$A:$A,0))))*1000)))) -> 694.51033 | K44: =IF(Inputs!$B$7+43-1>MAX(MORTALITY!$A:$A),"",IFERROR(J44,0)) -> 694.51033 | M44: =IF(A44="","",IF(E44=1,1000,IFERROR(((I44+IF(C44<=Inputs!$B$8,$H$2,0))*(1+G44)-E44*1000)/F44,0))) -> 694.51033
A45: =IF(D45>100,"",Inputs!$B$4) -> 34 | B45: =IF(D45>100,"",Inputs!$B$7) -> 16 | C45: =IFERROR(IF(Inputs!$B$7+C44+1>=100,"",C44+1),"") -> 43 | D45: =IFERROR(IF(Inputs!$B$7+C45>=100,"",Inputs!$B$7+C45),"") -> 59 | E45: =IF(D45="","",INDEX(MORTALITY!$B:$B,MATCH(D45,MORTALITY!$A:$A,0))) -> 0.02457 | F45: =IF(D45="","",1-E45) -> 0.97543 | G45: =IF(D45="","",Inputs!$B$23) -> 0.025 | H45: =IF(D45="","",INDEX(Commutation!$L:$L,MATCH(Inputs!$B$7,Commutation!$A:$A,0))) -> 11.090171 | I45: =IF(D45="","",J44) -> 694.51033 | J45: =IF(D45>99,"",IF(E45=1,1000,MIN(1000,MAX(0,(INDEX(Commutation!$K:$K,MATCH(D46,Commutation!$A:$A,0))-(INDEX(Commutation!$K:$K,MATCH(Inputs!$B$7,Commutation!$A:$A,0))/((INDEX(Commutation!$H:$H,MATCH(Inputs!$B$7,Commutation!$A:$A,0))-INDEX(Commutation!$H:$H,MATCH(Inputs!$B$8,Commutation!$A:$A,0)))/INDEX(Commutation!$F:$F,MATCH(Inputs!$B$7,Commutation!$A:$A,0))))*MAX(0,(INDEX(Commutation!$H:$H,MATCH(D46,Commutation!$A:$A,0))-INDEX(Commutation!$H:$H,MATCH(Inputs!$B$8,Commutation!$A:$A,0)))/INDEX(Commutation!$F:$F,MATCH(D46,Commutation!$A:$A,0))))*1000)))) -> 704.61549 | K45: =IF(Inputs!$B$7+44-1>MAX(MORTALITY!$A:$A),"",IFERROR(J45,0)) -> 704.61549 | M45: =IF(A45="","",IF(E45=1,1000,IFERROR(((I45+IF(C45<=Inputs!$B$8,$H$2,0))*(1+G45)-E45*1000)/F45,0))) -> 704.61549
A46: =IF(D46>100,"",Inputs!$B$4) -> 34 | B46: =IF(D46>100,"",Inputs!$B$7) -> 16 | C46: =IFERROR(IF(Inputs!$B$7+C45+1>=100,"",C45+1),"") -> 44 | D46: =IFERROR(IF(Inputs!$B$7+C46>=100,"",Inputs!$B$7+C46),"") -> 60 | E46: =IF(D46="","",INDEX(MORTALITY!$B:$B,MATCH(D46,MORTALITY!$A:$A,0))) -> 0.02659 | F46: =IF(D46="","",1-E46) -> 0.97341 | G46: =IF(D46="","",Inputs!$B$23) -> 0.025 | H46: =IF(D46="","",INDEX(Commutation!$L:$L,MATCH(Inputs!$B$7,Commutation!$A:$A,0))) -> 11.090171 | I46: =IF(D46="","",J45) -> 704.61549 | J46: =IF(D46>99,"",IF(E46=1,1000,MIN(1000,MAX(0,(INDEX(Commutation!$K:$K,MATCH(D47,Commutation!$A:$A,0))-(INDEX(Commutation!$K:$K,MATCH(Inputs!$B$7,Commutation!$A:$A,0))/((INDEX(Commutation!$H:$H,MATCH(Inputs!$B$7,Commutation!$A:$A,0))-INDEX(Commutation!$H:$H,MATCH(Inputs!$B$8,Commutation!$A:$A,0)))/INDEX(Commutation!$F:$F,MATCH(Inputs!$B$7,Commutation!$A:$A,0))))*MAX(0,(INDEX(Commutation!$H:$H,MATCH(D47,Commutation!$A:$A,0))-INDEX(Commutation!$H:$H,MATCH(Inputs!$B$8,Commutation!$A:$A,0)))/INDEX(Commutation!$F:$F,MATCH(D47,Commutation!$A:$A,0))))*1000)))) -> 714.64325 | K46: =IF(Inputs!$B$7+45-1>MAX(MORTALITY!$A:$A),"",IFERROR(J46,0)) -> 714.64325 | M46: =IF(A46="","",IF(E46=1,1000,IFERROR(((I46+IF(C46<=Inputs!$B$8,$H$2,0))*(1+G46)-E46*1000)/F46,0))) -> 714.64325
A47: =IF(D47>100,"",Inputs!$B$4) -> 34 | B47: =IF(D47>100,"",Inputs!$B$7) -> 16 | C47: =IFERROR(IF(Inputs!$B$7+C46+1>=100,"",C46+1),"") -> 45 | D47: =IFERROR(IF(Inputs!$B$7+C47>=100,"",Inputs!$B$7+C47),"") -> 61 | E47: =IF(D47="","",INDEX(MORTALITY!$B:$B,MATCH(D47,MORTALITY!$A:$A,0))) -> 0.02878 | F47: =IF(D47="","",1-E47) -> 0.97122 | G47: =IF(D47="","",Inputs!$B$23) -> 0.025 | H47: =IF(D47="","",INDEX(Commutation!$L:$L,MATCH(Inputs!$B$7,Commutation!$A:$A,0))) -> 11.090171 | I47: =IF(D47="","",J46) -> 714.64325 | J47: =IF(D47>99,"",IF(E47=1,1000,MIN(1000,MAX(0,(INDEX(Commutation!$K:$K,MATCH(D48,Commutation!$A:$A,0))-(INDEX(Commutation!$K:$K,MATCH(Inputs!$B$7,Commutation!$A:$A,0))/((INDEX(Commutation!$H:$H,MATCH(Inputs!$B$7,Commutation!$A:$A,0))-INDEX(Commutation!$H:$H,MATCH(Inputs!$B$8,Commutation!$A:$A,0)))/INDEX(Commutation!$F:$F,MATCH(Inputs!$B$7,Commutation!$A:$A,0))))*MAX(0,(INDEX(Commutation!$H:$H,MATCH(D48,Commutation!$A:$A,0))-INDEX(Commutation!$H:$H,MATCH(Inputs!$B$8,Commutation!$A:$A,0)))/INDEX(Commutation!$F:$F,MATCH(D48,Commutation!$A:$A,0))))*1000)))) -> 724.58282 | K47: =IF(Inputs!$B$7+46-1>MAX(MORTALITY!$A:$A),"",IFERROR(J47,0)) -> 724.58282 | M47: =IF(A47="","",IF(E47=1,1000,IFERROR(((I47+IF(C47<=Inputs!$B$8,$H$2,0))*(1+G47)-E47*1000)/F47,0))) -> 724.58282
A48: =IF(D48>100,"",Inputs!$B$4) -> 34 | B48: =IF(D48>100,"",Inputs!$B$7) -> 16 | C48: =IFERROR(IF(Inputs!$B$7+C47+1>=100,"",C47+1),"") -> 46 | D48: =IFERROR(IF(Inputs!$B$7+C48>=100,"",Inputs!$B$7+C48),"") -> 62 | E48: =IF(D48="","",INDEX(MORTALITY!$B:$B,MATCH(D48,MORTALITY!$A:$A,0))) -> 0.03118 | F48: =IF(D48="","",1-E48) -> 0.96882 | G48: =IF(D48="","",Inputs!$B$23) -> 0.025 | H48: =IF(D48="","",INDEX(Commutation!$L:$L,MATCH(Inputs!$B$7,Commutation!$A:$A,0))) -> 11.090171 | I48: =IF(D48="","",J47) -> 724.58282 | J48: =IF(D48>99,"",IF(E48=1,1000,MIN(1000,MAX(0,(INDEX(Commutation!$K:$K,MATCH(D49,Commutation!$A:$A,0))-(INDEX(Commutation!$K:$K,MATCH(Inputs!$B$7,Commutation!$A:$A,0))/((INDEX(Commutation!$H:$H,MATCH(Inputs!$B$7,Commutation!$A:$A,0))-INDEX(Commutation!$H:$H,MATCH(Inputs!$B$8,Commutation!$A:$A,0)))/INDEX(Commutation!$F:$F,MATCH(Inputs!$B$7,Commutation!$A:$A,0))))*MAX(0,(INDEX(Commutation!$H:$H,MATCH(D49,Commutation!$A:$A,0))-INDEX(Commutation!$H:$H,MATCH(Inputs!$B$8,Commutation!$A:$A,0)))/INDEX(Commutation!$F:$F,MATCH(D49,Commutation!$A:$A,0))))*1000)))) -> 734.4165 | K48: =IF(Inputs!$B$7+47-1>MAX(MORTALITY!$A:$A),"",IFERROR(J48,0)) -> 734.4165 | M48: =IF(A48="","",IF(E48=1,1000,IFERROR(((I48+IF(C48<=Inputs!$B$8,$H$2,0))*(1+G48)-E48*1000)/F48,0))) -> 734.4165
A49: =IF(D49>100,"",Inputs!$B$4) -> 34 | B49: =IF(D49>100,"",Inputs!$B$7) -> 16 | C49: =IFERROR(IF(Inputs!$B$7+C48+1>=100,"",C48+1),"") -> 47 | D49: =IFERROR(IF(Inputs!$B$7+C49>=100,"",Inputs!$B$7+C49),"") -> 63 | E49: =IF(D49="","",INDEX(MORTALITY!$B:$B,MATCH(D49,MORTALITY!$A:$A,0))) -> 0.03376 | F49: =IF(D49="","",1-E49) -> 0.96624 | G49: =IF(D49="","",Inputs!$B$23) -> 0.025 | H49: =IF(D49="","",INDEX(Commutation!$L:$L,MATCH(Inputs!$B$7,Commutation!$A:$A,0))) -> 11.090171 | I49: =IF(D49="","",J48) -> 734.4165 | J49: =IF(D49>99,"",IF(E49=1,1000,MIN(1000,MAX(0,(INDEX(Commutation!$K:$K,MATCH(D50,Commutation!$A:$A,0))-(INDEX(Commutation!$K:$K,MATCH(Inputs!$B$7,Commutation!$A:$A,0))/((INDEX(Commutation!$H:$H,MATCH(Inputs!$B$7,Commutation!$A:$A,0))-INDEX(Commutation!$H:$H,MATCH(Inputs!$B$8,Commutation!$A:$A,0)))/INDEX(Commutation!$F:$F,MATCH(Inputs!$B$7,Commutation!$A:$A,0))))*MAX(0,(INDEX(Commutation!$H:$H,MATCH(D50,Commutation!$A:$A,0))-INDEX(Commutation!$H:$H,MATCH(Inputs!$B$8,Commutation!$A:$A,0)))/INDEX(Commutation!$F:$F,MATCH(D50,Commutation!$A:$A,0))))*1000)))) -> 744.13904 | K49: =IF(Inputs!$B$7+48-1>MAX(MORTALITY!$A:$A),"",IFERROR(J49,0)) -> 744.13904 | M49: =IF(A49="","",IF(E49=1,1000,IFERROR(((I49+IF(C49<=Inputs!$B$8,$H$2,0))*(1+G49)-E49*1000)/F49,0))) -> 744.13904
A50: =IF(D50>100,"",Inputs!$B$4) -> 34 | B50: =IF(D50>100,"",Inputs!$B$7) -> 16 | C50: =IFERROR(IF(Inputs!$B$7+C49+1>=100,"",C49+1),"") -> 48 | D50: =IFERROR(IF(Inputs!$B$7+C50>=100,"",Inputs!$B$7+C50),"") -> 64 | E50: =IF(D50="","",INDEX(MORTALITY!$B:$B,MATCH(D50,MORTALITY!$A:$A,0))) -> 0.03658 | F50: =IF(D50="","",1-E50) -> 0.96342 | G50: =IF(D50="","",Inputs!$B$23) -> 0.025 | H50: =IF(D50="","",INDEX(Commutation!$L:$L,MATCH(Inputs!$B$7,Commutation!$A:$A,0))) -> 11.090171 | I50: =IF(D50="","",J49) -> 744.13904 | J50: =IF(D50>99,"",IF(E50=1,1000,MIN(1000,MAX(0,(INDEX(Commutation!$K:$K,MATCH(D51,Commutation!$A:$A,0))-(INDEX(Commutation!$K:$K,MATCH(Inputs!$B$7,Commutation!$A:$A,0))/((INDEX(Commutation!$H:$H,MATCH(Inputs!$B$7,Commutation!$A:$A,0))-INDEX(Commutation!$H:$H,MATCH(Inputs!$B$8,Commutation!$A:$A,0)))/INDEX(Commutation!$F:$F,MATCH(Inputs!$B$7,Commutation!$A:$A,0))))*MAX(0,(INDEX(Commutation!$H:$H,MATCH(D51,Commutation!$A:$A,0))-INDEX(Commutation!$H:$H,MATCH(Inputs!$B$8,Commutation!$A:$A,0)))/INDEX(Commutation!$F:$F,MATCH(D51,Commutation!$A:$A,0))))*1000)))) -> 753.73411 | K50: =IF(Inputs!$B$7+49-1>MAX(MORTALITY!$A:$A),"",IFERROR(J50,0)) -> 753.73411 | M50: =IF(A50="","",IF(E50=1,1000,IFERROR(((I50+IF(C50<=Inputs!$B$8,$H$2,0))*(1+G50)-E50*1000)/F50,0))) -> 753.73411
A51: =IF(D51>100,"",Inputs!$B$4) -> 34 | B51: =IF(D51>100,"",Inputs!$B$7) -> 16 | C51: =IFERROR(IF(Inputs!$B$7+C50+1>=100,"",C50+1),"") -> 49 | D51: =IFERROR(IF(Inputs!$B$7+C51>=100,"",Inputs!$B$7+C51),"") -> 65 | E51: =IF(D51="","",INDEX(MORTALITY!$B:$B,MATCH(D51,MORTALITY!$A:$A,0))) -> 0.03964 | F51: =IF(D51="","",1-E51) -> 0.96036 | G51: =IF(D51="","",Inputs!$B$23) -> 0.025 | H51: =IF(D51="","",INDEX(Commutation!$L:$L,MATCH(Inputs!$B$7,Commutation!$A:$A,0))) -> 11.090171 | I51: =IF(D51="","",J50) -> 753.73411 | J51: =IF(D51>99,"",IF(E51=1,1000,MIN(1000,MAX(0,(INDEX(Commutation!$K:$K,MATCH(D52,Commutation!$A:$A,0))-(INDEX(Commutation!$K:$K,MATCH(Inputs!$B$7,Commutation!$A:$A,0))/((INDEX(Commutation!$H:$H,MATCH(Inputs!$B$7,Commutation!$A:$A,0))-INDEX(Commutation!$H:$H,MATCH(Inputs!$B$8,Commutation!$A:$A,0)))/INDEX(Commutation!$F:$F,MATCH(Inputs!$B$7,Commutation!$A:$A,0))))*MAX(0,(INDEX(Commutation!$H:$H,MATCH(D52,Commutation!$A:$A,0))-INDEX(Commutation!$H:$H,MATCH(Inputs!$B$8,Commutation!$A:$A,0)))/INDEX(Commutation!$F:$F,MATCH(D52,Commutation!$A:$A,0))))*1000)))) -> 763.19033 | K51: =IF(Inputs!$B$7+50-1>MAX(MORTALITY!$A:$A),"",IFERROR(J51,0)) -> 763.19033 | M51: =IF(A51="","",IF(E51=1,1000,IFERROR(((I51+IF(C51<=Inputs!$B$8,$H$2,0))*(1+G51)-E51*1000)/F51,0))) -> 763.19033
A52: =IF(D52>100,"",Inputs!$B$4) -> 34 | B52: =IF(D52>100,"",Inputs!$B$7) -> 16 | C52: =IFERROR(IF(Inputs!$B$7+C51+1>=100,"",C51+1),"") -> 50 | D52: =IFERROR(IF(Inputs!$B$7+C52>=100,"",Inputs!$B$7+C52),"") -> 66 | E52: =IF(D52="","",INDEX(MORTALITY!$B:$B,MATCH(D52,MORTALITY!$A:$A,0))) -> 0.04296 | F52: =IF(D52="","",1-E52) -> 0.95704 | G52: =IF(D52="","",Inputs!$B$23) -> 0.025 | H52: =IF(D52="","",INDEX(Commutation!$L:$L,MATCH(Inputs!$B$7,Commutation!$A:$A,0))) -> 11.090171 | I52: =IF(D52="","",J51) -> 763.19033 | J52: =IF(D52>99,"",IF(E52=1,1000,MIN(1000,MAX(0,(INDEX(Commutation!$K:$K,MATCH(D53,Commutation!$A:$A,0))-(INDEX(Commutation!$K:$K,MATCH(Inputs!$B$7,Commutation!$A:$A,0))/((INDEX(Commutation!$H:$H,MATCH(Inputs!$B$7,Commutation!$A:$A,0))-INDEX(Commutation!$H:$H,MATCH(Inputs!$B$8,Commutation!$A:$A,0)))/INDEX(Commutation!$F:$F,MATCH(Inputs!$B$7,Commutation!$A:$A,0))))*MAX(0,(INDEX(Commutation!$H:$H,MATCH(D53,Commutation!$A:$A,0))-INDEX(Commutation!$H:$H,MATCH(Inputs!$B$8,Commutation!$A:$A,0)))/INDEX(Commutation!$F:$F,MATCH(D53,Commutation!$A:$A,0))))*1000)))) -> 772.49654 | K52: =IF(Inputs!$B$7+51-1>MAX(MORTALITY!$A:$A),"",IFERROR(J52,0)) -> 772.49654 | M52: =IF(A52="","",IF(E52=1,1000,IFERROR(((I52+IF(C52<=Inputs!$B$8,$H$2,0))*(1+G52)-E52*1000)/F52,0))) -> 772.49654
A53: =IF(D53>100,"",Inputs!$B$4) -> 34 | B53: =IF(D53>100,"",Inputs!$B$7) -> 16 | C53: =IFERROR(IF(Inputs!$B$7+C52+1>=100,"",C52+1),"") -> 51 | D53: =IFERROR(IF(Inputs!$B$7+C53>=100,"",Inputs!$B$7+C53),"") -> 67 | E53: =IF(D53="","",INDEX(MORTALITY!$B:$B,MATCH(D53,MORTALITY!$A:$A,0))) -> 0.04656 | F53: =IF(D53="","",1-E53) -> 0.95344 | G53: =IF(D53="","",Inputs!$B$23) -> 0.025 | H53: =IF(D53="","",INDEX(Commutation!$L:$L,MATCH(Inputs!$B$7,Commutation!$A:$A,0))) -> 11.090171 | I53: =IF(D53="","",J52) -> 772.49654 | J53: =IF(D53>99,"",IF(E53=1,1000,MIN(1000,MAX(0,(INDEX(Commutation!$K:$K,MATCH(D54,Commutation!$A:$A,0))-(INDEX(Commutation!$K:$K,MATCH(Inputs!$B$7,Commutation!$A:$A,0))/((INDEX(Commutation!$H:$H,MATCH(Inputs!$B$7,Commutation!$A:$A,0))-INDEX(Commutation!$H:$H,MATCH(Inputs!$B$8,Commutation!$A:$A,0)))/INDEX(Commutation!$F:$F,MATCH(Inputs!$B$7,Commutation!$A:$A,0))))*MAX(0,(INDEX(Commutation!$H:$H,MATCH(D54,Commutation!$A:$A,0))-INDEX(Commutation!$H:$H,MATCH(Inputs!$B$8,Commutation!$A:$A,0)))/INDEX(Commutation!$F:$F,MATCH(D54,Commutation!$A:$A,0))))*1000)))) -> 781.64222 | K53: =IF(Inputs!$B$7+52-1>MAX(MORTALITY!$A:$A),"",IFERROR(J53,0)) -> 781.64222 | M53: =IF(A53="","",IF(E53=1,1000,IFERROR(((I53+IF(C53<=Inputs!$B$8,$H$2,0))*(1+G53)-E53*1000)/F53,0))) -> 781.64222
A54: =IF(D54>100,"",Inputs!$B$4) -> 34 | B54: =IF(D54>100,"",Inputs!$B$7) -> 16 | C54: =IFERROR(IF(Inputs!$B$7+C53+1>=100,"",C53+1),"") -> 52 | D54: =IFERROR(IF(Inputs!$B$7+C54>=100,"",Inputs!$B$7+C54),"") -> 68 | E54: =IF(D54="","",INDEX(MORTALITY!$B:$B,MATCH(D54,MORTALITY!$A:$A,0))) -> 0.05046 | F54: =IF(D54="","",1-E54) -> 0.94954 | G54: =IF(D54="","",Inputs!$B$23) -> 0.025 | H54: =IF(D54="","",INDEX(Commutation!$L:$L,MATCH(Inputs!$B$7,Commutation!$A:$A,0))) -> 11.090171 | I54: =IF(D54="","",J53) -> 781.64222 | J54: =IF(D54>99,"",IF(E54=1,1000,MIN(1000,MAX(0,(INDEX(Commutation!$K:$K,MATCH(D55,Commutation!$A:$A,0))-(INDEX(Commutation!$K:$K,MATCH(Inputs!$B$7,Commutation!$A:$A,0))/((INDEX(Commutation!$H:$H,MATCH(Inputs!$B$7,Commutation!$A:$A,0))-INDEX(Commutation!$H:$H,MATCH(Inputs!$B$8,Commutation!$A:$A,0)))/INDEX(Commutation!$F:$F,MATCH(Inputs!$B$7,Commutation!$A:$A,0))))*MAX(0,(INDEX(Commutation!$H:$H,MATCH(D55,Commutation!$A:$A,0))-INDEX(Commutation!$H:$H,MATCH(Inputs!$B$8,Commutation!$A:$A,0)))/INDEX(Commutation!$F:$F,MATCH(D55,Commutation!$A:$A,0))))*1000)))) -> 790.61785 | K54: =IF(Inputs!$B$7+53-1>MAX(MORTALITY!$A:$A),"",IFERROR(J54,0)) -> 790.61785 | M54: =IF(A54="","",IF(E54=1,1000,IFERROR(((I54+IF(C54<=Inputs!$B$8,$H$2,0))*(1+G54)-E54*1000)/F54,0))) -> 790.61785
A55: =IF(D55>100,"",Inputs!$B$4) -> 34 | B55: =IF(D55>100,"",Inputs!$B$7) -> 16 | C55: =IFERROR(IF(Inputs!$B$7+C54+1>=100,"",C54+1),"") -> 53 | D55: =IFERROR(IF(Inputs!$B$7+C55>=100,"",Inputs!$B$7+C55),"") -> 69 | E55: =IF(D55="","",INDEX(MORTALITY!$B:$B,MATCH(D55,MORTALITY!$A:$A,0))) -> 0.0547 | F55: =IF(D55="","",1-E55) -> 0.9453 | G55: =IF(D55="","",Inputs!$B$23) -> 0.025 | H55: =IF(D55="","",INDEX(Commutation!$L:$L,MATCH(Inputs!$B$7,Commutation!$A:$A,0))) -> 11.090171 | I55: =IF(D55="","",J54) -> 790.61785 | J55: =IF(D55>99,"",IF(E55=1,1000,MIN(1000,MAX(0,(INDEX(Commutation!$K:$K,MATCH(D56,Commutation!$A:$A,0))-(INDEX(Commutation!$K:$K,MATCH(Inputs!$B$7,Commutation!$A:$A,0))/((INDEX(Commutation!$H:$H,MATCH(Inputs!$B$7,Commutation!$A:$A,0))-INDEX(Commutation!$H:$H,MATCH(Inputs!$B$8,Commutation!$A:$A,0)))/INDEX(Commutation!$F:$F,MATCH(Inputs!$B$7,Commutation!$A:$A,0))))*MAX(0,(INDEX(Commutation!$H:$H,MATCH(D56,Commutation!$A:$A,0))-INDEX(Commutation!$H:$H,MATCH(Inputs!$B$8,Commutation!$A:$A,0)))/INDEX(Commutation!$F:$F,MATCH(D56,Commutation!$A:$A,0))))*1000)))) -> 799.41108 | K55: =IF(Inputs!$B$7+54-1>MAX(MORTALITY!$A:$A),"",IFERROR(J55,0)) -> 799.41108 | M55: =IF(A55="","",IF(E55=1,1000,IFERROR(((I55+IF(C55<=Inputs!$B$8,$H$2,0))*(1+G55)-E55*1000)/F55,0))) -> 799.41108
A56: =IF(D56>100,"",Inputs!$B$4) -> 34 | B56: =IF(D56>100,"",Inputs!$B$7) -> 16 | C56: =IFERROR(IF(Inputs!$B$7+C55+1>=100,"",C55+1),"") -> 54 | D56: =IFERROR(IF(Inputs!$B$7+C56>=100,"",Inputs!$B$7+C56),"") -> 70 | E56: =IF(D56="","",INDEX(MORTALITY!$B:$B,MATCH(D56,MORTALITY!$A:$A,0))) -> 0.0593 | F56: =IF(D56="","",1-E56) -> 0.9407 | G56: =IF(D56="","",Inputs!$B$23) -> 0.025 | H56: =IF(D56="","",INDEX(Commutation!$L:$L,MATCH(Inputs!$B$7,Commutation!$A:$A,0))) -> 11.090171 | I56: =IF(D56="","",J55) -> 799.41108 | J56: =IF(D56>99,"",IF(E56=1,1000,MIN(1000,MAX(0,(INDEX(Commutation!$K:$K,MATCH(D57,Commutation!$A:$A,0))-(INDEX(Commutation!$K:$K,MATCH(Inputs!$B$7,Commutation!$A:$A,0))/((INDEX(Commutation!$H:$H,MATCH(Inputs!$B$7,Commutation!$A:$A,0))-INDEX(Commutation!$H:$H,MATCH(Inputs!$B$8,Commutation!$A:$A,0)))/INDEX(Commutation!$F:$F,MATCH(Inputs!$B$7,Commutation!$A:$A,0))))*MAX(0,(INDEX(Commutation!$H:$H,MATCH(D57,Commutation!$A:$A,0))-INDEX(Commutation!$H:$H,MATCH(Inputs!$B$8,Commutation!$A:$A,0)))/INDEX(Commutation!$F:$F,MATCH(D57,Commutation!$A:$A,0))))*1000)))) -> 808.01144 | K56: =IF(Inputs!$B$7+55-1>MAX(MORTALITY!$A:$A),"",IFERROR(J56,0)) -> 808.01144 | M56: =IF(A56="","",IF(E56=1,1000,IFERROR(((I56+IF(C56<=Inputs!$B$8,$H$2,0))*(1+G56)-E56*1000)/F56,0))) -> 808.01144
A57: =IF(D57>100,"",Inputs!$B$4) -> 34 | B57: =IF(D57>100,"",Inputs!$B$7) -> 16 | C57: =IFERROR(IF(Inputs!$B$7+C56+1>=100,"",C56+1),"") -> 55 | D57: =IFERROR(IF(Inputs!$B$7+C57>=100,"",Inputs!$B$7+C57),"") -> 71 | E57: =IF(D57="","",INDEX(MORTALITY!$B:$B,MATCH(D57,MORTALITY!$A:$A,0))) -> 0.06427 | F57: =IF(D57="","",1-E57) -> 0.93573 | G57: =IF(D57="","",Inputs!$B$23) -> 0.025 | H57: =IF(D57="","",INDEX(Commutation!$L:$L,MATCH(Inputs!$B$7,Commutation!$A:$A,0))) -> 11.090171 | I57: =IF(D57="","",J56) -> 808.01144 | J57: =IF(D57>99,"",IF(E57=1,1000,MIN(1000,MAX(0,(INDEX(Commutation!$K:$K,MATCH(D58,Commutation!$A:$A,0))-(INDEX(Commutation!$K:$K,MATCH(Inputs!$B$7,Commutation!$A:$A,0))/((INDEX(Commutation!$H:$H,MATCH(Inputs!$B$7,Commutation!$A:$A,0))-INDEX(Commutation!$H:$H,MATCH(Inputs!$B$8,Commutation!$A:$A,0)))/INDEX(Commutation!$F:$F,MATCH(Inputs!$B$7,Commutation!$A:$A,0))))*MAX(0,(INDEX(Commutation!$H:$H,MATCH(D58,Commutation!$A:$A,0))-INDEX(Commutation!$H:$H,MATCH(Inputs!$B$8,Commutation!$A:$A,0)))/INDEX(Commutation!$F:$F,MATCH(D58,Commutation!$A:$A,0))))*1000)))) -> 816.41256 | K57: =IF(Inputs!$B$7+56-1>MAX(MORTALITY!$A:$A),"",IFERROR(J57,0)) -> 816.41256 | M57: =IF(A57="","",IF(E57=1,1000,IFERROR(((I57+IF(C57<=Inputs!$B$8,$H$2,0))*(1+G57)-E57*1000)/F57,0))) -> 816.41256
A58: =IF(D58>100,"",Inputs!$B$4) -> 34 | B58: =IF(D58>100,"",Inputs!$B$7) -> 16 | C58: =IFERROR(IF(Inputs!$B$7+C57+1>=100,"",C57+1),"") -> 56 | D58: =IFERROR(IF(Inputs!$B$7+C58>=100,"",Inputs!$B$7+C58),"") -> 72 | E58: =IF(D58="","",INDEX(MORTALITY!$B:$B,MATCH(D58,MORTALITY!$A:$A,0))) -> 0.06966 | F58: =IF(D58="","",1-E58) -> 0.93034 | G58: =IF(D58="","",Inputs!$B$23) -> 0.025 | H58: =IF(D58="","",INDEX(Commutation!$L:$L,MATCH(Inputs!$B$7,Commutation!$A:$A,0))) -> 11.090171 | I58: =IF(D58="","",J57) -> 816.41256 | J58: =IF(D58>99,"",IF(E58=1,1000,MIN(1000,MAX(0,(INDEX(Commutation!$K:$K,MATCH(D59,Commutation!$A:$A,0))-(INDEX(Commutation!$K:$K,MATCH(Inputs!$B$7,Commutation!$A:$A,0))/((INDEX(Commutation!$H:$H,MATCH(Inputs!$B$7,Commutation!$A:$A,0))-INDEX(Commutation!$H:$H,MATCH(Inputs!$B$8,Commutation!$A:$A,0)))/INDEX(Commutation!$F:$F,MATCH(Inputs!$B$7,Commutation!$A:$A,0))))*MAX(0,(INDEX(Commutation!$H:$H,MATCH(D59,Commutation!$A:$A,0))-INDEX(Commutation!$H:$H,MATCH(Inputs!$B$8,Commutation!$A:$A,0)))/INDEX(Commutation!$F:$F,MATCH(D59,Commutation!$A:$A,0))))*1000)))) -> 824.60485 | K58: =IF(Inputs!$B$7+57-1>MAX(MORTALITY!$A:$A),"",IFERROR(J58,0)) -> 824.60485 | M58: =IF(A58="","",IF(E58=1,1000,IFERROR(((I58+IF(C58<=Inputs!$B$8,$H$2,0))*(1+G58)-E58*1000)/F58,0))) -> 824.60485
A59: =IF(D59>100,"",Inputs!$B$4) -> 34 | B59: =IF(D59>100,"",Inputs!$B$7) -> 16 | C59: =IFERROR(IF(Inputs!$B$7+C58+1>=100,"",C58+1),"") -> 57 | D59: =IFERROR(IF(Inputs!$B$7+C59>=100,"",Inputs!$B$7+C59),"") -> 73 | E59: =IF(D59="","",INDEX(MORTALITY!$B:$B,MATCH(D59,MORTALITY!$A:$A,0))) -> 0.0755 | F59: =IF(D59="","",1-E59) -> 0.9245 | G59: =IF(D59="","",Inputs!$B$23) -> 0.025 | H59: =IF(D59="","",INDEX(Commutation!$L:$L,MATCH(Inputs!$B$7,Commutation!$A:$A,0))) -> 11.090171 | I59: =IF(D59="","",J58) -> 824.60485 | J59: =IF(D59>99,"",IF(E59=1,1000,MIN(1000,MAX(0,(INDEX(Commutation!$K:$K,MATCH(D60,Commutation!$A:$A,0))-(INDEX(Commutation!$K:$K,MATCH(Inputs!$B$7,Commutation!$A:$A,0))/((INDEX(Commutation!$H:$H,MATCH(Inputs!$B$7,Commutation!$A:$A,0))-INDEX(Commutation!$H:$H,MATCH(Inputs!$B$8,Commutation!$A:$A,0)))/INDEX(Commutation!$F:$F,MATCH(Inputs!$B$7,Commutation!$A:$A,0))))*MAX(0,(INDEX(Commutation!$H:$H,MATCH(D60,Commutation!$A:$A,0))-INDEX(Commutation!$H:$H,MATCH(Inputs!$B$8,Commutation!$A:$A,0)))/INDEX(Commutation!$F:$F,MATCH(D60,Commutation!$A:$A,0))))*1000)))) -> 832.57974 | K59: =IF(Inputs!$B$7+58-1>MAX(MORTALITY!$A:$A),"",IFERROR(J59,0)) -> 832.57974 | M59: =IF(A59="","",IF(E59=1,1000,IFERROR(((I59+IF(C59<=Inputs!$B$8,$H$2,0))*(1+G59)-E59*1000)/F59,0))) -> 832.57974
A60: =IF(D60>100,"",Inputs!$B$4) -> 34 | B60: =IF(D60>100,"",Inputs!$B$7) -> 16 | C60: =IFERROR(IF(Inputs!$B$7+C59+1>=100,"",C59+1),"") -> 58 | D60: =IFERROR(IF(Inputs!$B$7+C60>=100,"",Inputs!$B$7+C60),"") -> 74 | E60: =IF(D60="","",INDEX(MORTALITY!$B:$B,MATCH(D60,MORTALITY!$A:$A,0))) -> 0.08181 | F60: =IF(D60="","",1-E60) -> 0.91819 | G60: =IF(D60="","",Inputs!$B$23) -> 0.025 | H60: =IF(D60="","",INDEX(Commutation!$L:$L,MATCH(Inputs!$B$7,Commutation!$A:$A,0))) -> 11.090171 | I60: =IF(D60="","",J59) -> 832.57974 | J60: =IF(D60>99,"",IF(E60=1,1000,MIN(1000,MAX(0,(INDEX(Commutation!$K:$K,MATCH(D61,Commutation!$A:$A,0))-(INDEX(Commutation!$K:$K,MATCH(Inputs!$B$7,Commutation!$A:$A,0))/((INDEX(Commutation!$H:$H,MATCH(Inputs!$B$7,Commutation!$A:$A,0))-INDEX(Commutation!$H:$H,MATCH(Inputs!$B$8,Commutation!$A:$A,0)))/INDEX(Commutation!$F:$F,MATCH(Inputs!$B$7,Commutation!$A:$A,0))))*MAX(0,(INDEX(Commutation!$H:$H,MATCH(D61,Commutation!$A:$A,0))-INDEX(Commutation!$H:$H,MATCH(Inputs!$B$8,Commutation!$A:$A,0)))/INDEX(Commutation!$F:$F,MATCH(D61,Commutation!$A:$A,0))))*1000)))) -> 840.33177 | K60: =IF(Inputs!$B$7+59-1>MAX(MORTALITY!$A:$A),"",IFERROR(J60,0)) -> 840.33177 | M60: =IF(A60="","",IF(E60=1,1000,IFERROR(((I60+IF(C60<=Inputs!$B$8,$H$2,0))*(1+G60)-E60*1000)/F60,0))) -> 840.33177
A61: =IF(D61>100,"",Inputs!$B$4) -> 34 | B61: =IF(D61>100,"",Inputs!$B$7) -> 16 | C61: =IFERROR(IF(Inputs!$B$7+C60+1>=100,"",C60+1),"") -> 59 | D61: =IFERROR(IF(Inputs!$B$7+C61>=100,"",Inputs!$B$7+C61),"") -> 75 | E61: =IF(D61="","",INDEX(MORTALITY!$B:$B,MATCH(D61,MORTALITY!$A:$A,0))) -> 0.08864 | F61: =IF(D61="","",1-E61) -> 0.91136 | G61: =IF(D61="","",Inputs!$B$23) -> 0.025 | H61: =IF(D61="","",INDEX(Commutation!$L:$L,MATCH(Inputs!$B$7,Commutation!$A:$A,0))) -> 11.090171 | I61: =IF(D61="","",J60) -> 840.33177 | J61: =IF(D61>99,"",IF(E61=1,1000,MIN(1000,MAX(0,(INDEX(Commutation!$K:$K,MATCH(D62,Commutation!$A:$A,0))-(INDEX(Commutation!$K:$K,MATCH(Inputs!$B$7,Commutation!$A:$A,0))/((INDEX(Commutation!$H:$H,MATCH(Inputs!$B$7,Commutation!$A:$A,0))-INDEX(Commutation!$H:$H,MATCH(Inputs!$B$8,Commutation!$A:$A,0)))/INDEX(Commutation!$F:$F,MATCH(Inputs!$B$7,Commutation!$A:$A,0))))*MAX(0,(INDEX(Commutation!$H:$H,MATCH(D62,Commutation!$A:$A,0))-INDEX(Commutation!$H:$H,MATCH(Inputs!$B$8,Commutation!$A:$A,0)))/INDEX(Commutation!$F:$F,MATCH(D62,Commutation!$A:$A,0))))*1000)))) -> 847.85383 | K61: =IF(Inputs!$B$7+60-1>MAX(MORTALITY!$A:$A),"",IFERROR(J61,0)) -> 847.85383 | M61: =IF(A61="","",IF(E61=1,1000,IFERROR(((I61+IF(C61<=Inputs!$B$8,$H$2,0))*(1+G61)-E61*1000)/F61,0))) -> 847.85383
A62: =IF(D62>100,"",Inputs!$B$4) -> 34 | B62: =IF(D62>100,"",Inputs!$B$7) -> 16 | C62: =IFERROR(IF(Inputs!$B$7+C61+1>=100,"",C61+1),"") -> 60 | D62: =IFERROR(IF(Inputs!$B$7+C62>=100,"",Inputs!$B$7+C62),"") -> 76 | E62: =IF(D62="","",INDEX(MORTALITY!$B:$B,MATCH(D62,MORTALITY!$A:$A,0))) -> 0.09602 | F62: =IF(D62="","",1-E62) -> 0.90398 | G62: =IF(D62="","",Inputs!$B$23) -> 0.025 | H62: =IF(D62="","",INDEX(Commutation!$L:$L,MATCH(Inputs!$B$7,Commutation!$A:$A,0))) -> 11.090171 | I62: =IF(D62="","",J61) -> 847.85383 | J62: =IF(D62>99,"",IF(E62=1,1000,MIN(1000,MAX(0,(INDEX(Commutation!$K:$K,MATCH(D63,Commutation!$A:$A,0))-(INDEX(Commutation!$K:$K,MATCH(Inputs!$B$7,Commutation!$A:$A,0))/((INDEX(Commutation!$H:$H,MATCH(Inputs!$B$7,Commutation!$A:$A,0))-INDEX(Commutation!$H:$H,MATCH(Inputs!$B$8,Commutation!$A:$A,0)))/INDEX(Commutation!$F:$F,MATCH(Inputs!$B$7,Commutation!$A:$A,0))))*MAX(0,(INDEX(Commutation!$H:$H,MATCH(D63,Commutation!$A:$A,0))-INDEX(Commutation!$H:$H,MATCH(Inputs!$B$8,Commutation!$A:$A,0)))/INDEX(Commutation!$F:$F,MATCH(D63,Commutation!$A:$A,0))))*1000)))) -> 855.14079 | K62: =IF(Inputs!$B$7+61-1>MAX(MORTALITY!$A:$A),"",IFERROR(J62,0)) -> 855.14079 | M62: =IF(A62="","",IF(E62=1,1000,IFERROR(((I62+IF(C62<=Inputs!$B$8,$H$2,0))*(1+G62)-E62*1000)/F62,0))) -> 855.14079
A63: =IF(D63>100,"",Inputs!$B$4) -> 34 | B63: =IF(D63>100,"",Inputs!$B$7) -> 16 | C63: =IFERROR(IF(Inputs!$B$7+C62+1>=100,"",C62+1),"") -> 61 | D63: =IFERROR(IF(Inputs!$B$7+C63>=100,"",Inputs!$B$7+C63),"") -> 77 | E63: =IF(D63="","",INDEX(MORTALITY!$B:$B,MATCH(D63,MORTALITY!$A:$A,0))) -> 0.10399 | F63: =IF(D63="","",1-E63) -> 0.89601 | G63: =IF(D63="","",Inputs!$B$23) -> 0.025 | H63: =IF(D63="","",INDEX(Commutation!$L:$L,MATCH(Inputs!$B$7,Commutation!$A:$A,0))) -> 11.090171 | I63: =IF(D63="","",J62) -> 855.14079 | J63: =IF(D63>99,"",IF(E63=1,1000,MIN(1000,MAX(0,(INDEX(Commutation!$K:$K,MATCH(D64,Commutation!$A:$A,0))-(INDEX(Commutation!$K:$K,MATCH(Inputs!$B$7,Commutation!$A:$A,0))/((INDEX(Commutation!$H:$H,MATCH(Inputs!$B$7,Commutation!$A:$A,0))-INDEX(Commutation!$H:$H,MATCH(Inputs!$B$8,Commutation!$A:$A,0)))/INDEX(Commutation!$F:$F,MATCH(Inputs!$B$7,Commutation!$A:$A,0))))*MAX(0,(INDEX(Commutation!$H:$H,MATCH(D64,Commutation!$A:$A,0))-INDEX(Commutation!$H:$H,MATCH(Inputs!$B$8,Commutation!$A:$A,0)))/INDEX(Commutation!$F:$F,MATCH(D64,Commutation!$A:$A,0))))*1000)))) -> 862.18827 | K63: =IF(Inputs!$B$7+62-1>MAX(MORTALITY!$A:$A),"",IFERROR(J63,0)) -> 862.18827 | M63: =IF(A63="","",IF(E63=1,1000,IFERROR(((I63+IF(C63<=Inputs!$B$8,$H$2,0))*(1+G63)-E63*1000)/F63,0))) -> 862.18827
A64: =IF(D64>100,"",Inputs!$B$4) -> 34 | B64: =IF(D64>100,"",Inputs!$B$7) -> 16 | C64: =IFERROR(IF(Inputs!$B$7+C63+1>=100,"",C63+1),"") -> 62 | D64: =IFERROR(IF(Inputs!$B$7+C64>=100,"",Inputs!$B$7+C64),"") -> 78 | E64: =IF(D64="","",INDEX(MORTALITY!$B:$B,MATCH(D64,MORTALITY!$A:$A,0))) -> 0.11259 | F64: =IF(D64="","",1-E64) -> 0.88741 | G64: =IF(D64="","",Inputs!$B$23) -> 0.025 | H64: =IF(D64="","",INDEX(Commutation!$L:$L,MATCH(Inputs!$B$7,Commutation!$A:$A,0))) -> 11.090171 | I64: =IF(D64="","",J63) -> 862.18827 | J64: =IF(D64>99,"",IF(E64=1,1000,MIN(1000,MAX(0,(INDEX(Commutation!$K:$K,MATCH(D65,Commutation!$A:$A,0))-(INDEX(Commutation!$K:$K,MATCH(Inputs!$B$7,Commutation!$A:$A,0))/((INDEX(Commutation!$H:$H,MATCH(Inputs!$B$7,Commutation!$A:$A,0))-INDEX(Commutation!$H:$H,MATCH(Inputs!$B$8,Commutation!$A:$A,0)))/INDEX(Commutation!$F:$F,MATCH(Inputs!$B$7,Commutation!$A:$A,0))))*MAX(0,(INDEX(Commutation!$H:$H,MATCH(D65,Commutation!$A:$A,0))-INDEX(Commutation!$H:$H,MATCH(Inputs!$B$8,Commutation!$A:$A,0)))/INDEX(Commutation!$F:$F,MATCH(D65,Commutation!$A:$A,0))))*1000)))) -> 868.99289 | K64: =IF(Inputs!$B$7+63-1>MAX(MORTALITY!$A:$A),"",IFERROR(J64,0)) -> 868.99289 | M64: =IF(A64="","",IF(E64=1,1000,IFERROR(((I64+IF(C64<=Inputs!$B$8,$H$2,0))*(1+G64)-E64*1000)/F64,0))) -> 868.99289
A65: =IF(D65>100,"",Inputs!$B$4) -> 34 | B65: =IF(D65>100,"",Inputs!$B$7) -> 16 | C65: =IFERROR(IF(Inputs!$B$7+C64+1>=100,"",C64+1),"") -> 63 | D65: =IFERROR(IF(Inputs!$B$7+C65>=100,"",Inputs!$B$7+C65),"") -> 79 | E65: =IF(D65="","",INDEX(MORTALITY!$B:$B,MATCH(D65,MORTALITY!$A:$A,0))) -> 0.12186 | F65: =IF(D65="","",1-E65) -> 0.87814 | G65: =IF(D65="","",Inputs!$B$23) -> 0.025 | H65: =IF(D65="","",INDEX(Commutation!$L:$L,MATCH(Inputs!$B$7,Commutation!$A:$A,0))) -> 11.090171 | I65: =IF(D65="","",J64) -> 868.99289 | J65: =IF(D65>99,"",IF(E65=1,1000,MIN(1000,MAX(0,(INDEX(Commutation!$K:$K,MATCH(D66,Commutation!$A:$A,0))-(INDEX(Commutation!$K:$K,MATCH(Inputs!$B$7,Commutation!$A:$A,0))/((INDEX(Commutation!$H:$H,MATCH(Inputs!$B$7,Commutation!$A:$A,0))-INDEX(Commutation!$H:$H,MATCH(Inputs!$B$8,Commutation!$A:$A,0)))/INDEX(Commutation!$F:$F,MATCH(Inputs!$B$7,Commutation!$A:$A,0))))*MAX(0,(INDEX(Commutation!$H:$H,MATCH(D66,Commutation!$A:$A,0))-INDEX(Commutation!$H:$H,MATCH(Inputs!$B$8,Commutation!$A:$A,0)))/INDEX(Commutation!$F:$F,MATCH(D66,Commutation!$A:$A,0))))*1000)))) -> 875.55254 | K65: =IF(Inputs!$B$7+64-1>MAX(MORTALITY!$A:$A),"",IFERROR(J65,0)) -> 875.55254 | M65: =IF(A65="","",IF(E65=1,1000,IFERROR(((I65+IF(C65<=Inputs!$B$8,$H$2,0))*(1+G65)-E65*1000)/F65,0))) -> 875.55254
A66: =IF(D66>100,"",Inputs!$B$4) -> 34 | B66: =IF(D66>100,"",Inputs!$B$7) -> 16 | C66: =IFERROR(IF(Inputs!$B$7+C65+1>=100,"",C65+1),"") -> 64 | D66: =IFERROR(IF(Inputs!$B$7+C66>=100,"",Inputs!$B$7+C66),"") -> 80 | E66: =IF(D66="","",INDEX(MORTALITY!$B:$B,MATCH(D66,MORTALITY!$A:$A,0))) -> 0.13185 | F66: =IF(D66="","",1-E66) -> 0.86815 | G66: =IF(D66="","",Inputs!$B$23) -> 0.025 | H66: =IF(D66="","",INDEX(Commutation!$L:$L,MATCH(Inputs!$B$7,Commutation!$A:$A,0))) -> 11.090171 | I66: =IF(D66="","",J65) -> 875.55254 | J66: =IF(D66>99,"",IF(E66=1,1000,MIN(1000,MAX(0,(INDEX(Commutation!$K:$K,MATCH(D67,Commutation!$A:$A,0))-(INDEX(Commutation!$K:$K,MATCH(Inputs!$B$7,Commutation!$A:$A,0))/((INDEX(Commutation!$H:$H,MATCH(Inputs!$B$7,Commutation!$A:$A,0))-INDEX(Commutation!$H:$H,MATCH(Inputs!$B$8,Commutation!$A:$A,0)))/INDEX(Commutation!$F:$F,MATCH(Inputs!$B$7,Commutation!$A:$A,0))))*MAX(0,(INDEX(Commutation!$H:$H,MATCH(D67,Commutation!$A:$A,0))-INDEX(Commutation!$H:$H,MATCH(Inputs!$B$8,Commutation!$A:$A,0)))/INDEX(Commutation!$F:$F,MATCH(D67,Commutation!$A:$A,0))))*1000)))) -> 881.8653 | K66: =IF(Inputs!$B$7+65-1>MAX(MORTALITY!$A:$A),"",IFERROR(J66,0)) -> 881.8653 | M66: =IF(A66="","",IF(E66=1,1000,IFERROR(((I66+IF(C66<=Inputs!$B$8,$H$2,0))*(1+G66)-E66*1000)/F66,0))) -> 881.8653
A67: =IF(D67>100,"",Inputs!$B$4) -> 34 | B67: =IF(D67>100,"",Inputs!$B$7) -> 16 | C67: =IFERROR(IF(Inputs!$B$7+C66+1>=100,"",C66+1),"") -> 65 | D67: =IFERROR(IF(Inputs!$B$7+C67>=100,"",Inputs!$B$7+C67),"") -> 81 | E67: =IF(D67="","",INDEX(MORTALITY!$B:$B,MATCH(D67,MORTALITY!$A:$A,0))) -> 0.1426 | F67: =IF(D67="","",1-E67) -> 0.8574 | G67: =IF(D67="","",Inputs!$B$23) -> 0.025 | H67: =IF(D67="","",INDEX(Commutation!$L:$L,MATCH(Inputs!$B$7,Commutation!$A:$A,0))) -> 11.090171 | I67: =IF(D67="","",J66) -> 881.8653 | J67: =IF(D67>99,"",IF(E67=1,1000,MIN(1000,MAX(0,(INDEX(Commutation!$K:$K,MATCH(D68,Commutation!$A:$A,0))-(INDEX(Commutation!$K:$K,MATCH(Inputs!$B$7,Commutation!$A:$A,0))/((INDEX(Commutation!$H:$H,MATCH(Inputs!$B$7,Commutation!$A:$A,0))-INDEX(Commutation!$H:$H,MATCH(Inputs!$B$8,Commutation!$A:$A,0)))/INDEX(Commutation!$F:$F,MATCH(Inputs!$B$7,Commutation!$A:$A,0))))*MAX(0,(INDEX(Commutation!$H:$H,MATCH(D68,Commutation!$A:$A,0))-INDEX(Commutation!$H:$H,MATCH(Inputs!$B$8,Commutation!$A:$A,0)))/INDEX(Commutation!$F:$F,MATCH(D68,Commutation!$A:$A,0))))*1000)))) -> 887.93087 | K67: =IF(Inputs!$B$7+66-1>MAX(MORTALITY!$A:$A),"",IFERROR(J67,0)) -> 887.93087 | M67: =IF(A67="","",IF(E67=1,1000,IFERROR(((I67+IF(C67<=Inputs!$B$8,$H$2,0))*(1+G67)-E67*1000)/F67,0))) -> 887.93087
A68: =IF(D68>100,"",Inputs!$B$4) -> 34 | B68: =IF(D68>100,"",Inputs!$B$7) -> 16 | C68: =IFERROR(IF(Inputs!$B$7+C67+1>=100,"",C67+1),"") -> 66 | D68: =IFERROR(IF(Inputs!$B$7+C68>=100,"",Inputs!$B$7+C68),"") -> 82 | E68: =IF(D68="","",INDEX(MORTALITY!$B:$B,MATCH(D68,MORTALITY!$A:$A,0))) -> 0.15416 | F68: =IF(D68="","",1-E68) -> 0.84584 | G68: =IF(D68="","",Inputs!$B$23) -> 0.025 | H68: =IF(D68="","",INDEX(Commutation!$L:$L,MATCH(Inputs!$B$7,Commutation!$A:$A,0))) -> 11.090171 | I68: =IF(D68="","",J67) -> 887.93087 | J68: =IF(D68>99,"",IF(E68=1,1000,MIN(1000,MAX(0,(INDEX(Commutation!$K:$K,MATCH(D69,Commutation!$A:$A,0))-(INDEX(Commutation!$K:$K,MATCH(Inputs!$B$7,Commutation!$A:$A,0))/((INDEX(Commutation!$H:$H,MATCH(Inputs!$B$7,Commutation!$A:$A,0))-INDEX(Commutation!$H:$H,MATCH(Inputs!$B$8,Commutation!$A:$A,0)))/INDEX(Commutation!$F:$F,MATCH(Inputs!$B$7,Commutation!$A:$A,0))))*MAX(0,(INDEX(Commutation!$H:$H,MATCH(D69,Commutation!$A:$A,0))-INDEX(Commutation!$H:$H,MATCH(Inputs!$B$8,Commutation!$A:$A,0)))/INDEX(Commutation!$F:$F,MATCH(D69,Commutation!$A:$A,0))))*1000)))) -> 893.74958 | K68: =IF(Inputs!$B$7+67-1>MAX(MORTALITY!$A:$A),"",IFERROR(J68,0)) -> 893.74958 | M68: =IF(A68="","",IF(E68=1,1000,IFERROR(((I68+IF(C68<=Inputs!$B$8,$H$2,0))*(1+G68)-E68*1000)/F68,0))) -> 893.74958
A69: =IF(D69>100,"",Inputs!$B$4) -> 34 | B69: =IF(D69>100,"",Inputs!$B$7) -> 16 | C69: =IFERROR(IF(Inputs!$B$7+C68+1>=100,"",C68+1),"") -> 67 | D69: =IFERROR(IF(Inputs!$B$7+C69>=100,"",Inputs!$B$7+C69),"") -> 83 | E69: =IF(D69="","",INDEX(MORTALITY!$B:$B,MATCH(D69,MORTALITY!$A:$A,0))) -> 0.16657 | F69: =IF(D69="","",1-E69) -> 0.83343 | G69: =IF(D69="","",Inputs!$B$23) -> 0.025 | H69: =IF(D69="","",INDEX(Commutation!$L:$L,MATCH(Inputs!$B$7,Commutation!$A:$A,0))) -> 11.090171 | I69: =IF(D69="","",J68) -> 893.74958 | J69: =IF(D69>99,"",IF(E69=1,1000,MIN(1000,MAX(0,(INDEX(Commutation!$K:$K,MATCH(D70,Commutation!$A:$A,0))-(INDEX(Commutation!$K:$K,MATCH(Inputs!$B$7,Commutation!$A:$A,0))/((INDEX(Commutation!$H:$H,MATCH(Inputs!$B$7,Commutation!$A:$A,0))-INDEX(Commutation!$H:$H,MATCH(Inputs!$B$8,Commutation!$A:$A,0)))/INDEX(Commutation!$F:$F,MATCH(Inputs!$B$7,Commutation!$A:$A,0))))*MAX(0,(INDEX(Commutation!$H:$H,MATCH(D70,Commutation!$A:$A,0))-INDEX(Commutation!$H:$H,MATCH(Inputs!$B$8,Commutation!$A:$A,0)))/INDEX(Commutation!$F:$F,MATCH(D70,Commutation!$A:$A,0))))*1000)))) -> 899.32366 | K69: =IF(Inputs!$B$7+68-1>MAX(MORTALITY!$A:$A),"",IFERROR(J69,0)) -> 899.32366 | M69: =IF(A69="","",IF(E69=1,1000,IFERROR(((I69+IF(C69<=Inputs!$B$8,$H$2,0))*(1+G69)-E69*1000)/F69,0))) -> 899.32366
A70: =IF(D70>100,"",Inputs!$B$4) -> 34 | B70: =IF(D70>100,"",Inputs!$B$7) -> 16 | C70: =IFERROR(IF(Inputs!$B$7+C69+1>=100,"",C69+1),"") -> 68 | D70: =IFERROR(IF(Inputs!$B$7+C70>=100,"",Inputs!$B$7+C70),"") -> 84 | E70: =IF(D70="","",INDEX(MORTALITY!$B:$B,MATCH(D70,MORTALITY!$A:$A,0))) -> 0.17988 | F70: =IF(D70="","",1-E70) -> 0.82012 | G70: =IF(D70="","",Inputs!$B$23) -> 0.025 | H70: =IF(D70="","",INDEX(Commutation!$L:$L,MATCH(Inputs!$B$7,Commutation!$A:$A,0))) -> 11.090171 | I70: =IF(D70="","",J69) -> 899.32366 | J70: =IF(D70>99,"",IF(E70=1,1000,MIN(1000,MAX(0,(INDEX(Commutation!$K:$K,MATCH(D71,Commutation!$A:$A,0))-(INDEX(Commutation!$K:$K,MATCH(Inputs!$B$7,Commutation!$A:$A,0))/((INDEX(Commutation!$H:$H,MATCH(Inputs!$B$7,Commutation!$A:$A,0))-INDEX(Commutation!$H:$H,MATCH(Inputs!$B$8,Commutation!$A:$A,0)))/INDEX(Commutation!$F:$F,MATCH(Inputs!$B$7,Commutation!$A:$A,0))))*MAX(0,(INDEX(Commutation!$H:$H,MATCH(D71,Commutation!$A:$A,0))-INDEX(Commutation!$H:$H,MATCH(Inputs!$B$8,Commutation!$A:$A,0)))/INDEX(Commutation!$F:$F,MATCH(D71,Commutation!$A:$A,0))))*1000)))) -> 904.65633 | K70: =IF(Inputs!$B$7+69-1>MAX(MORTALITY!$A:$A),"",IFERROR(J70,0)) -> 904.65633 | M70: =IF(A70="","",IF(E70=1,1000,IFERROR(((I70+IF(C70<=Inputs!$B$8,$H$2,0))*(1+G70)-E70*1000)/F70,0))) -> 904.65633
A71: =IF(D71>100,"",Inputs!$B$4) -> 34 | B71: =IF(D71>100,"",Inputs!$B$7) -> 16 | C71: =IFERROR(IF(Inputs!$B$7+C70+1>=100,"",C70+1),"") -> 69 | D71: =IFERROR(IF(Inputs!$B$7+C71>=100,"",Inputs!$B$7+C71),"") -> 85 | E71: =IF(D71="","",INDEX(MORTALITY!$B:$B,MATCH(D71,MORTALITY!$A:$A,0))) -> 0.19413 | F71: =IF(D71="","",1-E71) -> 0.80587 | G71: =IF(D71="","",Inputs!$B$23) -> 0.025 | H71: =IF(D71="","",INDEX(Commutation!$L:$L,MATCH(Inputs!$B$7,Commutation!$A:$A,0))) -> 11.090171 | I71: =IF(D71="","",J70) -> 904.65633 | J71: =IF(D71>99,"",IF(E71=1,1000,MIN(1000,MAX(0,(INDEX(Commutation!$K:$K,MATCH(D72,Commutation!$A:$A,0))-(INDEX(Commutation!$K:$K,MATCH(Inputs!$B$7,Commutation!$A:$A,0))/((INDEX(Commutation!$H:$H,MATCH(Inputs!$B$7,Commutation!$A:$A,0))-INDEX(Commutation!$H:$H,MATCH(Inputs!$B$8,Commutation!$A:$A,0)))/INDEX(Commutation!$F:$F,MATCH(Inputs!$B$7,Commutation!$A:$A,0))))*MAX(0,(INDEX(Commutation!$H:$H,MATCH(D72,Commutation!$A:$A,0))-INDEX(Commutation!$H:$H,MATCH(Inputs!$B$8,Commutation!$A:$A,0)))/INDEX(Commutation!$F:$F,MATCH(D72,Commutation!$A:$A,0))))*1000)))) -> 909.75312 | K71: =IF(Inputs!$B$7+70-1>MAX(MORTALITY!$A:$A),"",IFERROR(J71,0)) -> 909.75312 | M71: =IF(A71="","",IF(E71=1,1000,IFERROR(((I71+IF(C71<=Inputs!$B$8,$H$2,0))*(1+G71)-E71*1000)/F71,0))) -> 909.75312
A72: =IF(D72>100,"",Inputs!$B$4) -> 34 | B72: =IF(D72>100,"",Inputs!$B$7) -> 16 | C72: =IFERROR(IF(Inputs!$B$7+C71+1>=100,"",C71+1),"") -> 70 | D72: =IFERROR(IF(Inputs!$B$7+C72>=100,"",Inputs!$B$7+C72),"") -> 86 | E72: =IF(D72="","",INDEX(MORTALITY!$B:$B,MATCH(D72,MORTALITY!$A:$A,0))) -> 0.20937 | F72: =IF(D72="","",1-E72) -> 0.79063 | G72: =IF(D72="","",Inputs!$B$23) -> 0.025 | H72: =IF(D72="","",INDEX(Commutation!$L:$L,MATCH(Inputs!$B$7,Commutation!$A:$A,0))) -> 11.090171 | I72: =IF(D72="","",J71) -> 909.75312 | J72: =IF(D72>99,"",IF(E72=1,1000,MIN(1000,MAX(0,(INDEX(Commutation!$K:$K,MATCH(D73,Commutation!$A:$A,0))-(INDEX(Commutation!$K:$K,MATCH(Inputs!$B$7,Commutation!$A:$A,0))/((INDEX(Commutation!$H:$H,MATCH(Inputs!$B$7,Commutation!$A:$A,0))-INDEX(Commutation!$H:$H,MATCH(Inputs!$B$8,Commutation!$A:$A,0)))/INDEX(Commutation!$F:$F,MATCH(Inputs!$B$7,Commutation!$A:$A,0))))*MAX(0,(INDEX(Commutation!$H:$H,MATCH(D73,Commutation!$A:$A,0))-INDEX(Commutation!$H:$H,MATCH(Inputs!$B$8,Commutation!$A:$A,0)))/INDEX(Commutation!$F:$F,MATCH(D73,Commutation!$A:$A,0))))*1000)))) -> 914.62118 | K72: =IF(Inputs!$B$7+71-1>MAX(MORTALITY!$A:$A),"",IFERROR(J72,0)) -> 914.62118 | M72: =IF(A72="","",IF(E72=1,1000,IFERROR(((I72+IF(C72<=Inputs!$B$8,$H$2,0))*(1+G72)-E72*1000)/F72,0))) -> 914.62118
A73: =IF(D73>100,"",Inputs!$B$4) -> 34 | B73: =IF(D73>100,"",Inputs!$B$7) -> 16 | C73: =IFERROR(IF(Inputs!$B$7+C72+1>=100,"",C72+1),"") -> 71 | D73: =IFERROR(IF(Inputs!$B$7+C73>=100,"",Inputs!$B$7+C73),"") -> 87 | E73: =IF(D73="","",INDEX(MORTALITY!$B:$B,MATCH(D73,MORTALITY!$A:$A,0))) -> 0.22563 | F73: =IF(D73="","",1-E73) -> 0.77437 | G73: =IF(D73="","",Inputs!$B$23) -> 0.025 | H73: =IF(D73="","",INDEX(Commutation!$L:$L,MATCH(Inputs!$B$7,Commutation!$A:$A,0))) -> 11.090171 | I73: =IF(D73="","",J72) -> 914.62118 | J73: =IF(D73>99,"",IF(E73=1,1000,MIN(1000,MAX(0,(INDEX(Commutation!$K:$K,MATCH(D74,Commutation!$A:$A,0))-(INDEX(Commutation!$K:$K,MATCH(Inputs!$B$7,Commutation!$A:$A,0))/((INDEX(Commutation!$H:$H,MATCH(Inputs!$B$7,Commutation!$A:$A,0))-INDEX(Commutation!$H:$H,MATCH(Inputs!$B$8,Commutation!$A:$A,0)))/INDEX(Commutation!$F:$F,MATCH(Inputs!$B$7,Commutation!$A:$A,0))))*MAX(0,(INDEX(Commutation!$H:$H,MATCH(D74,Commutation!$A:$A,0))-INDEX(Commutation!$H:$H,MATCH(Inputs!$B$8,Commutation!$A:$A,0)))/INDEX(Commutation!$F:$F,MATCH(D74,Commutation!$A:$A,0))))*1000)))) -> 919.27206 | K73: =IF(Inputs!$B$7+72-1>MAX(MORTALITY!$A:$A),"",IFERROR(J73,0)) -> 919.27206 | M73: =IF(A73="","",IF(E73=1,1000,IFERROR(((I73+IF(C73<=Inputs!$B$8,$H$2,0))*(1+G73)-E73*1000)/F73,0))) -> 919.27206
A74: =IF(D74>100,"",Inputs!$B$4) -> 34 | B74: =IF(D74>100,"",Inputs!$B$7) -> 16 | C74: =IFERROR(IF(Inputs!$B$7+C73+1>=100,"",C73+1),"") -> 72 | D74: =IFERROR(IF(Inputs!$B$7+C74>=100,"",Inputs!$B$7+C74),"") -> 88 | E74: =IF(D74="","",INDEX(MORTALITY!$B:$B,MATCH(D74,MORTALITY!$A:$A,0))) -> 0.243 | F74: =IF(D74="","",1-E74) -> 0.757 | G74: =IF(D74="","",Inputs!$B$23) -> 0.025 | H74: =IF(D74="","",INDEX(Commutation!$L:$L,MATCH(Inputs!$B$7,Commutation!$A:$A,0))) -> 11.090171 | I74: =IF(D74="","",J73) -> 919.27206 | J74: =IF(D74>99,"",IF(E74=1,1000,MIN(1000,MAX(0,(INDEX(Commutation!$K:$K,MATCH(D75,Commutation!$A:$A,0))-(INDEX(Commutation!$K:$K,MATCH(Inputs!$B$7,Commutation!$A:$A,0))/((INDEX(Commutation!$H:$H,MATCH(Inputs!$B$7,Commutation!$A:$A,0))-INDEX(Commutation!$H:$H,MATCH(Inputs!$B$8,Commutation!$A:$A,0)))/INDEX(Commutation!$F:$F,MATCH(Inputs!$B$7,Commutation!$A:$A,0))))*MAX(0,(INDEX(Commutation!$H:$H,MATCH(D75,Commutation!$A:$A,0))-INDEX(Commutation!$H:$H,MATCH(Inputs!$B$8,Commutation!$A:$A,0)))/INDEX(Commutation!$F:$F,MATCH(D75,Commutation!$A:$A,0))))*1000)))) -> 923.71713 | K74: =IF(Inputs!$B$7+73-1>MAX(MORTALITY!$A:$A),"",IFERROR(J74,0)) -> 923.71713 | M74: =IF(A74="","",IF(E74=1,1000,IFERROR(((I74+IF(C74<=Inputs!$B$8,$H$2,0))*(1+G74)-E74*1000)/F74,0))) -> 923.71713
A75: =IF(D75>100,"",Inputs!$B$4) -> 34 | B75: =IF(D75>100,"",Inputs!$B$7) -> 16 | C75: =IFERROR(IF(Inputs!$B$7+C74+1>=100,"",C74+1),"") -> 73 | D75: =IFERROR(IF(Inputs!$B$7+C75>=100,"",Inputs!$B$7+C75),"") -> 89 | E75: =IF(D75="","",INDEX(MORTALITY!$B:$B,MATCH(D75,MORTALITY!$A:$A,0))) -> 0.26144 | F75: =IF(D75="","",1-E75) -> 0.73856 | G75: =IF(D75="","",Inputs!$B$23) -> 0.025 | H75: =IF(D75="","",INDEX(Commutation!$L:$L,MATCH(Inputs!$B$7,Commutation!$A:$A,0))) -> 11.090171 | I75: =IF(D75="","",J74) -> 923.71713 | J75: =IF(D75>99,"",IF(E75=1,1000,MIN(1000,MAX(0,(INDEX(Commutation!$K:$K,MATCH(D76,Commutation!$A:$A,0))-(INDEX(Commutation!$K:$K,MATCH(Inputs!$B$7,Commutation!$A:$A,0))/((INDEX(Commutation!$H:$H,MATCH(Inputs!$B$7,Commutation!$A:$A,0))-INDEX(Commutation!$H:$H,MATCH(Inputs!$B$8,Commutation!$A:$A,0)))/INDEX(Commutation!$F:$F,MATCH(Inputs!$B$7,Commutation!$A:$A,0))))*MAX(0,(INDEX(Commutation!$H:$H,MATCH(D76,Commutation!$A:$A,0))-INDEX(Commutation!$H:$H,MATCH(Inputs!$B$8,Commutation!$A:$A,0)))/INDEX(Commutation!$F:$F,MATCH(D76,Commutation!$A:$A,0))))*1000)))) -> 927.98155 | K75: =IF(Inputs!$B$7+74-1>MAX(MORTALITY!$A:$A),"",IFERROR(J75,0)) -> 927.98155 | M75: =IF(A75="","",IF(E75=1,1000,IFERROR(((I75+IF(C75<=Inputs!$B$8,$H$2,0))*(1+G75)-E75*1000)/F75,0))) -> 927.98155
A76: =IF(D76>100,"",Inputs!$B$4) -> 34 | B76: =IF(D76>100,"",Inputs!$B$7) -> 16 | C76: =IFERROR(IF(Inputs!$B$7+C75+1>=100,"",C75+1),"") -> 74 | D76: =IFERROR(IF(Inputs!$B$7+C76>=100,"",Inputs!$B$7+C76),"") -> 90 | E76: =IF(D76="","",INDEX(MORTALITY!$B:$B,MATCH(D76,MORTALITY!$A:$A,0))) -> 0.28099 | F76: =IF(D76="","",1-E76) -> 0.71901 | G76: =IF(D76="","",Inputs!$B$23) -> 0.025 | H76: =IF(D76="","",INDEX(Commutation!$L:$L,MATCH(Inputs!$B$7,Commutation!$A:$A,0))) -> 11.090171 | I76: =IF(D76="","",J75) -> 927.98155 | J76: =IF(D76>99,"",IF(E76=1,1000,MIN(1000,MAX(0,(INDEX(Commutation!$K:$K,MATCH(D77,Commutation!$A:$A,0))-(INDEX(Commutation!$K:$K,MATCH(Inputs!$B$7,Commutation!$A:$A,0))/((INDEX(Commutation!$H:$H,MATCH(Inputs!$B$7,Commutation!$A:$A,0))-INDEX(Commutation!$H:$H,MATCH(Inputs!$B$8,Commutation!$A:$A,0)))/INDEX(Commutation!$F:$F,MATCH(Inputs!$B$7,Commutation!$A:$A,0))))*MAX(0,(INDEX(Commutation!$H:$H,MATCH(D77,Commutation!$A:$A,0))-INDEX(Commutation!$H:$H,MATCH(Inputs!$B$8,Commutation!$A:$A,0)))/INDEX(Commutation!$F:$F,MATCH(D77,Commutation!$A:$A,0))))*1000)))) -> 932.1026 | K76: =IF(Inputs!$B$7+75-1>MAX(MORTALITY!$A:$A),"",IFERROR(J76,0)) -> 932.1026 | M76: =IF(A76="","",IF(E76=1,1000,IFERROR(((I76+IF(C76<=Inputs!$B$8,$H$2,0))*(1+G76)-E76*1000)/F76,0))) -> 932.1026
A77: =IF(D77>100,"",Inputs!$B$4) -> 34 | B77: =IF(D77>100,"",Inputs!$B$7) -> 16 | C77: =IFERROR(IF(Inputs!$B$7+C76+1>=100,"",C76+1),"") -> 75 | D77: =IFERROR(IF(Inputs!$B$7+C77>=100,"",Inputs!$B$7+C77),"") -> 91 | E77: =IF(D77="","",INDEX(MORTALITY!$B:$B,MATCH(D77,MORTALITY!$A:$A,0))) -> 0.30173 | F77: =IF(D77="","",1-E77) -> 0.69827 | G77: =IF(D77="","",Inputs!$B$23) -> 0.025 | H77: =IF(D77="","",INDEX(Commutation!$L:$L,MATCH(Inputs!$B$7,Commutation!$A:$A,0))) -> 11.090171 | I77: =IF(D77="","",J76) -> 932.1026 | J77: =IF(D77>99,"",IF(E77=1,1000,MIN(1000,MAX(0,(INDEX(Commutation!$K:$K,MATCH(D78,Commutation!$A:$A,0))-(INDEX(Commutation!$K:$K,MATCH(Inputs!$B$7,Commutation!$A:$A,0))/((INDEX(Commutation!$H:$H,MATCH(Inputs!$B$7,Commutation!$A:$A,0))-INDEX(Commutation!$H:$H,MATCH(Inputs!$B$8,Commutation!$A:$A,0)))/INDEX(Commutation!$F:$F,MATCH(Inputs!$B$7,Commutation!$A:$A,0))))*MAX(0,(INDEX(Commutation!$H:$H,MATCH(D78,Commutation!$A:$A,0))-INDEX(Commutation!$H:$H,MATCH(Inputs!$B$8,Commutation!$A:$A,0)))/INDEX(Commutation!$F:$F,MATCH(D78,Commutation!$A:$A,0))))*1000)))) -> 936.13526 | K77: =IF(Inputs!$B$7+76-1>MAX(MORTALITY!$A:$A),"",IFERROR(J77,0)) -> 936.13526 | M77: =IF(A77="","",IF(E77=1,1000,IFERROR(((I77+IF(C77<=Inputs!$B$8,$H$2,0))*(1+G77)-E77*1000)/F77,0))) -> 936.13526
A78: =IF(D78>100,"",Inputs!$B$4) -> 34 | B78: =IF(D78>100,"",Inputs!$B$7) -> 16 | C78: =IFERROR(IF(Inputs!$B$7+C77+1>=100,"",C77+1),"") -> 76 | D78: =IFERROR(IF(Inputs!$B$7+C78>=100,"",Inputs!$B$7+C78),"") -> 92 | E78: =IF(D78="","",INDEX(MORTALITY!$B:$B,MATCH(D78,MORTALITY!$A:$A,0))) -> 0.32364 | F78: =IF(D78="","",1-E78) -> 0.67636 | G78: =IF(D78="","",Inputs!$B$23) -> 0.025 | H78: =IF(D78="","",INDEX(Commutation!$L:$L,MATCH(Inputs!$B$7,Commutation!$A:$A,0))) -> 11.090171 | I78: =IF(D78="","",J77) -> 936.13526 | J78: =IF(D78>99,"",IF(E78=1,1000,MIN(1000,MAX(0,(INDEX(Commutation!$K:$K,MATCH(D79,Commutation!$A:$A,0))-(INDEX(Commutation!$K:$K,MATCH(Inputs!$B$7,Commutation!$A:$A,0))/((INDEX(Commutation!$H:$H,MATCH(Inputs!$B$7,Commutation!$A:$A,0))-INDEX(Commutation!$H:$H,MATCH(Inputs!$B$8,Commutation!$A:$A,0)))/INDEX(Commutation!$F:$F,MATCH(Inputs!$B$7,Commutation!$A:$A,0))))*MAX(0,(INDEX(Commutation!$H:$H,MATCH(D79,Commutation!$A:$A,0))-INDEX(Commutation!$H:$H,MATCH(Inputs!$B$8,Commutation!$A:$A,0)))/INDEX(Commutation!$F:$F,MATCH(D79,Commutation!$A:$A,0))))*1000)))) -> 940.17778 | K78: =IF(Inputs!$B$7+77-1>MAX(MORTALITY!$A:$A),"",IFERROR(J78,0)) -> 940.17778 | M78: =IF(A78="","",IF(E78=1,1000,IFERROR(((I78+IF(C78<=Inputs!$B$8,$H$2,0))*(1+G78)-E78*1000)/F78,0))) -> 940.17778
A79: =IF(D79>100,"",Inputs!$B$4) -> 34 | B79: =IF(D79>100,"",Inputs!$B$7) -> 16 | C79: =IFERROR(IF(Inputs!$B$7+C78+1>=100,"",C78+1),"") -> 77 | D79: =IFERROR(IF(Inputs!$B$7+C79>=100,"",Inputs!$B$7+C79),"") -> 93 | E79: =IF(D79="","",INDEX(MORTALITY!$B:$B,MATCH(D79,MORTALITY!$A:$A,0))) -> 0.34666 | F79: =IF(D79="","",1-E79) -> 0.65334 | G79: =IF(D79="","",Inputs!$B$23) -> 0.025 | H79: =IF(D79="","",INDEX(Commutation!$L:$L,MATCH(Inputs!$B$7,Commutation!$A:$A,0))) -> 11.090171 | I79: =IF(D79="","",J78) -> 940.17778 | J79: =IF(D79>99,"",IF(E79=1,1000,MIN(1000,MAX(0,(INDEX(Commutation!$K:$K,MATCH(D80,Commutation!$A:$A,0))-(INDEX(Commutation!$K:$K,MATCH(Inputs!$B$7,Commutation!$A:$A,0))/((INDEX(Commutation!$H:$H,MATCH(Inputs!$B$7,Commutation!$A:$A,0))-INDEX(Commutation!$H:$H,MATCH(Inputs!$B$8,Commutation!$A:$A,0)))/INDEX(Commutation!$F:$F,MATCH(Inputs!$B$7,Commutation!$A:$A,0))))*MAX(0,(INDEX(Commutation!$H:$H,MATCH(D80,Commutation!$A:$A,0))-INDEX(Commutation!$H:$H,MATCH(Inputs!$B$8,Commutation!$A:$A,0)))/INDEX(Commutation!$F:$F,MATCH(D80,Commutation!$A:$A,0))))*1000)))) -> 944.41214 | K79: =IF(Inputs!$B$7+78-1>MAX(MORTALITY!$A:$A),"",IFERROR(J79,0)) -> 944.41214 | M79: =IF(A79="","",IF(E79=1,1000,IFERROR(((I79+IF(C79<=Inputs!$B$8,$H$2,0))*(1+G79)-E79*1000)/F79,0))) -> 944.41214
A80: =IF(D80>100,"",Inputs!$B$4) -> 34 | B80: =IF(D80>100,"",Inputs!$B$7) -> 16 | C80: =IFERROR(IF(Inputs!$B$7+C79+1>=100,"",C79+1),"") -> 78 | D80: =IFERROR(IF(Inputs!$B$7+C80>=100,"",Inputs!$B$7+C80),"") -> 94 | E80: =IF(D80="","",INDEX(MORTALITY!$B:$B,MATCH(D80,MORTALITY!$A:$A,0))) -> 0.371 | F80: =IF(D80="","",1-E80) -> 0.629 | G80: =IF(D80="","",Inputs!$B$23) -> 0.025 | H80: =IF(D80="","",INDEX(Commutation!$L:$L,MATCH(Inputs!$B$7,Commutation!$A:$A,0))) -> 11.090171 | I80: =IF(D80="","",J79) -> 944.41214 | J80: =IF(D80>99,"",IF(E80=1,1000,MIN(1000,MAX(0,(INDEX(Commutation!$K:$K,MATCH(D81,Commutation!$A:$A,0))-(INDEX(Commutation!$K:$K,MATCH(Inputs!$B$7,Commutation!$A:$A,0))/((INDEX(Commutation!$H:$H,MATCH(Inputs!$B$7,Commutation!$A:$A,0))-INDEX(Commutation!$H:$H,MATCH(Inputs!$B$8,Commutation!$A:$A,0)))/INDEX(Commutation!$F:$F,MATCH(Inputs!$B$7,Commutation!$A:$A,0))))*MAX(0,(INDEX(Commutation!$H:$H,MATCH(D81,Commutation!$A:$A,0))-INDEX(Commutation!$H:$H,MATCH(Inputs!$B$8,Commutation!$A:$A,0)))/INDEX(Commutation!$F:$F,MATCH(D81,Commutation!$A:$A,0))))*1000)))) -> 949.16127 | K80: =IF(Inputs!$B$7+79-1>MAX(MORTALITY!$A:$A),"",IFERROR(J80,0)) -> 949.16127 | M80: =IF(A80="","",IF(E80=1,1000,IFERROR(((I80+IF(C80<=Inputs!$B$8,$H$2,0))*(1+G80)-E80*1000)/F80,0))) -> 949.16127
A81: =IF(D81>100,"",Inputs!$B$4) -> 34 | B81: =IF(D81>100,"",Inputs!$B$7) -> 16 | C81: =IFERROR(IF(Inputs!$B$7+C80+1>=100,"",C80+1),"") -> 79 | D81: =IFERROR(IF(Inputs!$B$7+C81>=100,"",Inputs!$B$7+C81),"") -> 95 | E81: =IF(D81="","",INDEX(MORTALITY!$B:$B,MATCH(D81,MORTALITY!$A:$A,0))) -> 0.39621 | F81: =IF(D81="","",1-E81) -> 0.60379 | G81: =IF(D81="","",Inputs!$B$23) -> 0.025 | H81: =IF(D81="","",INDEX(Commutation!$L:$L,MATCH(Inputs!$B$7,Commutation!$A:$A,0))) -> 11.090171 | I81: =IF(D81="","",J80) -> 949.16127 | J81: =IF(D81>99,"",IF(E81=1,1000,MIN(1000,MAX(0,(INDEX(Commutation!$K:$K,MATCH(D82,Commutation!$A:$A,0))-(INDEX(Commutation!$K:$K,MATCH(Inputs!$B$7,Commutation!$A:$A,0))/((INDEX(Commutation!$H:$H,MATCH(Inputs!$B$7,Commutation!$A:$A,0))-INDEX(Commutation!$H:$H,MATCH(Inputs!$B$8,Commutation!$A:$A,0)))/INDEX(Commutation!$F:$F,MATCH(Inputs!$B$7,Commutation!$A:$A,0))))*MAX(0,(INDEX(Commutation!$H:$H,MATCH(D82,Commutation!$A:$A,0))-INDEX(Commutation!$H:$H,MATCH(Inputs!$B$8,Commutation!$A:$A,0)))/INDEX(Commutation!$F:$F,MATCH(D82,Commutation!$A:$A,0))))*1000)))) -> 955.10078 | K81: =IF(Inputs!$B$7+80-1>MAX(MORTALITY!$A:$A),"",IFERROR(J81,0)) -> 955.10078 | M81: =IF(A81="","",IF(E81=1,1000,IFERROR(((I81+IF(C81<=Inputs!$B$8,$H$2,0))*(1+G81)-E81*1000)/F81,0))) -> 955.10078
A82: =IF(D82>100,"",Inputs!$B$4) -> 34 | B82: =IF(D82>100,"",Inputs!$B$7) -> 16 | C82: =IFERROR(IF(Inputs!$B$7+C81+1>=100,"",C81+1),"") -> 80 | D82: =IFERROR(IF(Inputs!$B$7+C82>=100,"",Inputs!$B$7+C82),"") -> 96 | E82: =IF(D82="","",INDEX(MORTALITY!$B:$B,MATCH(D82,MORTALITY!$A:$A,0))) -> 0.44719 | F82: =IF(D82="","",1-E82) -> 0.55281 | G82: =IF(D82="","",Inputs!$B$23) -> 0.025 | H82: =IF(D82="","",INDEX(Commutation!$L:$L,MATCH(Inputs!$B$7,Commutation!$A:$A,0))) -> 11.090171 | I82: =IF(D82="","",J81) -> 955.10078 | J82: =IF(D82>99,"",IF(E82=1,1000,MIN(1000,MAX(0,(INDEX(Commutation!$K:$K,MATCH(D83,Commutation!$A:$A,0))-(INDEX(Commutation!$K:$K,MATCH(Inputs!$B$7,Commutation!$A:$A,0))/((INDEX(Commutation!$H:$H,MATCH(Inputs!$B$7,Commutation!$A:$A,0))-INDEX(Commutation!$H:$H,MATCH(Inputs!$B$8,Commutation!$A:$A,0)))/INDEX(Commutation!$F:$F,MATCH(Inputs!$B$7,Commutation!$A:$A,0))))*MAX(0,(INDEX(Commutation!$H:$H,MATCH(D83,Commutation!$A:$A,0))-INDEX(Commutation!$H:$H,MATCH(Inputs!$B$8,Commutation!$A:$A,0)))/INDEX(Commutation!$F:$F,MATCH(D83,Commutation!$A:$A,0))))*1000)))) -> 961.97302 | K82: =IF(Inputs!$B$7+81-1>MAX(MORTALITY!$A:$A),"",IFERROR(J82,0)) -> 961.97302 | M82: =IF(A82="","",IF(E82=1,1000,IFERROR(((I82+IF(C82<=Inputs!$B$8,$H$2,0))*(1+G82)-E82*1000)/F82,0))) -> 961.97302
A83: =IF(D83>100,"",Inputs!$B$4) -> 34 | B83: =IF(D83>100,"",Inputs!$B$7) -> 16 | C83: =IFERROR(IF(Inputs!$B$7+C82+1>=100,"",C82+1),"") -> 81 | D83: =IFERROR(IF(Inputs!$B$7+C83>=100,"",Inputs!$B$7+C83),"") -> 97 | E83: =IF(D83="","",INDEX(MORTALITY!$B:$B,MATCH(D83,MORTALITY!$A:$A,0))) -> 0.54826 | F83: =IF(D83="","",1-E83) -> 0.45174 | G83: =IF(D83="","",Inputs!$B$23) -> 0.025 | H83: =IF(D83="","",INDEX(Commutation!$L:$L,MATCH(Inputs!$B$7,Commutation!$A:$A,0))) -> 11.090171 | I83: =IF(D83="","",J82) -> 961.97302 | J83: =IF(D83>99,"",IF(E83=1,1000,MIN(1000,MAX(0,(INDEX(Commutation!$K:$K,MATCH(D84,Commutation!$A:$A,0))-(INDEX(Commutation!$K:$K,MATCH(Inputs!$B$7,Commutation!$A:$A,0))/((INDEX(Commutation!$H:$H,MATCH(Inputs!$B$7,Commutation!$A:$A,0))-INDEX(Commutation!$H:$H,MATCH(Inputs!$B$8,Commutation!$A:$A,0)))/INDEX(Commutation!$F:$F,MATCH(Inputs!$B$7,Commutation!$A:$A,0))))*MAX(0,(INDEX(Commutation!$H:$H,MATCH(D84,Commutation!$A:$A,0))-INDEX(Commutation!$H:$H,MATCH(Inputs!$B$8,Commutation!$A:$A,0)))/INDEX(Commutation!$F:$F,MATCH(D84,Commutation!$A:$A,0))))*1000)))) -> 969.05818 | K83: =IF(Inputs!$B$7+82-1>MAX(MORTALITY!$A:$A),"",IFERROR(J83,0)) -> 969.05818 | M83: =IF(A83="","",IF(E83=1,1000,IFERROR(((I83+IF(C83<=Inputs!$B$8,$H$2,0))*(1+G83)-E83*1000)/F83,0))) -> 969.05818
A84: =IF(D84>100,"",Inputs!$B$4) -> 34 | B84: =IF(D84>100,"",Inputs!$B$7) -> 16 | C84: =IFERROR(IF(Inputs!$B$7+C83+1>=100,"",C83+1),"") -> 82 | D84: =IFERROR(IF(Inputs!$B$7+C84>=100,"",Inputs!$B$7+C84),"") -> 98 | E84: =IF(D84="","",INDEX(MORTALITY!$B:$B,MATCH(D84,MORTALITY!$A:$A,0))) -> 0.72467 | F84: =IF(D84="","",1-E84) -> 0.27533 | G84: =IF(D84="","",Inputs!$B$23) -> 0.025 | H84: =IF(D84="","",INDEX(Commutation!$L:$L,MATCH(Inputs!$B$7,Commutation!$A:$A,0))) -> 11.090171 | I84: =IF(D84="","",J83) -> 969.05818 | J84: =IF(D84>99,"",IF(E84=1,1000,MIN(1000,MAX(0,(INDEX(Commutation!$K:$K,MATCH(D85,Commutation!$A:$A,0))-(INDEX(Commutation!$K:$K,MATCH(Inputs!$B$7,Commutation!$A:$A,0))/((INDEX(Commutation!$H:$H,MATCH(Inputs!$B$7,Commutation!$A:$A,0))-INDEX(Commutation!$H:$H,MATCH(Inputs!$B$8,Commutation!$A:$A,0)))/INDEX(Commutation!$F:$F,MATCH(Inputs!$B$7,Commutation!$A:$A,0))))*MAX(0,(INDEX(Commutation!$H:$H,MATCH(D85,Commutation!$A:$A,0))-INDEX(Commutation!$H:$H,MATCH(Inputs!$B$8,Commutation!$A:$A,0)))/INDEX(Commutation!$F:$F,MATCH(D85,Commutation!$A:$A,0))))*1000)))) -> 975.60976 | K84: =IF(Inputs!$B$7+83-1>MAX(MORTALITY!$A:$A),"",IFERROR(J84,0)) -> 975.60976 | M84: =IF(A84="","",IF(E84=1,1000,IFERROR(((I84+IF(C84<=Inputs!$B$8,$H$2,0))*(1+G84)-E84*1000)/F84,0))) -> 975.60976
A85: =IF(D85>100,"",Inputs!$B$4) -> 34 | B85: =IF(D85>100,"",Inputs!$B$7) -> 16 | C85: =IFERROR(IF(Inputs!$B$7+C84+1>=100,"",C84+1),"") -> 83 | D85: =IFERROR(IF(Inputs!$B$7+C85>=100,"",Inputs!$B$7+C85),"") -> 99 | E85: =IF(D85="","",INDEX(MORTALITY!$B:$B,MATCH(D85,MORTALITY!$A:$A,0))) -> 1 | F85: =IF(D85="","",1-E85) -> 0 | G85: =IF(D85="","",Inputs!$B$23) -> 0.025 | H85: =IF(D85="","",INDEX(Commutation!$L:$L,MATCH(Inputs!$B$7,Commutation!$A:$A,0))) -> 11.090171 | I85: =IF(D85="","",J84) -> 975.60976 | J85: =IF(D85>99,"",IF(E85=1,1000,MIN(1000,MAX(0,(INDEX(Commutation!$K:$K,MATCH(D86,Commutation!$A:$A,0))-(INDEX(Commutation!$K:$K,MATCH(Inputs!$B$7,Commutation!$A:$A,0))/((INDEX(Commutation!$H:$H,MATCH(Inputs!$B$7,Commutation!$A:$A,0))-INDEX(Commutation!$H:$H,MATCH(Inputs!$B$8,Commutation!$A:$A,0)))/INDEX(Commutation!$F:$F,MATCH(Inputs!$B$7,Commutation!$A:$A,0))))*MAX(0,(INDEX(Commutation!$H:$H,MATCH(D86,Commutation!$A:$A,0))-INDEX(Commutation!$H:$H,MATCH(Inputs!$B$8,Commutation!$A:$A,0)))/INDEX(Commutation!$F:$F,MATCH(D86,Commutation!$A:$A,0))))*1000)))) -> 1000 | K85: =IF(Inputs!$B$7+84-1>MAX(MORTALITY!$A:$A),"",IFERROR(J85,0)) -> 1000 | M85: =IF(A85="","",IF(E85=1,1000,IFERROR(((I85+IF(C85<=Inputs!$B$8,$H$2,0))*(1+G85)-E85*1000)/F85,0))) -> 1000
A86: =IF(D86>100,"",Inputs!$B$4) | B86: =IF(D86>100,"",Inputs!$B$7) | C86: =IFERROR(IF(Inputs!$B$7+C85+1>=100,"",C85+1),"") | D86: =IFERROR(IF(Inputs!$B$7+C86>=100,"",Inputs!$B$7+C86),"") | E86: =IF(D86="","",INDEX(MORTALITY!$B:$B,MATCH(D86,MORTALITY!$A:$A,0))) | F86: =IF(D86="","",1-E86) | G86: =IF(D86="","",Inputs!$B$23) | H86: =IF(D86="","",INDEX(Commutation!$L:$L,MATCH(Inputs!$B$7,Commutation!$A:$A,0))) | I86: =IF(D86="","",J85) | J86: =IF(D86>99,"",IF(E86=1,1000,MIN(1000,MAX(0,(INDEX(Commutation!$K:$K,MATCH(D87,Commutation!$A:$A,0))-(INDEX(Commutation!$K:$K,MATCH(Inputs!$B$7,Commutation!$A:$A,0))/((INDEX(Commutation!$H:$H,MATCH(Inputs!$B$7,Commutation!$A:$A,0))-INDEX(Commutation!$H:$H,MATCH(Inputs!$B$8,Commutation!$A:$A,0)))/INDEX(Commutation!$F:$F,MATCH(Inputs!$B$7,Commutation!$A:$A,0))))*MAX(0,(INDEX(Commutation!$H:$H,MATCH(D87,Commutation!$A:$A,0))-INDEX(Commutation!$H:$H,MATCH(Inputs!$B$8,Commutation!$A:$A,0)))/INDEX(Commutation!$F:$F,MATCH(D87,Commutation!$A:$A,0))))*1000)))) | K86: =IF(Inputs!$B$7+85-1>MAX(MORTALITY!$A:$A),"",IFERROR(J86,0)) | M86: =IF(A86="","",IF(E86=1,1000,IFERROR(((I86+IF(C86<=Inputs!$B$8,$H$2,0))*(1+G86)-E86*1000)/F86,0)))
A87: =IF(D87>100,"",Inputs!$B$4) | B87: =IF(D87>100,"",Inputs!$B$7) | C87: =IFERROR(IF(Inputs!$B$7+C86+1>=100,"",C86+1),"") | D87: =IFERROR(IF(Inputs!$B$7+C87>=100,"",Inputs!$B$7+C87),"") | E87: =IF(D87="","",INDEX(MORTALITY!$B:$B,MATCH(D87,MORTALITY!$A:$A,0))) | F87: =IF(D87="","",1-E87) | G87: =IF(D87="","",Inputs!$B$23) | H87: =IF(D87="","",INDEX(Commutation!$L:$L,MATCH(Inputs!$B$7,Commutation!$A:$A,0))) | I87: =IF(D87="","",J86) | J87: =IF(D87>99,"",IF(E87=1,1000,MIN(1000,MAX(0,(INDEX(Commutation!$K:$K,MATCH(D88,Commutation!$A:$A,0))-(INDEX(Commutation!$K:$K,MATCH(Inputs!$B$7,Commutation!$A:$A,0))/((INDEX(Commutation!$H:$H,MATCH(Inputs!$B$7,Commutation!$A:$A,0))-INDEX(Commutation!$H:$H,MATCH(Inputs!$B$8,Commutation!$A:$A,0)))/INDEX(Commutation!$F:$F,MATCH(Inputs!$B$7,Commutation!$A:$A,0))))*MAX(0,(INDEX(Commutation!$H:$H,MATCH(D88,Commutation!$A:$A,0))-INDEX(Commutation!$H:$H,MATCH(Inputs!$B$8,Commutation!$A:$A,0)))/INDEX(Commutation!$F:$F,MATCH(D88,Commutation!$A:$A,0))))*1000)))) | K87: =IF(Inputs!$B$7+86-1>MAX(MORTALITY!$A:$A),"",IFERROR(J87,0)) | M87: =IF(A87="","",IF(E87=1,1000,IFERROR(((I87+IF(C87<=Inputs!$B$8,$H$2,0))*(1+G87)-E87*1000)/F87,0)))
A88: =IF(D88>100,"",Inputs!$B$4) | B88: =IF(D88>100,"",Inputs!$B$7) | C88: =IFERROR(IF(Inputs!$B$7+C87+1>=100,"",C87+1),"") | D88: =IFERROR(IF(Inputs!$B$7+C88>=100,"",Inputs!$B$7+C88),"") | E88: =IF(D88="","",INDEX(MORTALITY!$B:$B,MATCH(D88,MORTALITY!$A:$A,0))) | F88: =IF(D88="","",1-E88) | G88: =IF(D88="","",Inputs!$B$23) | H88: =IF(D88="","",INDEX(Commutation!$L:$L,MATCH(Inputs!$B$7,Commutation!$A:$A,0))) | I88: =IF(D88="","",J87) | J88: =IF(D88>99,"",IF(E88=1,1000,MIN(1000,MAX(0,(INDEX(Commutation!$K:$K,MATCH(D89,Commutation!$A:$A,0))-(INDEX(Commutation!$K:$K,MATCH(Inputs!$B$7,Commutation!$A:$A,0))/((INDEX(Commutation!$H:$H,MATCH(Inputs!$B$7,Commutation!$A:$A,0))-INDEX(Commutation!$H:$H,MATCH(Inputs!$B$8,Commutation!$A:$A,0)))/INDEX(Commutation!$F:$F,MATCH(Inputs!$B$7,Commutation!$A:$A,0))))*MAX(0,(INDEX(Commutation!$H:$H,MATCH(D89,Commutation!$A:$A,0))-INDEX(Commutation!$H:$H,MATCH(Inputs!$B$8,Commutation!$A:$A,0)))/INDEX(Commutation!$F:$F,MATCH(D89,Commutation!$A:$A,0))))*1000)))) | K88: =IF(Inputs!$B$7+87-1>MAX(MORTALITY!$A:$A),"",IFERROR(J88,0)) | M88: =IF(A88="","",IF(E88=1,1000,IFERROR(((I88+IF(C88<=Inputs!$B$8,$H$2,0))*(1+G88)-E88*1000)/F88,0)))
A89: =IF(D89>100,"",Inputs!$B$4) | B89: =IF(D89>100,"",Inputs!$B$7) | C89: =IFERROR(IF(Inputs!$B$7+C88+1>=100,"",C88+1),"") | D89: =IFERROR(IF(Inputs!$B$7+C89>=100,"",Inputs!$B$7+C89),"") | E89: =IF(D89="","",INDEX(MORTALITY!$B:$B,MATCH(D89,MORTALITY!$A:$A,0))) | F89: =IF(D89="","",1-E89) | G89: =IF(D89="","",Inputs!$B$23) | H89: =IF(D89="","",INDEX(Commutation!$L:$L,MATCH(Inputs!$B$7,Commutation!$A:$A,0))) | I89: =IF(D89="","",J88) | J89: =IF(D89>99,"",IF(E89=1,1000,MIN(1000,MAX(0,(INDEX(Commutation!$K:$K,MATCH(D90,Commutation!$A:$A,0))-(INDEX(Commutation!$K:$K,MATCH(Inputs!$B$7,Commutation!$A:$A,0))/((INDEX(Commutation!$H:$H,MATCH(Inputs!$B$7,Commutation!$A:$A,0))-INDEX(Commutation!$H:$H,MATCH(Inputs!$B$8,Commutation!$A:$A,0)))/INDEX(Commutation!$F:$F,MATCH(Inputs!$B$7,Commutation!$A:$A,0))))*MAX(0,(INDEX(Commutation!$H:$H,MATCH(D90,Commutation!$A:$A,0))-INDEX(Commutation!$H:$H,MATCH(Inputs!$B$8,Commutation!$A:$A,0)))/INDEX(Commutation!$F:$F,MATCH(D90,Commutation!$A:$A,0))))*1000)))) | K89: =IF(Inputs!$B$7+88-1>MAX(MORTALITY!$A:$A),"",IFERROR(J89,0)) | M89: =IF(A89="","",IF(E89=1,1000,IFERROR(((I89+IF(C89<=Inputs!$B$8,$H$2,0))*(1+G89)-E89*1000)/F89,0)))
A90: =IF(D90>100,"",Inputs!$B$4) | B90: =IF(D90>100,"",Inputs!$B$7) | C90: =IFERROR(IF(Inputs!$B$7+C89+1>=100,"",C89+1),"") | D90: =IFERROR(IF(Inputs!$B$7+C90>=100,"",Inputs!$B$7+C90),"") | E90: =IF(D90="","",INDEX(MORTALITY!$B:$B,MATCH(D90,MORTALITY!$A:$A,0))) | F90: =IF(D90="","",1-E90) | G90: =IF(D90="","",Inputs!$B$23) | H90: =IF(D90="","",INDEX(Commutation!$L:$L,MATCH(Inputs!$B$7,Commutation!$A:$A,0))) | I90: =IF(D90="","",J89) | J90: =IF(D90>99,"",IF(E90=1,1000,MIN(1000,MAX(0,(INDEX(Commutation!$K:$K,MATCH(D91,Commutation!$A:$A,0))-(INDEX(Commutation!$K:$K,MATCH(Inputs!$B$7,Commutation!$A:$A,0))/((INDEX(Commutation!$H:$H,MATCH(Inputs!$B$7,Commutation!$A:$A,0))-INDEX(Commutation!$H:$H,MATCH(Inputs!$B$8,Commutation!$A:$A,0)))/INDEX(Commutation!$F:$F,MATCH(Inputs!$B$7,Commutation!$A:$A,0))))*MAX(0,(INDEX(Commutation!$H:$H,MATCH(D91,Commutation!$A:$A,0))-INDEX(Commutation!$H:$H,MATCH(Inputs!$B$8,Commutation!$A:$A,0)))/INDEX(Commutation!$F:$F,MATCH(D91,Commutation!$A:$A,0))))*1000)))) | K90: =IF(Inputs!$B$7+89-1>MAX(MORTALITY!$A:$A),"",IFERROR(J90,0)) | M90: =IF(A90="","",IF(E90=1,1000,IFERROR(((I90+IF(C90<=Inputs!$B$8,$H$2,0))*(1+G90)-E90*1000)/F90,0)))
A91: =IF(D91>100,"",Inputs!$B$4) | B91: =IF(D91>100,"",Inputs!$B$7) | C91: =IFERROR(IF(Inputs!$B$7+C90+1>=100,"",C90+1),"") | D91: =IFERROR(IF(Inputs!$B$7+C91>=100,"",Inputs!$B$7+C91),"") | E91: =IF(D91="","",INDEX(MORTALITY!$B:$B,MATCH(D91,MORTALITY!$A:$A,0))) | F91: =IF(D91="","",1-E91) | G91: =IF(D91="","",Inputs!$B$23) | H91: =IF(D91="","",INDEX(Commutation!$L:$L,MATCH(Inputs!$B$7,Commutation!$A:$A,0))) | I91: =IF(D91="","",J90) | J91: =IF(D91>99,"",IF(E91=1,1000,MIN(1000,MAX(0,(INDEX(Commutation!$K:$K,MATCH(D92,Commutation!$A:$A,0))-(INDEX(Commutation!$K:$K,MATCH(Inputs!$B$7,Commutation!$A:$A,0))/((INDEX(Commutation!$H:$H,MATCH(Inputs!$B$7,Commutation!$A:$A,0))-INDEX(Commutation!$H:$H,MATCH(Inputs!$B$8,Commutation!$A:$A,0)))/INDEX(Commutation!$F:$F,MATCH(Inputs!$B$7,Commutation!$A:$A,0))))*MAX(0,(INDEX(Commutation!$H:$H,MATCH(D92,Commutation!$A:$A,0))-INDEX(Commutation!$H:$H,MATCH(Inputs!$B$8,Commutation!$A:$A,0)))/INDEX(Commutation!$F:$F,MATCH(D92,Commutation!$A:$A,0))))*1000)))) | K91: =IF(Inputs!$B$7+90-1>MAX(MORTALITY!$A:$A),"",IFERROR(J91,0)) | M91: =IF(A91="","",IF(E91=1,1000,IFERROR(((I91+IF(C91<=Inputs!$B$8,$H$2,0))*(1+G91)-E91*1000)/F91,0)))
A92: =IF(D92>100,"",Inputs!$B$4) | B92: =IF(D92>100,"",Inputs!$B$7) | C92: =IFERROR(IF(Inputs!$B$7+C91+1>=100,"",C91+1),"") | D92: =IFERROR(IF(Inputs!$B$7+C92>=100,"",Inputs!$B$7+C92),"") | E92: =IF(D92="","",INDEX(MORTALITY!$B:$B,MATCH(D92,MORTALITY!$A:$A,0))) | F92: =IF(D92="","",1-E92) | G92: =IF(D92="","",Inputs!$B$23) | H92: =IF(D92="","",INDEX(Commutation!$L:$L,MATCH(Inputs!$B$7,Commutation!$A:$A,0))) | I92: =IF(D92="","",J91) | J92: =IF(D92>99,"",IF(E92=1,1000,MIN(1000,MAX(0,(INDEX(Commutation!$K:$K,MATCH(D93,Commutation!$A:$A,0))-(INDEX(Commutation!$K:$K,MATCH(Inputs!$B$7,Commutation!$A:$A,0))/((INDEX(Commutation!$H:$H,MATCH(Inputs!$B$7,Commutation!$A:$A,0))-INDEX(Commutation!$H:$H,MATCH(Inputs!$B$8,Commutation!$A:$A,0)))/INDEX(Commutation!$F:$F,MATCH(Inputs!$B$7,Commutation!$A:$A,0))))*MAX(0,(INDEX(Commutation!$H:$H,MATCH(D93,Commutation!$A:$A,0))-INDEX(Commutation!$H:$H,MATCH(Inputs!$B$8,Commutation!$A:$A,0)))/INDEX(Commutation!$F:$F,MATCH(D93,Commutation!$A:$A,0))))*1000)))) | K92: =IF(Inputs!$B$7+91-1>MAX(MORTALITY!$A:$A),"",IFERROR(J92,0)) | M92: =IF(A92="","",IF(E92=1,1000,IFERROR(((I92+IF(C92<=Inputs!$B$8,$H$2,0))*(1+G92)-E92*1000)/F92,0)))
A93: =IF(D93>100,"",Inputs!$B$4) | B93: =IF(D93>100,"",Inputs!$B$7) | C93: =IFERROR(IF(Inputs!$B$7+C92+1>=100,"",C92+1),"") | D93: =IFERROR(IF(Inputs!$B$7+C93>=100,"",Inputs!$B$7+C93),"") | E93: =IF(D93="","",INDEX(MORTALITY!$B:$B,MATCH(D93,MORTALITY!$A:$A,0))) | F93: =IF(D93="","",1-E93) | G93: =IF(D93="","",Inputs!$B$23) | H93: =IF(D93="","",INDEX(Commutation!$L:$L,MATCH(Inputs!$B$7,Commutation!$A:$A,0))) | I93: =IF(D93="","",J92) | J93: =IF(D93>99,"",IF(E93=1,1000,MIN(1000,MAX(0,(INDEX(Commutation!$K:$K,MATCH(D94,Commutation!$A:$A,0))-(INDEX(Commutation!$K:$K,MATCH(Inputs!$B$7,Commutation!$A:$A,0))/((INDEX(Commutation!$H:$H,MATCH(Inputs!$B$7,Commutation!$A:$A,0))-INDEX(Commutation!$H:$H,MATCH(Inputs!$B$8,Commutation!$A:$A,0)))/INDEX(Commutation!$F:$F,MATCH(Inputs!$B$7,Commutation!$A:$A,0))))*MAX(0,(INDEX(Commutation!$H:$H,MATCH(D94,Commutation!$A:$A,0))-INDEX(Commutation!$H:$H,MATCH(Inputs!$B$8,Commutation!$A:$A,0)))/INDEX(Commutation!$F:$F,MATCH(D94,Commutation!$A:$A,0))))*1000)))) | K93: =IF(Inputs!$B$7+92-1>MAX(MORTALITY!$A:$A),"",IFERROR(J93,0)) | M93: =IF(A93="","",IF(E93=1,1000,IFERROR(((I93+IF(C93<=Inputs!$B$8,$H$2,0))*(1+G93)-E93*1000)/F93,0)))
A94: =IF(D94>100,"",Inputs!$B$4) | B94: =IF(D94>100,"",Inputs!$B$7) | C94: =IFERROR(IF(Inputs!$B$7+C93+1>=100,"",C93+1),"") | D94: =IFERROR(IF(Inputs!$B$7+C94>=100,"",Inputs!$B$7+C94),"") | E94: =IF(D94="","",INDEX(MORTALITY!$B:$B,MATCH(D94,MORTALITY!$A:$A,0))) | F94: =IF(D94="","",1-E94) | G94: =IF(D94="","",Inputs!$B$23) | H94: =IF(D94="","",INDEX(Commutation!$L:$L,MATCH(Inputs!$B$7,Commutation!$A:$A,0))) | I94: =IF(D94="","",J93) | J94: =IF(D94>99,"",IF(E94=1,1000,MIN(1000,MAX(0,(INDEX(Commutation!$K:$K,MATCH(D95,Commutation!$A:$A,0))-(INDEX(Commutation!$K:$K,MATCH(Inputs!$B$7,Commutation!$A:$A,0))/((INDEX(Commutation!$H:$H,MATCH(Inputs!$B$7,Commutation!$A:$A,0))-INDEX(Commutation!$H:$H,MATCH(Inputs!$B$8,Commutation!$A:$A,0)))/INDEX(Commutation!$F:$F,MATCH(Inputs!$B$7,Commutation!$A:$A,0))))*MAX(0,(INDEX(Commutation!$H:$H,MATCH(D95,Commutation!$A:$A,0))-INDEX(Commutation!$H:$H,MATCH(Inputs!$B$8,Commutation!$A:$A,0)))/INDEX(Commutation!$F:$F,MATCH(D95,Commutation!$A:$A,0))))*1000)))) | K94: =IF(Inputs!$B$7+93-1>MAX(MORTALITY!$A:$A),"",IFERROR(J94,0)) | M94: =IF(A94="","",IF(E94=1,1000,IFERROR(((I94+IF(C94<=Inputs!$B$8,$H$2,0))*(1+G94)-E94*1000)/F94,0)))
A95: =IF(D95>100,"",Inputs!$B$4) | B95: =IF(D95>100,"",Inputs!$B$7) | C95: =IFERROR(IF(Inputs!$B$7+C94+1>=100,"",C94+1),"") | D95: =IFERROR(IF(Inputs!$B$7+C95>=100,"",Inputs!$B$7+C95),"") | E95: =IF(D95="","",INDEX(MORTALITY!$B:$B,MATCH(D95,MORTALITY!$A:$A,0))) | F95: =IF(D95="","",1-E95) | G95: =IF(D95="","",Inputs!$B$23) | H95: =IF(D95="","",INDEX(Commutation!$L:$L,MATCH(Inputs!$B$7,Commutation!$A:$A,0))) | I95: =IF(D95="","",J94) | J95: =IF(D95>99,"",IF(E95=1,1000,MIN(1000,MAX(0,(INDEX(Commutation!$K:$K,MATCH(D96,Commutation!$A:$A,0))-(INDEX(Commutation!$K:$K,MATCH(Inputs!$B$7,Commutation!$A:$A,0))/((INDEX(Commutation!$H:$H,MATCH(Inputs!$B$7,Commutation!$A:$A,0))-INDEX(Commutation!$H:$H,MATCH(Inputs!$B$8,Commutation!$A:$A,0)))/INDEX(Commutation!$F:$F,MATCH(Inputs!$B$7,Commutation!$A:$A,0))))*MAX(0,(INDEX(Commutation!$H:$H,MATCH(D96,Commutation!$A:$A,0))-INDEX(Commutation!$H:$H,MATCH(Inputs!$B$8,Commutation!$A:$A,0)))/INDEX(Commutation!$F:$F,MATCH(D96,Commutation!$A:$A,0))))*1000)))) | K95: =IF(Inputs!$B$7+94-1>MAX(MORTALITY!$A:$A),"",IFERROR(J95,0)) | M95: =IF(A95="","",IF(E95=1,1000,IFERROR(((I95+IF(C95<=Inputs!$B$8,$H$2,0))*(1+G95)-E95*1000)/F95,0)))
A96: =IF(D96>100,"",Inputs!$B$4) | B96: =IF(D96>100,"",Inputs!$B$7) | C96: =IFERROR(IF(Inputs!$B$7+C95+1>=100,"",C95+1),"") | D96: =IFERROR(IF(Inputs!$B$7+C96>=100,"",Inputs!$B$7+C96),"") | E96: =IF(D96="","",INDEX(MORTALITY!$B:$B,MATCH(D96,MORTALITY!$A:$A,0))) | F96: =IF(D96="","",1-E96) | G96: =IF(D96="","",Inputs!$B$23) | H96: =IF(D96="","",INDEX(Commutation!$L:$L,MATCH(Inputs!$B$7,Commutation!$A:$A,0))) | I96: =IF(D96="","",J95) | J96: =IF(D96>99,"",IF(E96=1,1000,MIN(1000,MAX(0,(INDEX(Commutation!$K:$K,MATCH(D97,Commutation!$A:$A,0))-(INDEX(Commutation!$K:$K,MATCH(Inputs!$B$7,Commutation!$A:$A,0))/((INDEX(Commutation!$H:$H,MATCH(Inputs!$B$7,Commutation!$A:$A,0))-INDEX(Commutation!$H:$H,MATCH(Inputs!$B$8,Commutation!$A:$A,0)))/INDEX(Commutation!$F:$F,MATCH(Inputs!$B$7,Commutation!$A:$A,0))))*MAX(0,(INDEX(Commutation!$H:$H,MATCH(D97,Commutation!$A:$A,0))-INDEX(Commutation!$H:$H,MATCH(Inputs!$B$8,Commutation!$A:$A,0)))/INDEX(Commutation!$F:$F,MATCH(D97,Commutation!$A:$A,0))))*1000)))) | K96: =IF(Inputs!$B$7+95-1>MAX(MORTALITY!$A:$A),"",IFERROR(J96,0)) | M96: =IF(A96="","",IF(E96=1,1000,IFERROR(((I96+IF(C96<=Inputs!$B$8,$H$2,0))*(1+G96)-E96*1000)/F96,0)))
A97: =IF(D97>100,"",Inputs!$B$4) | B97: =IF(D97>100,"",Inputs!$B$7) | C97: =IFERROR(IF(Inputs!$B$7+C96+1>=100,"",C96+1),"") | D97: =IFERROR(IF(Inputs!$B$7+C97>=100,"",Inputs!$B$7+C97),"") | E97: =IF(D97="","",INDEX(MORTALITY!$B:$B,MATCH(D97,MORTALITY!$A:$A,0))) | F97: =IF(D97="","",1-E97) | G97: =IF(D97="","",Inputs!$B$23) | H97: =IF(D97="","",INDEX(Commutation!$L:$L,MATCH(Inputs!$B$7,Commutation!$A:$A,0))) | I97: =IF(D97="","",J96) | J97: =IF(D97>99,"",IF(E97=1,1000,MIN(1000,MAX(0,(INDEX(Commutation!$K:$K,MATCH(D98,Commutation!$A:$A,0))-(INDEX(Commutation!$K:$K,MATCH(Inputs!$B$7,Commutation!$A:$A,0))/((INDEX(Commutation!$H:$H,MATCH(Inputs!$B$7,Commutation!$A:$A,0))-INDEX(Commutation!$H:$H,MATCH(Inputs!$B$8,Commutation!$A:$A,0)))/INDEX(Commutation!$F:$F,MATCH(Inputs!$B$7,Commutation!$A:$A,0))))*MAX(0,(INDEX(Commutation!$H:$H,MATCH(D98,Commutation!$A:$A,0))-INDEX(Commutation!$H:$H,MATCH(Inputs!$B$8,Commutation!$A:$A,0)))/INDEX(Commutation!$F:$F,MATCH(D98,Commutation!$A:$A,0))))*1000)))) | K97: =IF(Inputs!$B$7+96-1>MAX(MORTALITY!$A:$A),"",IFERROR(J97,0)) | M97: =IF(A97="","",IF(E97=1,1000,IFERROR(((I97+IF(C97<=Inputs!$B$8,$H$2,0))*(1+G97)-E97*1000)/F97,0)))
A98: =IF(D98>100,"",Inputs!$B$4) | B98: =IF(D98>100,"",Inputs!$B$7) | C98: =IFERROR(IF(Inputs!$B$7+C97+1>=100,"",C97+1),"") | D98: =IFERROR(IF(Inputs!$B$7+C98>=100,"",Inputs!$B$7+C98),"") | E98: =IF(D98="","",INDEX(MORTALITY!$B:$B,MATCH(D98,MORTALITY!$A:$A,0))) | F98: =IF(D98="","",1-E98) | G98: =IF(D98="","",Inputs!$B$23) | H98: =IF(D98="","",INDEX(Commutation!$L:$L,MATCH(Inputs!$B$7,Commutation!$A:$A,0))) | I98: =IF(D98="","",J97) | J98: =IF(D98>99,"",IF(E98=1,1000,MIN(1000,MAX(0,(INDEX(Commutation!$K:$K,MATCH(D99,Commutation!$A:$A,0))-(INDEX(Commutation!$K:$K,MATCH(Inputs!$B$7,Commutation!$A:$A,0))/((INDEX(Commutation!$H:$H,MATCH(Inputs!$B$7,Commutation!$A:$A,0))-INDEX(Commutation!$H:$H,MATCH(Inputs!$B$8,Commutation!$A:$A,0)))/INDEX(Commutation!$F:$F,MATCH(Inputs!$B$7,Commutation!$A:$A,0))))*MAX(0,(INDEX(Commutation!$H:$H,MATCH(D99,Commutation!$A:$A,0))-INDEX(Commutation!$H:$H,MATCH(Inputs!$B$8,Commutation!$A:$A,0)))/INDEX(Commutation!$F:$F,MATCH(D99,Commutation!$A:$A,0))))*1000)))) | K98: =IF(Inputs!$B$7+97-1>MAX(MORTALITY!$A:$A),"",IFERROR(J98,0)) | M98: =IF(A98="","",IF(E98=1,1000,IFERROR(((I98+IF(C98<=Inputs!$B$8,$H$2,0))*(1+G98)-E98*1000)/F98,0)))
A99: =IF(D99>100,"",Inputs!$B$4) | B99: =IF(D99>100,"",Inputs!$B$7) | C99: =IFERROR(IF(Inputs!$B$7+C98+1>=100,"",C98+1),"") | D99: =IFERROR(IF(Inputs!$B$7+C99>=100,"",Inputs!$B$7+C99),"") | E99: =IF(D99="","",INDEX(MORTALITY!$B:$B,MATCH(D99,MORTALITY!$A:$A,0))) | F99: =IF(D99="","",1-E99) | G99: =IF(D99="","",Inputs!$B$23) | H99: =IF(D99="","",INDEX(Commutation!$L:$L,MATCH(Inputs!$B$7,Commutation!$A:$A,0))) | I99: =IF(D99="","",J98) | J99: =IF(D99>99,"",IF(E99=1,1000,MIN(1000,MAX(0,(INDEX(Commutation!$K:$K,MATCH(D100,Commutation!$A:$A,0))-(INDEX(Commutation!$K:$K,MATCH(Inputs!$B$7,Commutation!$A:$A,0))/((INDEX(Commutation!$H:$H,MATCH(Inputs!$B$7,Commutation!$A:$A,0))-INDEX(Commutation!$H:$H,MATCH(Inputs!$B$8,Commutation!$A:$A,0)))/INDEX(Commutation!$F:$F,MATCH(Inputs!$B$7,Commutation!$A:$A,0))))*MAX(0,(INDEX(Commutation!$H:$H,MATCH(D100,Commutation!$A:$A,0))-INDEX(Commutation!$H:$H,MATCH(Inputs!$B$8,Commutation!$A:$A,0)))/INDEX(Commutation!$F:$F,MATCH(D100,Commutation!$A:$A,0))))*1000)))) | K99: =IF(Inputs!$B$7+98-1>MAX(MORTALITY!$A:$A),"",IFERROR(J99,0)) | M99: =IF(A99="","",IF(E99=1,1000,IFERROR(((I99+IF(C99<=Inputs!$B$8,$H$2,0))*(1+G99)-E99*1000)/F99,0)))
A100: =IF(D100>100,"",Inputs!$B$4) | B100: =IF(D100>100,"",Inputs!$B$7) | C100: =IFERROR(IF(Inputs!$B$7+C99+1>=100,"",C99+1),"") | D100: =IFERROR(IF(Inputs!$B$7+C100>=100,"",Inputs!$B$7+C100),"") | E100: =IF(D100="","",INDEX(MORTALITY!$B:$B,MATCH(D100,MORTALITY!$A:$A,0))) | F100: =IF(D100="","",1-E100) | G100: =IF(D100="","",Inputs!$B$23) | H100: =IF(D100="","",INDEX(Commutation!$L:$L,MATCH(Inputs!$B$7,Commutation!$A:$A,0))) | I100: =IF(D100="","",J99) | J100: =IF(D100>99,"",IF(E100=1,1000,MIN(1000,MAX(0,(INDEX(Commutation!$K:$K,MATCH(D101,Commutation!$A:$A,0))-(INDEX(Commutation!$K:$K,MATCH(Inputs!$B$7,Commutation!$A:$A,0))/((INDEX(Commutation!$H:$H,MATCH(Inputs!$B$7,Commutation!$A:$A,0))-INDEX(Commutation!$H:$H,MATCH(Inputs!$B$8,Commutation!$A:$A,0)))/INDEX(Commutation!$F:$F,MATCH(Inputs!$B$7,Commutation!$A:$A,0))))*MAX(0,(INDEX(Commutation!$H:$H,MATCH(D101,Commutation!$A:$A,0))-INDEX(Commutation!$H:$H,MATCH(Inputs!$B$8,Commutation!$A:$A,0)))/INDEX(Commutation!$F:$F,MATCH(D101,Commutation!$A:$A,0))))*1000)))) | K100: =IF(Inputs!$B$7+99-1>MAX(MORTALITY!$A:$A),"",IFERROR(J100,0)) | M100: =IF(A100="","",IF(E100=1,1000,IFERROR(((I100+IF(C100<=Inputs!$B$8,$H$2,0))*(1+G100)-E100*1000)/F100,0)))
...

Sheet PUA_TABLE
A3: Issue Age | B3: Duration | C3: Attained Age | D3: PUA SP per $1 SA (Ax) | E3: Dx | F3: Nx+1 | G3: Mx | H3: Beta (NLP/1000) | I3: PUA CVF per 1000 (Fackler)
A4: =IF(Inputs!$B$7+1-1>MAX(MORTALITY!$A:$A),"",Inputs!$B$7) -> 16 | B4: =IF(Inputs!$B$7+1-1>MAX(MORTALITY!$A:$A),"",1) -> 1 | C4: =IF(Inputs!$B$7+1-1>MAX(MORTALITY!$A:$A),"",Inputs!$B$7+1-1) -> 16 | D4: =IF(C4="","",INDEX(Commutation!$K:$K,MATCH(C4,Commutation!$A:$A,0))) -> 0.31257163 | E4: =IF(Inputs!$B$7+1-1>MAX(MORTALITY!$A:$A),"",IFERROR(INDEX(Commutation!$F:$F,MATCH(C4,Commutation!$A:$A,0)),0)) -> 6322101.7 | F4: =IF(Inputs!$B$7+1-1>MAX(MORTALITY!$A:$A),"",IFERROR(INDEX(Commutation!$H:$H,MATCH(C4+1,Commutation!$A:$A,0)),0)) -> 1.7186357e+08 | G4: =IF(Inputs!$B$7+1-1>MAX(MORTALITY!$A:$A),"",IFERROR(INDEX(Commutation!$I:$I,MATCH(C4,Commutation!$A:$A,0)),0)) -> 1976109.6 | H4: =IF(Inputs!$B$7+1-1>MAX(MORTALITY!$A:$A),"",IFERROR(1000*INDEX(Commutation!$I:$I,MATCH(Inputs!$B$7,Commutation!$A:$A,0))/INDEX(Commutation!$H:$H,MATCH(Inputs!$B$7,Commutation!$A:$A,0)),0)) -> 11.090171 | I4: =IF(Inputs!$B$7+1-1>MAX(MORTALITY!$A:$A),"",IFERROR((1000*G4-H4*F4)/E4,0)) -> 11.090171
A5: =IF(Inputs!$B$7+2-1>MAX(MORTALITY!$A:$A),"",Inputs!$B$7) -> 16 | B5: =IF(Inputs!$B$7+2-1>MAX(MORTALITY!$A:$A),"",2) -> 2 | C5: =IF(Inputs!$B$7+2-1>MAX(MORTALITY!$A:$A),"",Inputs!$B$7+2-1) -> 17 | D5: =IF(C5="","",INDEX(Commutation!$K:$K,MATCH(C5,Commutation!$A:$A,0))) -> 0.3188943 | E5: =IF(Inputs!$B$7+2-1>MAX(MORTALITY!$A:$A),"",IFERROR(INDEX(Commutation!$F:$F,MATCH(C5,Commutation!$A:$A,0)),0)) -> 6154396.4 | F5: =IF(Inputs!$B$7+2-1>MAX(MORTALITY!$A:$A),"",IFERROR(INDEX(Commutation!$H:$H,MATCH(C5+1,Commutation!$A:$A,0)),0)) -> 1.6570918e+08 | G5: =IF(Inputs!$B$7+2-1>MAX(MORTALITY!$A:$A),"",IFERROR(INDEX(Commutation!$I:$I,MATCH(C5,Commutation!$A:$A,0)),0)) -> 1962601.9 | H5: =IF(Inputs!$B$7+2-1>MAX(MORTALITY!$A:$A),"",IFERROR(1000*INDEX(Commutation!$I:$I,MATCH(Inputs!$B$7,Commutation!$A:$A,0))/INDEX(Commutation!$H:$H,MATCH(Inputs!$B$7,Commutation!$A:$A,0)),0)) -> 11.090171 | I5: =IF(Inputs!$B$7+2-1>MAX(MORTALITY!$A:$A),"",IFERROR((1000*G5-H5*F5)/E5,0)) -> 20.287739
A6: =IF(Inputs!$B$7+3-1>MAX(MORTALITY!$A:$A),"",Inputs!$B$7) -> 16 | B6: =IF(Inputs!$B$7+3-1>MAX(MORTALITY!$A:$A),"",3) -> 3 | C6: =IF(Inputs!$B$7+3-1>MAX(MORTALITY!$A:$A),"",Inputs!$B$7+3-1) -> 18 | D6: =IF(C6="","",INDEX(Commutation!$K:$K,MATCH(C6,Commutation!$A:$A,0))) -> 0.32534869 | E6: =IF(Inputs!$B$7+3-1>MAX(MORTALITY!$A:$A),"",IFERROR(INDEX(Commutation!$F:$F,MATCH(C6,Commutation!$A:$A,0)),0)) -> 5990779.6 | F6: =IF(Inputs!$B$7+3-1>MAX(MORTALITY!$A:$A),"",IFERROR(INDEX(Commutation!$H:$H,MATCH(C6+1,Commutation!$A:$A,0)),0)) -> 1.597184e+08 | G6: =IF(Inputs!$B$7+3-1>MAX(MORTALITY!$A:$A),"",IFERROR(INDEX(Commutation!$I:$I,MATCH(C6,Commutation!$A:$A,0)),0)) -> 1949092.3 | H6: =IF(Inputs!$B$7+3-1>MAX(MORTALITY!$A:$A),"",IFERROR(1000*INDEX(Commutation!$I:$I,MATCH(Inputs!$B$7,Commutation!$A:$A,0))/INDEX(Commutation!$H:$H,MATCH(Inputs!$B$7,Commutation!$A:$A,0)),0)) -> 11.090171 | I6: =IF(Inputs!$B$7+3-1>MAX(MORTALITY!$A:$A),"",IFERROR((1000*G6-H6*F6)/E6,0)) -> 29.676924
A7: =IF(Inputs!$B$7+4-1>MAX(MORTALITY!$A:$A),"",Inputs!$B$7) -> 16 | B7: =IF(Inputs!$B$7+4-1>MAX(MORTALITY!$A:$A),"",4) -> 4 | C7: =IF(Inputs!$B$7+4-1>MAX(MORTALITY!$A:$A),"",Inputs!$B$7+4-1) -> 19 | D7: =IF(C7="","",INDEX(Commutation!$K:$K,MATCH(C7,Commutation!$A:$A,0))) -> 0.33194588 | E7: =IF(Inputs!$B$7+4-1>MAX(MORTALITY!$A:$A),"",IFERROR(INDEX(Commutation!$F:$F,MATCH(C7,Commutation!$A:$A,0)),0)) -> 5831220.3 | F7: =IF(Inputs!$B$7+4-1>MAX(MORTALITY!$A:$A),"",IFERROR(INDEX(Commutation!$H:$H,MATCH(C7+1,Commutation!$A:$A,0)),0)) -> 1.5388718e+08 | G7: =IF(Inputs!$B$7+4-1>MAX(MORTALITY!$A:$A),"",IFERROR(INDEX(Commutation!$I:$I,MATCH(C7,Commutation!$A:$A,0)),0)) -> 1935649.6 | H7: =IF(Inputs!$B$7+4-1>MAX(MORTALITY!$A:$A),"",IFERROR(1000*INDEX(Commutation!$I:$I,MATCH(Inputs!$B$7,Commutation!$A:$A,0))/INDEX(Commutation!$H:$H,MATCH(Inputs!$B$7,Commutation!$A:$A,0)),0)) -> 11.090171 | I7: =IF(Inputs!$B$7+4-1>MAX(MORTALITY!$A:$A),"",IFERROR((1000*G7-H7*F7)/E7,0)) -> 39.273841
A8: =IF(Inputs!$B$7+5-1>MAX(MORTALITY!$A:$A),"",Inputs!$B$7) -> 16 | B8: =IF(Inputs!$B$7+5-1>MAX(MORTALITY!$A:$A),"",5) -> 5 | C8: =IF(Inputs!$B$7+5-1>MAX(MORTALITY!$A:$A),"",Inputs!$B$7+5-1) -> 20 | D8: =IF(C8="","",INDEX(Commutation!$K:$K,MATCH(C8,Commutation!$A:$A,0))) -> 0.3386772 | E8: =IF(Inputs!$B$7+5-1>MAX(MORTALITY!$A:$A),"",IFERROR(INDEX(Commutation!$F:$F,MATCH(C8,Commutation!$A:$A,0)),0)) -> 5675512.4 | F8: =IF(Inputs!$B$7+5-1>MAX(MORTALITY!$A:$A),"",IFERROR(INDEX(Commutation!$H:$H,MATCH(C8+1,Commutation!$A:$A,0)),0)) -> 1.4821167e+08 | G8: =IF(Inputs!$B$7+5-1>MAX(MORTALITY!$A:$A),"",IFERROR(INDEX(Commutation!$I:$I,MATCH(C8,Commutation!$A:$A,0)),0)) -> 1922166.6 | H8: =IF(Inputs!$B$7+5-1>MAX(MORTALITY!$A:$A),"",IFERROR(1000*INDEX(Commutation!$I:$I,MATCH(Inputs!$B$7,Commutation!$A:$A,0))/INDEX(Commutation!$H:$H,MATCH(Inputs!$B$7,Commutation!$A:$A,0)),0)) -> 11.090171 | I8: =IF(Inputs!$B$7+5-1>MAX(MORTALITY!$A:$A),"",IFERROR((1000*G8-H8*F8)/E8,0)) -> 49.06586
A9: =IF(Inputs!$B$7+6-1>MAX(MORTALITY!$A:$A),"",Inputs!$B$7) -> 16 | B9: =IF(Inputs!$B$7+6-1>MAX(MORTALITY!$A:$A),"",6) -> 6 | C9: =IF(Inputs!$B$7+6-1>MAX(MORTALITY!$A:$A),"",Inputs!$B$7+6-1) -> 21 | D9: =IF(C9="","",INDEX(Commutation!$K:$K,MATCH(C9,Commutation!$A:$A,0))) -> 0.34555382 | E9: =IF(Inputs!$B$7+6-1>MAX(MORTALITY!$A:$A),"",IFERROR(INDEX(Commutation!$F:$F,MATCH(C9,Commutation!$A:$A,0)),0)) -> 5523630.2 | F9: =IF(Inputs!$B$7+6-1>MAX(MORTALITY!$A:$A),"",IFERROR(INDEX(Commutation!$H:$H,MATCH(C9+1,Commutation!$A:$A,0)),0)) -> 1.4268804e+08 | G9: =IF(Inputs!$B$7+6-1>MAX(MORTALITY!$A:$A),"",IFERROR(INDEX(Commutation!$I:$I,MATCH(C9,Commutation!$A:$A,0)),0)) -> 1908711.5 | H9: =IF(Inputs!$B$7+6-1>MAX(MORTALITY!$A:$A),"",IFERROR(1000*INDEX(Commutation!$I:$I,MATCH(Inputs!$B$7,Commutation!$A:$A,0))/INDEX(Commutation!$H:$H,MATCH(Inputs!$B$7,Commutation!$A:$A,0)),0)) -> 11.090171 | I9: =IF(Inputs!$B$7+6-1>MAX(MORTALITY!$A:$A),"",IFERROR((1000*G9-H9*F9)/E9,0)) -> 59.069267
A10: =IF(Inputs!$B$7+7-1>MAX(MORTALITY!$A:$A),"",Inputs!$B$7) -> 16 | B10: =IF(Inputs!$B$7+7-1>MAX(MORTALITY!$A:$A),"",7) -> 7 | C10: =IF(Inputs!$B$7+7-1>MAX(MORTALITY!$A:$A),"",Inputs!$B$7+7-1) -> 22 | D10: =IF(C10="","",INDEX(Commutation!$K:$K,MATCH(C10,Commutation!$A:$A,0))) -> 0.35256761 | E10: =IF(Inputs!$B$7+7-1>MAX(MORTALITY!$A:$A),"",IFERROR(INDEX(Commutation!$F:$F,MATCH(C10,Commutation!$A:$A,0)),0)) -> 5375381.4 | F10: =IF(Inputs!$B$7+7-1>MAX(MORTALITY!$A:$A),"",IFERROR(INDEX(Commutation!$H:$H,MATCH(C10+1,Commutation!$A:$A,0)),0)) -> 1.3731265e+08 | G10: =IF(Inputs!$B$7+7-1>MAX(MORTALITY!$A:$A),"",IFERROR(INDEX(Commutation!$I:$I,MATCH(C10,Commutation!$A:$A,0)),0)) -> 1895185.4 | H10: =IF(Inputs!$B$7+7-1>MAX(MORTALITY!$A:$A),"",IFERROR(1000*INDEX(Commutation!$I:$I,MATCH(Inputs!$B$7,Commutation!$A:$A,0))/INDEX(Commutation!$H:$H,MATCH(Inputs!$B$7,Commutation!$A:$A,0)),0)) -> 11.090171 | I10: =IF(Inputs!$B$7+7-1>MAX(MORTALITY!$A:$A),"",IFERROR((1000*G10-H10*F10)/E10,0)) -> 69.272207
A11: =IF(Inputs!$B$7+8-1>MAX(MORTALITY!$A:$A),"",Inputs!$B$7) -> 16 | B11: =IF(Inputs!$B$7+8-1>MAX(MORTALITY!$A:$A),"",8) -> 8 | C11: =IF(Inputs!$B$7+8-1>MAX(MORTALITY!$A:$A),"",Inputs!$B$7+8-1) -> 23 | D11: =IF(C11="","",INDEX(Commutation!$K:$K,MATCH(C11,Commutation!$A:$A,0))) -> 0.35972349 | E11: =IF(Inputs!$B$7+8-1>MAX(MORTALITY!$A:$A),"",IFERROR(INDEX(Commutation!$F:$F,MATCH(C11,Commutation!$A:$A,0)),0)) -> 5230691.8 | F11: =IF(Inputs!$B$7+8-1>MAX(MORTALITY!$A:$A),"",IFERROR(INDEX(Commutation!$H:$H,MATCH(C11+1,Commutation!$A:$A,0)),0)) -> 1.3208196e+08 | G11: =IF(Inputs!$B$7+8-1>MAX(MORTALITY!$A:$A),"",IFERROR(INDEX(Commutation!$I:$I,MATCH(C11,Commutation!$A:$A,0)),0)) -> 1881602.7 | H11: =IF(Inputs!$B$7+8-1>MAX(MORTALITY!$A:$A),"",IFERROR(1000*INDEX(Commutation!$I:$I,MATCH(Inputs!$B$7,Commutation!$A:$A,0))/INDEX(Commutation!$H:$H,MATCH(Inputs!$B$7,Commutation!$A:$A,0)),0)) -> 11.090171 | I11: =IF(Inputs!$B$7+8-1>MAX(MORTALITY!$A:$A),"",IFERROR((1000*G11-H11*F11)/E11,0)) -> 79.681835
A12: =IF(Inputs!$B$7+9-1>MAX(MORTALITY!$A:$A),"",Inputs!$B$7) -> 16 | B12: =IF(Inputs!$B$7+9-1>MAX(MORTALITY!$A:$A),"",9) -> 9 | C12: =IF(Inputs!$B$7+9-1>MAX(MORTALITY!$A:$A),"",Inputs!$B$7+9-1) -> 24 | D12: =IF(C12="","",INDEX(Commutation!$K:$K,MATCH(C12,Commutation!$A:$A,0))) -> 0.36702019 | E12: =IF(Inputs!$B$7+9-1>MAX(MORTALITY!$A:$A),"",IFERROR(INDEX(Commutation!$F:$F,MATCH(C12,Commutation!$A:$A,0)),0)) -> 5089437.6 | F12: =IF(Inputs!$B$7+9-1>MAX(MORTALITY!$A:$A),"",IFERROR(INDEX(Commutation!$H:$H,MATCH(C12+1,Commutation!$A:$A,0)),0)) -> 1.2699252e+08 | G12: =IF(Inputs!$B$7+9-1>MAX(MORTALITY!$A:$A),"",IFERROR(INDEX(Commutation!$I:$I,MATCH(C12,Commutation!$A:$A,0)),0)) -> 1867926.3 | H12: =IF(Inputs!$B$7+9-1>MAX(MORTALITY!$A:$A),"",IFERROR(1000*INDEX(Commutation!$I:$I,MATCH(Inputs!$B$7,Commutation!$A:$A,0))/INDEX(Commutation!$H:$H,MATCH(Inputs!$B$7,Commutation!$A:$A,0)),0)) -> 11.090171 | I12: =IF(Inputs!$B$7+9-1>MAX(MORTALITY!$A:$A),"",IFERROR((1000*G12-H12*F12)/E12,0)) -> 90.296325
A13: =IF(Inputs!$B$7+10-1>MAX(MORTALITY!$A:$A),"",Inputs!$B$7) -> 16 | B13: =IF(Inputs!$B$7+10-1>MAX(MORTALITY!$A:$A),"",10) -> 10 | C13: =IF(Inputs!$B$7+10-1>MAX(MORTALITY!$A:$A),"",Inputs!$B$7+10-1) -> 25 | D13: =IF(C13="","",INDEX(Commutation!$K:$K,MATCH(C13,Commutation!$A:$A,0))) -> 0.37446295 | E13: =IF(Inputs!$B$7+10-1>MAX(MORTALITY!$A:$A),"",IFERROR(INDEX(Commutation!$F:$F,MATCH(C13,Commutation!$A:$A,0)),0)) -> 4951551.1 | F13: =IF(Inputs!$B$7+10-1>MAX(MORTALITY!$A:$A),"",IFERROR(INDEX(Commutation!$H:$H,MATCH(C13+1,Commutation!$A:$A,0)),0)) -> 1.2204097e+08 | G13: =IF(Inputs!$B$7+10-1>MAX(MORTALITY!$A:$A),"",IFERROR(INDEX(Commutation!$I:$I,MATCH(C13,Commutation!$A:$A,0)),0)) -> 1854172.5 | H13: =IF(Inputs!$B$7+10-1>MAX(MORTALITY!$A:$A),"",IFERROR(1000*INDEX(Commutation!$I:$I,MATCH(Inputs!$B$7,Commutation!$A:$A,0))/INDEX(Commutation!$H:$H,MATCH(Inputs!$B$7,Commutation!$A:$A,0)),0)) -> 11.090171 | I13: =IF(Inputs!$B$7+10-1>MAX(MORTALITY!$A:$A),"",IFERROR((1000*G13-H13*F13)/E13,0)) -> 101.1233
A14: =IF(Inputs!$B$7+11-1>MAX(MORTALITY!$A:$A),"",Inputs!$B$7) -> 16 | B14: =IF(Inputs!$B$7+11-1>MAX(MORTALITY!$A:$A),"",11) -> 11 | C14: =IF(Inputs!$B$7+11-1>MAX(MORTALITY!$A:$A),"",Inputs!$B$7+11-1) -> 26 | D14: =IF(C14="","",INDEX(Commutation!$K:$K,MATCH(C14,Commutation!$A:$A,0))) -> 0.38204482 | E14: =IF(Inputs!$B$7+11-1>MAX(MORTALITY!$A:$A),"",IFERROR(INDEX(Commutation!$F:$F,MATCH(C14,Commutation!$A:$A,0)),0)) -> 4816868.9 | F14: =IF(Inputs!$B$7+11-1>MAX(MORTALITY!$A:$A),"",IFERROR(INDEX(Commutation!$H:$H,MATCH(C14+1,Commutation!$A:$A,0)),0)) -> 1.172241e+08 | G14: =IF(Inputs!$B$7+11-1>MAX(MORTALITY!$A:$A),"",IFERROR(INDEX(Commutation!$I:$I,MATCH(C14,Commutation!$A:$A,0)),0)) -> 1840259.8 | H14: =IF(Inputs!$B$7+11-1>MAX(MORTALITY!$A:$A),"",IFERROR(1000*INDEX(Commutation!$I:$I,MATCH(Inputs!$B$7,Commutation!$A:$A,0))/INDEX(Commutation!$H:$H,MATCH(Inputs!$B$7,Commutation!$A:$A,0)),0)) -> 11.090171 | I14: =IF(Inputs!$B$7+11-1>MAX(MORTALITY!$A:$A),"",IFERROR((1000*G14-H14*F14)/E14,0)) -> 112.15261
A15: =IF(Inputs!$B$7+12-1>MAX(MORTALITY!$A:$A),"",Inputs!$B$7) -> 16 | B15: =IF(Inputs!$B$7+12-1>MAX(MORTALITY!$A:$A),"",12) -> 12 | C15: =IF(Inputs!$B$7+12-1>MAX(MORTALITY!$A:$A),"",Inputs!$B$7+12-1) -> 27 | D15: =IF(C15="","",INDEX(Commutation!$K:$K,MATCH(C15,Commutation!$A:$A,0))) -> 0.38977135 | E15: =IF(Inputs!$B$7+12-1>MAX(MORTALITY!$A:$A),"",IFERROR(INDEX(Commutation!$F:$F,MATCH(C15,Commutation!$A:$A,0)),0)) -> 4685333.1 | F15: =IF(Inputs!$B$7+12-1>MAX(MORTALITY!$A:$A),"",IFERROR(INDEX(Commutation!$H:$H,MATCH(C15+1,Commutation!$A:$A,0)),0)) -> 1.1253877e+08 | G15: =IF(Inputs!$B$7+12-1>MAX(MORTALITY!$A:$A),"",IFERROR(INDEX(Commutation!$I:$I,MATCH(C15,Commutation!$A:$A,0)),0)) -> 1826208.6 | H15: =IF(Inputs!$B$7+12-1>MAX(MORTALITY!$A:$A),"",IFERROR(1000*INDEX(Commutation!$I:$I,MATCH(Inputs!$B$7,Commutation!$A:$A,0))/INDEX(Commutation!$H:$H,MATCH(Inputs!$B$7,Commutation!$A:$A,0)),0)) -> 11.090171 | I15: =IF(Inputs!$B$7+12-1>MAX(MORTALITY!$A:$A),"",IFERROR((1000*G15-H15*F15)/E15,0)) -> 123.39238
A16: =IF(Inputs!$B$7+13-1>MAX(MORTALITY!$A:$A),"",Inputs!$B$7) -> 16 | B16: =IF(Inputs!$B$7+13-1>MAX(MORTALITY!$A:$A),"",13) -> 13 | C16: =IF(Inputs!$B$7+13-1>MAX(MORTALITY!$A:$A),"",Inputs!$B$7+13-1) -> 28 | D16: =IF(C16="","",INDEX(Commutation!$K:$K,MATCH(C16,Commutation!$A:$A,0))) -> 0.3976423 | E16: =IF(Inputs!$B$7+13-1>MAX(MORTALITY!$A:$A),"",IFERROR(INDEX(Commutation!$F:$F,MATCH(C16,Commutation!$A:$A,0)),0)) -> 4556840.7 | F16: =IF(Inputs!$B$7+13-1>MAX(MORTALITY!$A:$A),"",IFERROR(INDEX(Commutation!$H:$H,MATCH(C16+1,Commutation!$A:$A,0)),0)) -> 1.0798193e+08 | G16: =IF(Inputs!$B$7+13-1>MAX(MORTALITY!$A:$A),"",IFERROR(INDEX(Commutation!$I:$I,MATCH(C16,Commutation!$A:$A,0)),0)) -> 1811992.7 | H16: =IF(Inputs!$B$7+13-1>MAX(MORTALITY!$A:$A),"",IFERROR(1000*INDEX(Commutation!$I:$I,MATCH(Inputs!$B$7,Commutation!$A:$A,0))/INDEX(Commutation!$H:$H,MATCH(Inputs!$B$7,Commutation!$A:$A,0)),0)) -> 11.090171 | I16: =IF(Inputs!$B$7+13-1>MAX(MORTALITY!$A:$A),"",IFERROR((1000*G16-H16*F16)/E16,0)) -> 134.84223
A17: =IF(Inputs!$B$7+14-1>MAX(MORTALITY!$A:$A),"",Inputs!$B$7) -> 16 | B17: =IF(Inputs!$B$7+14-1>MAX(MORTALITY!$A:$A),"",14) -> 14 | C17: =IF(Inputs!$B$7+14-1>MAX(MORTALITY!$A:$A),"",Inputs!$B$7+14-1) -> 29 | D17: =IF(C17="","",INDEX(Commutation!$K:$K,MATCH(C17,Commutation!$A:$A,0))) -> 0.40565173 | E17: =IF(Inputs!$B$7+14-1>MAX(MORTALITY!$A:$A),"",IFERROR(INDEX(Commutation!$F:$F,MATCH(C17,Commutation!$A:$A,0)),0)) -> 4431249.8 | F17: =IF(Inputs!$B$7+14-1>MAX(MORTALITY!$A:$A),"",IFERROR(INDEX(Commutation!$H:$H,MATCH(C17+1,Commutation!$A:$A,0)),0)) -> 1.0355068e+08 | G17: =IF(Inputs!$B$7+14-1>MAX(MORTALITY!$A:$A),"",IFERROR(INDEX(Commutation!$I:$I,MATCH(C17,Commutation!$A:$A,0)),0)) -> 1797544.1 | H17: =IF(Inputs!$B$7+14-1>MAX(MORTALITY!$A:$A),"",IFERROR(1000*INDEX(Commutation!$I:$I,MATCH(Inputs!$B$7,Commutation!$A:$A,0))/INDEX(Commutation!$H:$H,MATCH(Inputs!$B$7,Commutation!$A:$A,0)),0)) -> 11.090171 | I17: =IF(Inputs!$B$7+14-1>MAX(MORTALITY!$A:$A),"",IFERROR((1000*G17-H17*F17)/E17,0)) -> 146.49352
A18: =IF(Inputs!$B$7+15-1>MAX(MORTALITY!$A:$A),"",Inputs!$B$7) -> 16 | B18: =IF(Inputs!$B$7+15-1>MAX(MORTALITY!$A:$A),"",15) -> 15 | C18: =IF(Inputs!$B$7+15-1>MAX(MORTALITY!$A:$A),"",Inputs!$B$7+15-1) -> 30 | D18: =IF(C18="","",INDEX(Commutation!$K:$K,MATCH(C18,Commutation!$A:$A,0))) -> 0.41379994 | E18: =IF(Inputs!$B$7+15-1>MAX(MORTALITY!$A:$A),"",IFERROR(INDEX(Commutation!$F:$F,MATCH(C18,Commutation!$A:$A,0)),0)) -> 4308471.7 | F18: =IF(Inputs!$B$7+15-1>MAX(MORTALITY!$A:$A),"",IFERROR(INDEX(Commutation!$H:$H,MATCH(C18+1,Commutation!$A:$A,0)),0)) -> 99242209 | G18: =IF(Inputs!$B$7+15-1>MAX(MORTALITY!$A:$A),"",IFERROR(INDEX(Commutation!$I:$I,MATCH(C18,Commutation!$A:$A,0)),0)) -> 1782845.4 | H18: =IF(Inputs!$B$7+15-1>MAX(MORTALITY!$A:$A),"",IFERROR(1000*INDEX(Commutation!$I:$I,MATCH(Inputs!$B$7,Commutation!$A:$A,0))/INDEX(Commutation!$H:$H,MATCH(Inputs!$B$7,Commutation!$A:$A,0)),0)) -> 11.090171 | I18: =IF(Inputs!$B$7+15-1>MAX(MORTALITY!$A:$A),"",IFERROR((1000*G18-H18*F18)/E18,0)) -> 158.3467
A19: =IF(Inputs!$B$7+16-1>MAX(MORTALITY!$A:$A),"",Inputs!$B$7) -> 16 | B19: =IF(Inputs!$B$7+16-1>MAX(MORTALITY!$A:$A),"",16) -> 16 | C19: =IF(Inputs!$B$7+16-1>MAX(MORTALITY!$A:$A),"",Inputs!$B$7+16-1) -> 31 | D19: =IF(C19="","",INDEX(Commutation!$K:$K,MATCH(C19,Commutation!$A:$A,0))) -> 0.42208757 | E19: =IF(Inputs!$B$7+16-1>MAX(MORTALITY!$A:$A),"",IFERROR(INDEX(Commutation!$F:$F,MATCH(C19,Commutation!$A:$A,0)),0)) -> 4188423 | F19: =IF(Inputs!$B$7+16-1>MAX(MORTALITY!$A:$A),"",IFERROR(INDEX(Commutation!$H:$H,MATCH(C19+1,Commutation!$A:$A,0)),0)) -> 95053786 | G19: =IF(Inputs!$B$7+16-1>MAX(MORTALITY!$A:$A),"",IFERROR(INDEX(Commutation!$I:$I,MATCH(C19,Commutation!$A:$A,0)),0)) -> 1767881.3 | H19: =IF(Inputs!$B$7+16-1>MAX(MORTALITY!$A:$A),"",IFERROR(1000*INDEX(Commutation!$I:$I,MATCH(Inputs!$B$7,Commutation!$A:$A,0))/INDEX(Commutation!$H:$H,MATCH(Inputs!$B$7,Commutation!$A:$A,0)),0)) -> 11.090171 | I19: =IF(Inputs!$B$7+16-1>MAX(MORTALITY!$A:$A),"",IFERROR((1000*G19-H19*F19)/E19,0)) -> 170.40269
A20: =IF(Inputs!$B$7+17-1>MAX(MORTALITY!$A:$A),"",Inputs!$B$7) -> 16 | B20: =IF(Inputs!$B$7+17-1>MAX(MORTALITY!$A:$A),"",17) -> 17 | C20: =IF(Inputs!$B$7+17-1>MAX(MORTALITY!$A:$A),"",Inputs!$B$7+17-1) -> 32 | D20: =IF(C20="","",INDEX(Commutation!$K:$K,MATCH(C20,Commutation!$A:$A,0))) -> 0.43051559 | E20: =IF(Inputs!$B$7+17-1>MAX(MORTALITY!$A:$A),"",IFERROR(INDEX(Commutation!$F:$F,MATCH(C20,Commutation!$A:$A,0)),0)) -> 4071024.6 | F20: =IF(Inputs!$B$7+17-1>MAX(MORTALITY!$A:$A),"",IFERROR(INDEX(Commutation!$H:$H,MATCH(C20+1,Commutation!$A:$A,0)),0)) -> 90982762 | G20: =IF(Inputs!$B$7+17-1>MAX(MORTALITY!$A:$A),"",IFERROR(INDEX(Commutation!$I:$I,MATCH(C20,Commutation!$A:$A,0)),0)) -> 1752639.5 | H20: =IF(Inputs!$B$7+17-1>MAX(MORTALITY!$A:$A),"",IFERROR(1000*INDEX(Commutation!$I:$I,MATCH(Inputs!$B$7,Commutation!$A:$A,0))/INDEX(Commutation!$H:$H,MATCH(Inputs!$B$7,Commutation!$A:$A,0)),0)) -> 11.090171 | I20: =IF(Inputs!$B$7+17-1>MAX(MORTALITY!$A:$A),"",IFERROR((1000*G20-H20*F20)/E20,0)) -> 182.66289
A21: =IF(Inputs!$B$7+18-1>MAX(MORTALITY!$A:$A),"",Inputs!$B$7) -> 16 | B21: =IF(Inputs!$B$7+18-1>MAX(MORTALITY!$A:$A),"",18) -> 18 | C21: =IF(Inputs!$B$7+18-1>MAX(MORTALITY!$A:$A),"",Inputs!$B$7+18-1) -> 33 | D21: =IF(C21="","",INDEX(Commutation!$K:$K,MATCH(C21,Commutation!$A:$A,0))) -> 0.43907967 | E21: =IF(Inputs!$B$7+18-1>MAX(MORTALITY!$A:$A),"",IFERROR(INDEX(Commutation!$F:$F,MATCH(C21,Commutation!$A:$A,0)),0)) -> 3956162.1 | F21: =IF(Inputs!$B$7+18-1>MAX(MORTALITY!$A:$A),"",IFERROR(INDEX(Commutation!$H:$H,MATCH(C21+1,Commutation!$A:$A,0)),0)) -> 87026600 | G21: =IF(Inputs!$B$7+18-1>MAX(MORTALITY!$A:$A),"",IFERROR(INDEX(Commutation!$I:$I,MATCH(C21,Commutation!$A:$A,0)),0)) -> 1737070.3 | H21: =IF(Inputs!$B$7+18-1>MAX(MORTALITY!$A:$A),"",IFERROR(1000*INDEX(Commutation!$I:$I,MATCH(Inputs!$B$7,Commutation!$A:$A,0))/INDEX(Commutation!$H:$H,MATCH(Inputs!$B$7,Commutation!$A:$A,0)),0)) -> 11.090171 | I21: =IF(Inputs!$B$7+18-1>MAX(MORTALITY!$A:$A),"",IFERROR((1000*G21-H21*F21)/E21,0)) -> 195.12104
A22: =IF(Inputs!$B$7+19-1>MAX(MORTALITY!$A:$A),"",Inputs!$B$7) -> 16 | B22: =IF(Inputs!$B$7+19-1>MAX(MORTALITY!$A:$A),"",19) -> 19 | C22: =IF(Inputs!$B$7+19-1>MAX(MORTALITY!$A:$A),"",Inputs!$B$7+19-1) -> 34 | D22: =IF(C22="","",INDEX(Commutation!$K:$K,MATCH(C22,Commutation!$A:$A,0))) -> 0.44778152 | E22: =IF(Inputs!$B$7+19-1>MAX(MORTALITY!$A:$A),"",IFERROR(INDEX(Commutation!$F:$F,MATCH(C22,Commutation!$A:$A,0)),0)) -> 3843768.5 | F22: =IF(Inputs!$B$7+19-1>MAX(MORTALITY!$A:$A),"",IFERROR(INDEX(Commutation!$H:$H,MATCH(C22+1,Commutation!$A:$A,0)),0)) -> 83182831 | G22: =IF(Inputs!$B$7+19-1>MAX(MORTALITY!$A:$A),"",IFERROR(INDEX(Commutation!$I:$I,MATCH(C22,Commutation!$A:$A,0)),0)) -> 1721168.5 | H22: =IF(Inputs!$B$7+19-1>MAX(MORTALITY!$A:$A),"",IFERROR(1000*INDEX(Commutation!$I:$I,MATCH(Inputs!$B$7,Commutation!$A:$A,0))/INDEX(Commutation!$H:$H,MATCH(Inputs!$B$7,Commutation!$A:$A,0)),0)) -> 11.090171 | I22: =IF(Inputs!$B$7+19-1>MAX(MORTALITY!$A:$A),"",IFERROR((1000*G22-H22*F22)/E22,0)) -> 207.7796
A23: =IF(Inputs!$B$7+20-1>MAX(MORTALITY!$A:$A),"",Inputs!$B$7) -> 16 | B23: =IF(Inputs!$B$7+20-1>MAX(MORTALITY!$A:$A),"",20) -> 20 | C23: =IF(Inputs!$B$7+20-1>MAX(MORTALITY!$A:$A),"",Inputs!$B$7+20-1) -> 35 | D23: =IF(C23="","",INDEX(Commutation!$K:$K,MATCH(C23,Commutation!$A:$A,0))) -> 0.45661232 | E23: =IF(Inputs!$B$7+20-1>MAX(MORTALITY!$A:$A),"",IFERROR(INDEX(Commutation!$F:$F,MATCH(C23,Commutation!$A:$A,0)),0)) -> 3733705.5 | F23: =IF(Inputs!$B$7+20-1>MAX(MORTALITY!$A:$A),"",IFERROR(INDEX(Commutation!$H:$H,MATCH(C23+1,Commutation!$A:$A,0)),0)) -> 79449126 | G23: =IF(Inputs!$B$7+20-1>MAX(MORTALITY!$A:$A),"",IFERROR(INDEX(Commutation!$I:$I,MATCH(C23,Commutation!$A:$A,0)),0)) -> 1704855.9 | H23: =IF(Inputs!$B$7+20-1>MAX(MORTALITY!$A:$A),"",IFERROR(1000*INDEX(Commutation!$I:$I,MATCH(Inputs!$B$7,Commutation!$A:$A,0))/INDEX(Commutation!$H:$H,MATCH(Inputs!$B$7,Commutation!$A:$A,0)),0)) -> 11.090171 | I23: =IF(Inputs!$B$7+20-1>MAX(MORTALITY!$A:$A),"",IFERROR((1000*G23-H23*F23)/E23,0)) -> 220.62574
A24: =IF(Inputs!$B$7+21-1>MAX(MORTALITY!$A:$A),"",Inputs!$B$7) -> 16 | B24: =IF(Inputs!$B$7+21-1>MAX(MORTALITY!$A:$A),"",21) -> 21 | C24: =IF(Inputs!$B$7+21-1>MAX(MORTALITY!$A:$A),"",Inputs!$B$7+21-1) -> 36 | D24: =IF(C24="","",INDEX(Commutation!$K:$K,MATCH(C24,Commutation!$A:$A,0))) -> 0.46557462 | E24: =IF(Inputs!$B$7+21-1>MAX(MORTALITY!$A:$A),"",IFERROR(INDEX(Commutation!$F:$F,MATCH(C24,Commutation!$A:$A,0)),0)) -> 3625919.8 | F24: =IF(Inputs!$B$7+21-1>MAX(MORTALITY!$A:$A),"",IFERROR(INDEX(Commutation!$H:$H,MATCH(C24+1,Commutation!$A:$A,0)),0)) -> 75823206 | G24: =IF(Inputs!$B$7+21-1>MAX(MORTALITY!$A:$A),"",IFERROR(INDEX(Commutation!$I:$I,MATCH(C24,Commutation!$A:$A,0)),0)) -> 1688136.2 | H24: =IF(Inputs!$B$7+21-1>MAX(MORTALITY!$A:$A),"",IFERROR(1000*INDEX(Commutation!$I:$I,MATCH(Inputs!$B$7,Commutation!$A:$A,0))/INDEX(Commutation!$H:$H,MATCH(Inputs!$B$7,Commutation!$A:$A,0)),0)) -> 11.090171 | I24: =IF(Inputs!$B$7+21-1>MAX(MORTALITY!$A:$A),"",IFERROR((1000*G24-H24*F24)/E24,0)) -> 233.66316
A25: =IF(Inputs!$B$7+22-1>MAX(MORTALITY!$A:$A),"",Inputs!$B$7) -> 16 | B25: =IF(Inputs!$B$7+22-1>MAX(MORTALITY!$A:$A),"",22) -> 22 | C25: =IF(Inputs!$B$7+22-1>MAX(MORTALITY!$A:$A),"",Inputs!$B$7+22-1) -> 37 | D25: =IF(C25="","",INDEX(Commutation!$K:$K,MATCH(C25,Commutation!$A:$A,0))) -> 0.47466083 | E25: =IF(Inputs!$B$7+22-1>MAX(MORTALITY!$A:$A),"",IFERROR(INDEX(Commutation!$F:$F,MATCH(C25,Commutation!$A:$A,0)),0)) -> 3520290.5 | F25: =IF(Inputs!$B$7+22-1>MAX(MORTALITY!$A:$A),"",IFERROR(INDEX(Commutation!$H:$H,MATCH(C25+1,Commutation!$A:$A,0)),0)) -> 72302916 | G25: =IF(Inputs!$B$7+22-1>MAX(MORTALITY!$A:$A),"",IFERROR(INDEX(Commutation!$I:$I,MATCH(C25,Commutation!$A:$A,0)),0)) -> 1670944 | H25: =IF(Inputs!$B$7+22-1>MAX(MORTALITY!$A:$A),"",IFERROR(1000*INDEX(Commutation!$I:$I,MATCH(Inputs!$B$7,Commutation!$A:$A,0))/INDEX(Commutation!$H:$H,MATCH(Inputs!$B$7,Commutation!$A:$A,0)),0)) -> 11.090171 | I25: =IF(Inputs!$B$7+22-1>MAX(MORTALITY!$A:$A),"",IFERROR((1000*G25-H25*F25)/E25,0)) -> 246.88085
A26: =IF(Inputs!$B$7+23-1>MAX(MORTALITY!$A:$A),"",Inputs!$B$7) -> 16 | B26: =IF(Inputs!$B$7+23-1>MAX(MORTALITY!$A:$A),"",23) -> 23 | C26: =IF(Inputs!$B$7+23-1>MAX(MORTALITY!$A:$A),"",Inputs!$B$7+23-1) -> 38 | D26: =IF(C26="","",INDEX(Commutation!$K:$K,MATCH(C26,Commutation!$A:$A,0))) -> 0.48386928 | E26: =IF(Inputs!$B$7+23-1>MAX(MORTALITY!$A:$A),"",IFERROR(INDEX(Commutation!$F:$F,MATCH(C26,Commutation!$A:$A,0)),0)) -> 3416742.5 | F26: =IF(Inputs!$B$7+23-1>MAX(MORTALITY!$A:$A),"",IFERROR(INDEX(Commutation!$H:$H,MATCH(C26+1,Commutation!$A:$A,0)),0)) -> 68886173 | G26: =IF(Inputs!$B$7+23-1>MAX(MORTALITY!$A:$A),"",IFERROR(INDEX(Commutation!$I:$I,MATCH(C26,Commutation!$A:$A,0)),0)) -> 1653256.7 | H26: =IF(Inputs!$B$7+23-1>MAX(MORTALITY!$A:$A),"",IFERROR(1000*INDEX(Commutation!$I:$I,MATCH(Inputs!$B$7,Commutation!$A:$A,0))/INDEX(Commutation!$H:$H,MATCH(Inputs!$B$7,Commutation!$A:$A,0)),0)) -> 11.090171 | I26: =IF(Inputs!$B$7+23-1>MAX(MORTALITY!$A:$A),"",IFERROR((1000*G26-H26*F26)/E26,0)) -> 260.27635
A27: =IF(Inputs!$B$7+24-1>MAX(MORTALITY!$A:$A),"",Inputs!$B$7) -> 16 | B27: =IF(Inputs!$B$7+24-1>MAX(MORTALITY!$A:$A),"",24) -> 24 | C27: =IF(Inputs!$B$7+24-1>MAX(MORTALITY!$A:$A),"",Inputs!$B$7+24-1) -> 39 | D27: =IF(C27="","",INDEX(Commutation!$K:$K,MATCH(C27,Commutation!$A:$A,0))) -> 0.49319888 | E27: =IF(Inputs!$B$7+24-1>MAX(MORTALITY!$A:$A),"",IFERROR(INDEX(Commutation!$F:$F,MATCH(C27,Commutation!$A:$A,0)),0)) -> 3315206.9 | F27: =IF(Inputs!$B$7+24-1>MAX(MORTALITY!$A:$A),"",IFERROR(INDEX(Commutation!$H:$H,MATCH(C27+1,Commutation!$A:$A,0)),0)) -> 65570966 | G27: =IF(Inputs!$B$7+24-1>MAX(MORTALITY!$A:$A),"",IFERROR(INDEX(Commutation!$I:$I,MATCH(C27,Commutation!$A:$A,0)),0)) -> 1635056.3 | H27: =IF(Inputs!$B$7+24-1>MAX(MORTALITY!$A:$A),"",IFERROR(1000*INDEX(Commutation!$I:$I,MATCH(Inputs!$B$7,Commutation!$A:$A,0))/INDEX(Commutation!$H:$H,MATCH(Inputs!$B$7,Commutation!$A:$A,0)),0)) -> 11.090171 | I27: =IF(Inputs!$B$7+24-1>MAX(MORTALITY!$A:$A),"",IFERROR((1000*G27-H27*F27)/E27,0)) -> 273.84809
A28: =IF(Inputs!$B$7+25-1>MAX(MORTALITY!$A:$A),"",Inputs!$B$7) -> 16 | B28: =IF(Inputs!$B$7+25-1>MAX(MORTALITY!$A:$A),"",25) -> 25 | C28: =IF(Inputs!$B$7+25-1>MAX(MORTALITY!$A:$A),"",Inputs!$B$7+25-1) -> 40 | D28: =IF(C28="","",INDEX(Commutation!$K:$K,MATCH(C28,Commutation!$A:$A,0))) -> 0.50263918 | E28: =IF(Inputs!$B$7+25-1>MAX(MORTALITY!$A:$A),"",IFERROR(INDEX(Commutation!$F:$F,MATCH(C28,Commutation!$A:$A,0)),0)) -> 3215556.6 | F28: =IF(Inputs!$B$7+25-1>MAX(MORTALITY!$A:$A),"",IFERROR(INDEX(Commutation!$H:$H,MATCH(C28+1,Commutation!$A:$A,0)),0)) -> 62355410 | G28: =IF(Inputs!$B$7+25-1>MAX(MORTALITY!$A:$A),"",IFERROR(INDEX(Commutation!$I:$I,MATCH(C28,Commutation!$A:$A,0)),0)) -> 1616264.8 | H28: =IF(Inputs!$B$7+25-1>MAX(MORTALITY!$A:$A),"",IFERROR(1000*INDEX(Commutation!$I:$I,MATCH(Inputs!$B$7,Commutation!$A:$A,0))/INDEX(Commutation!$H:$H,MATCH(Inputs!$B$7,Commutation!$A:$A,0)),0)) -> 11.090171 | I28: =IF(Inputs!$B$7+25-1>MAX(MORTALITY!$A:$A),"",IFERROR((1000*G28-H28*F28)/E28,0)) -> 287.58088
A29: =IF(Inputs!$B$7+26-1>MAX(MORTALITY!$A:$A),"",Inputs!$B$7) -> 16 | B29: =IF(Inputs!$B$7+26-1>MAX(MORTALITY!$A:$A),"",26) -> 26 | C29: =IF(Inputs!$B$7+26-1>MAX(MORTALITY!$A:$A),"",Inputs!$B$7+26-1) -> 41 | D29: =IF(C29="","",INDEX(Commutation!$K:$K,MATCH(C29,Commutation!$A:$A,0))) -> 0.5121905 | E29: =IF(Inputs!$B$7+26-1>MAX(MORTALITY!$A:$A),"",IFERROR(INDEX(Commutation!$F:$F,MATCH(C29,Commutation!$A:$A,0)),0)) -> 3117741 | F29: =IF(Inputs!$B$7+26-1>MAX(MORTALITY!$A:$A),"",IFERROR(INDEX(Commutation!$H:$H,MATCH(C29+1,Commutation!$A:$A,0)),0)) -> 59237669 | G29: =IF(Inputs!$B$7+26-1>MAX(MORTALITY!$A:$A),"",IFERROR(INDEX(Commutation!$I:$I,MATCH(C29,Commutation!$A:$A,0)),0)) -> 1596877.3 | H29: =IF(Inputs!$B$7+26-1>MAX(MORTALITY!$A:$A),"",IFERROR(1000*INDEX(Commutation!$I:$I,MATCH(Inputs!$B$7,Commutation!$A:$A,0))/INDEX(Commutation!$H:$H,MATCH(Inputs!$B$7,Commutation!$A:$A,0)),0)) -> 11.090171 | I29: =IF(Inputs!$B$7+26-1>MAX(MORTALITY!$A:$A),"",IFERROR((1000*G29-H29*F29)/E29,0)) -> 301.47515
A30: =IF(Inputs!$B$7+27-1>MAX(MORTALITY!$A:$A),"",Inputs!$B$7) -> 16 | B30: =IF(Inputs!$B$7+27-1>MAX(MORTALITY!$A:$A),"",27) -> 27 | C30: =IF(Inputs!$B$7+27-1>MAX(MORTALITY!$A:$A),"",Inputs!$B$7+27-1) -> 42 | D30: =IF(C30="","",INDEX(Commutation!$K:$K,MATCH(C30,Commutation!$A:$A,0))) -> 0.52184422 | E30: =IF(Inputs!$B$7+27-1>MAX(MORTALITY!$A:$A),"",IFERROR(INDEX(Commutation!$F:$F,MATCH(C30,Commutation!$A:$A,0)),0)) -> 3021653.7 | F30: =IF(Inputs!$B$7+27-1>MAX(MORTALITY!$A:$A),"",IFERROR(INDEX(Commutation!$H:$H,MATCH(C30+1,Commutation!$A:$A,0)),0)) -> 56216015 | G30: =IF(Inputs!$B$7+27-1>MAX(MORTALITY!$A:$A),"",IFERROR(INDEX(Commutation!$I:$I,MATCH(C30,Commutation!$A:$A,0)),0)) -> 1576832.5 | H30: =IF(Inputs!$B$7+27-1>MAX(MORTALITY!$A:$A),"",IFERROR(1000*INDEX(Commutation!$I:$I,MATCH(Inputs!$B$7,Commutation!$A:$A,0))/INDEX(Commutation!$H:$H,MATCH(Inputs!$B$7,Commutation!$A:$A,0)),0)) -> 11.090171 | I30: =IF(Inputs!$B$7+27-1>MAX(MORTALITY!$A:$A),"",IFERROR((1000*G30-H30*F30)/E30,0)) -> 315.51838
A31: =IF(Inputs!$B$7+28-1>MAX(MORTALITY!$A:$A),"",Inputs!$B$7) -> 16 | B31: =IF(Inputs!$B$7+28-1>MAX(MORTALITY!$A:$A),"",28) -> 28 | C31: =IF(Inputs!$B$7+28-1>MAX(MORTALITY!$A:$A),"",Inputs!$B$7+28-1) -> 43 | D31: =IF(C31="","",INDEX(Commutation!$K:$K,MATCH(C31,Commutation!$A:$A,0))) -> 0.53159745 | E31: =IF(Inputs!$B$7+28-1>MAX(MORTALITY!$A:$A),"",IFERROR(INDEX(Commutation!$F:$F,MATCH(C31,Commutation!$A:$A,0)),0)) -> 2927230.7 | F31: =IF(Inputs!$B$7+28-1>MAX(MORTALITY!$A:$A),"",IFERROR(INDEX(Commutation!$H:$H,MATCH(C31+1,Commutation!$A:$A,0)),0)) -> 53288784 | G31: =IF(Inputs!$B$7+28-1>MAX(MORTALITY!$A:$A),"",IFERROR(INDEX(Commutation!$I:$I,MATCH(C31,Commutation!$A:$A,0)),0)) -> 1556108.4 | H31: =IF(Inputs!$B$7+28-1>MAX(MORTALITY!$A:$A),"",IFERROR(1000*INDEX(Commutation!$I:$I,MATCH(Inputs!$B$7,Commutation!$A:$A,0))/INDEX(Commutation!$H:$H,MATCH(Inputs!$B$7,Commutation!$A:$A,0)),0)) -> 11.090171 | I31: =IF(Inputs!$B$7+28-1>MAX(MORTALITY!$A:$A),"",IFERROR((1000*G31-H31*F31)/E31,0)) -> 329.70638
A32: =IF(Inputs!$B$7+29-1>MAX(MORTALITY!$A:$A),"",Inputs!$B$7) -> 16 | B32: =IF(Inputs!$B$7+29-1>MAX(MORTALITY!$A:$A),"",29) -> 29 | C32: =IF(Inputs!$B$7+29-1>MAX(MORTALITY!$A:$A),"",Inputs!$B$7+29-1) -> 44 | D32: =IF(C32="","",INDEX(Commutation!$K:$K,MATCH(C32,Commutation!$A:$A,0))) -> 0.54144363 | E32: =IF(Inputs!$B$7+29-1>MAX(MORTALITY!$A:$A),"",IFERROR(INDEX(Commutation!$F:$F,MATCH(C32,Commutation!$A:$A,0)),0)) -> 2834387.5 | F32: =IF(Inputs!$B$7+29-1>MAX(MORTALITY!$A:$A),"",IFERROR(INDEX(Commutation!$H:$H,MATCH(C32+1,Commutation!$A:$A,0)),0)) -> 50454397 | G32: =IF(Inputs!$B$7+29-1>MAX(MORTALITY!$A:$A),"",IFERROR(INDEX(Commutation!$I:$I,MATCH(C32,Commutation!$A:$A,0)),0)) -> 1534661.1 | H32: =IF(Inputs!$B$7+29-1>MAX(MORTALITY!$A:$A),"",IFERROR(1000*INDEX(Commutation!$I:$I,MATCH(Inputs!$B$7,Commutation!$A:$A,0))/INDEX(Commutation!$H:$H,MATCH(Inputs!$B$7,Commutation!$A:$A,0)),0)) -> 11.090171 | I32: =IF(Inputs!$B$7+29-1>MAX(MORTALITY!$A:$A),"",IFERROR((1000*G32-H32*F32)/E32,0)) -> 344.02959
A33: =IF(Inputs!$B$7+30-1>MAX(MORTALITY!$A:$A),"",Inputs!$B$7) -> 16 | B33: =IF(Inputs!$B$7+30-1>MAX(MORTALITY!$A:$A),"",30) -> 30 | C33: =IF(Inputs!$B$7+30-1>MAX(MORTALITY!$A:$A),"",Inputs!$B$7+30-1) -> 45 | D33: =IF(C33="","",INDEX(Commutation!$K:$K,MATCH(C33,Commutation!$A:$A,0))) -> 0.55137276 | E33: =IF(Inputs!$B$7+30-1>MAX(MORTALITY!$A:$A),"",IFERROR(INDEX(Commutation!$F:$F,MATCH(C33,Commutation!$A:$A,0)),0)) -> 2743023.5 | F33: =IF(Inputs!$B$7+30-1>MAX(MORTALITY!$A:$A),"",IFERROR(INDEX(Commutation!$H:$H,MATCH(C33+1,Commutation!$A:$A,0)),0)) -> 47711373 | G33: =IF(Inputs!$B$7+30-1>MAX(MORTALITY!$A:$A),"",IFERROR(INDEX(Commutation!$I:$I,MATCH(C33,Commutation!$A:$A,0)),0)) -> 1512428.4 | H33: =IF(Inputs!$B$7+30-1>MAX(MORTALITY!$A:$A),"",IFERROR(1000*INDEX(Commutation!$I:$I,MATCH(Inputs!$B$7,Commutation!$A:$A,0))/INDEX(Commutation!$H:$H,MATCH(Inputs!$B$7,Commutation!$A:$A,0)),0)) -> 11.090171 | I33: =IF(Inputs!$B$7+30-1>MAX(MORTALITY!$A:$A),"",IFERROR((1000*G33-H33*F33)/E33,0)) -> 358.47346
A34: =IF(Inputs!$B$7+31-1>MAX(MORTALITY!$A:$A),"",Inputs!$B$7) -> 16 | B34: =IF(Inputs!$B$7+31-1>MAX(MORTALITY!$A:$A),"",31) -> 31 | C34: =IF(Inputs!$B$7+31-1>MAX(MORTALITY!$A:$A),"",Inputs!$B$7+31-1) -> 46 | D34: =IF(C34="","",INDEX(Commutation!$K:$K,MATCH(C34,Commutation!$A:$A,0))) -> 0.56138056 | E34: =IF(Inputs!$B$7+31-1>MAX(MORTALITY!$A:$A),"",IFERROR(INDEX(Commutation!$F:$F,MATCH(C34,Commutation!$A:$A,0)),0)) -> 2653079 | F34: =IF(Inputs!$B$7+31-1>MAX(MORTALITY!$A:$A),"",IFERROR(INDEX(Commutation!$H:$H,MATCH(C34+1,Commutation!$A:$A,0)),0)) -> 45058294 | G34: =IF(Inputs!$B$7+31-1>MAX(MORTALITY!$A:$A),"",IFERROR(INDEX(Commutation!$I:$I,MATCH(C34,Commutation!$A:$A,0)),0)) -> 1489387 | H34: =IF(Inputs!$B$7+31-1>MAX(MORTALITY!$A:$A),"",IFERROR(1000*INDEX(Commutation!$I:$I,MATCH(Inputs!$B$7,Commutation!$A:$A,0))/INDEX(Commutation!$H:$H,MATCH(Inputs!$B$7,Commutation!$A:$A,0)),0)) -> 11.090171 | I34: =IF(Inputs!$B$7+31-1>MAX(MORTALITY!$A:$A),"",IFERROR((1000*G34-H34*F34)/E34,0)) -> 373.03179
A35: =IF(Inputs!$B$7+32-1>MAX(MORTALITY!$A:$A),"",Inputs!$B$7) -> 16 | B35: =IF(Inputs!$B$7+32-1>MAX(MORTALITY!$A:$A),"",32) -> 32 | C35: =IF(Inputs!$B$7+32-1>MAX(MORTALITY!$A:$A),"",Inputs!$B$7+32-1) -> 47 | D35: =IF(C35="","",INDEX(Commutation!$K:$K,MATCH(C35,Commutation!$A:$A,0))) -> 0.57145965 | E35: =IF(Inputs!$B$7+32-1>MAX(MORTALITY!$A:$A),"",IFERROR(INDEX(Commutation!$F:$F,MATCH(C35,Commutation!$A:$A,0)),0)) -> 2564479.1 | F35: =IF(Inputs!$B$7+32-1>MAX(MORTALITY!$A:$A),"",IFERROR(INDEX(Commutation!$H:$H,MATCH(C35+1,Commutation!$A:$A,0)),0)) -> 42493815 | G35: =IF(Inputs!$B$7+32-1>MAX(MORTALITY!$A:$A),"",IFERROR(INDEX(Commutation!$I:$I,MATCH(C35,Commutation!$A:$A,0)),0)) -> 1465496.4 | H35: =IF(Inputs!$B$7+32-1>MAX(MORTALITY!$A:$A),"",IFERROR(1000*INDEX(Commutation!$I:$I,MATCH(Inputs!$B$7,Commutation!$A:$A,0))/INDEX(Commutation!$H:$H,MATCH(Inputs!$B$7,Commutation!$A:$A,0)),0)) -> 11.090171 | I35: =IF(Inputs!$B$7+32-1>MAX(MORTALITY!$A:$A),"",IFERROR((1000*G35-H35*F35)/E35,0)) -> 387.6938
A36: =IF(Inputs!$B$7+33-1>MAX(MORTALITY!$A:$A),"",Inputs!$B$7) -> 16 | B36: =IF(Inputs!$B$7+33-1>MAX(MORTALITY!$A:$A),"",33) -> 33 | C36: =IF(Inputs!$B$7+33-1>MAX(MORTALITY!$A:$A),"",Inputs!$B$7+33-1) -> 48 | D36: =IF(C36="","",INDEX(Commutation!$K:$K,MATCH(C36,Commutation!$A:$A,0))) -> 0.5815998 | E36: =IF(Inputs!$B$7+33-1>MAX(MORTALITY!$A:$A),"",IFERROR(INDEX(Commutation!$F:$F,MATCH(C36,Commutation!$A:$A,0)),0)) -> 2477136.7 | F36: =IF(Inputs!$B$7+33-1>MAX(MORTALITY!$A:$A),"",IFERROR(INDEX(Commutation!$H:$H,MATCH(C36+1,Commutation!$A:$A,0)),0)) -> 40016678 | G36: =IF(Inputs!$B$7+33-1>MAX(MORTALITY!$A:$A),"",IFERROR(INDEX(Commutation!$I:$I,MATCH(C36,Commutation!$A:$A,0)),0)) -> 1440702.2 | H36: =IF(Inputs!$B$7+33-1>MAX(MORTALITY!$A:$A),"",IFERROR(1000*INDEX(Commutation!$I:$I,MATCH(Inputs!$B$7,Commutation!$A:$A,0))/INDEX(Commutation!$H:$H,MATCH(Inputs!$B$7,Commutation!$A:$A,0)),0)) -> 11.090171 | I36: =IF(Inputs!$B$7+33-1>MAX(MORTALITY!$A:$A),"",IFERROR((1000*G36-H36*F36)/E36,0)) -> 402.44464
A37: =IF(Inputs!$B$7+34-1>MAX(MORTALITY!$A:$A),"",Inputs!$B$7) -> 16 | B37: =IF(Inputs!$B$7+34-1>MAX(MORTALITY!$A:$A),"",34) -> 34 | C37: =IF(Inputs!$B$7+34-1>MAX(MORTALITY!$A:$A),"",Inputs!$B$7+34-1) -> 49 | D37: =IF(C37="","",INDEX(Commutation!$K:$K,MATCH(C37,Commutation!$A:$A,0))) -> 0.59179651 | E37: =IF(Inputs!$B$7+34-1>MAX(MORTALITY!$A:$A),"",IFERROR(INDEX(Commutation!$F:$F,MATCH(C37,Commutation!$A:$A,0)),0)) -> 2391004.9 | F37: =IF(Inputs!$B$7+34-1>MAX(MORTALITY!$A:$A),"",IFERROR(INDEX(Commutation!$H:$H,MATCH(C37+1,Commutation!$A:$A,0)),0)) -> 37625673 | G37: =IF(Inputs!$B$7+34-1>MAX(MORTALITY!$A:$A),"",IFERROR(INDEX(Commutation!$I:$I,MATCH(C37,Commutation!$A:$A,0)),0)) -> 1414988.3 | H37: =IF(Inputs!$B$7+34-1>MAX(MORTALITY!$A:$A),"",IFERROR(1000*INDEX(Commutation!$I:$I,MATCH(Inputs!$B$7,Commutation!$A:$A,0))/INDEX(Commutation!$H:$H,MATCH(Inputs!$B$7,Commutation!$A:$A,0)),0)) -> 11.090171 | I37: =IF(Inputs!$B$7+34-1>MAX(MORTALITY!$A:$A),"",IFERROR((1000*G37-H37*F37)/E37,0)) -> 417.27777
A38: =IF(Inputs!$B$7+35-1>MAX(MORTALITY!$A:$A),"",Inputs!$B$7) -> 16 | B38: =IF(Inputs!$B$7+35-1>MAX(MORTALITY!$A:$A),"",35) -> 35 | C38: =IF(Inputs!$B$7+35-1>MAX(MORTALITY!$A:$A),"",Inputs!$B$7+35-1) -> 50 | D38: =IF(C38="","",INDEX(Commutation!$K:$K,MATCH(C38,Commutation!$A:$A,0))) -> 0.60203472 | E38: =IF(Inputs!$B$7+35-1>MAX(MORTALITY!$A:$A),"",IFERROR(INDEX(Commutation!$F:$F,MATCH(C38,Commutation!$A:$A,0)),0)) -> 2305978.4 | F38: =IF(Inputs!$B$7+35-1>MAX(MORTALITY!$A:$A),"",IFERROR(INDEX(Commutation!$H:$H,MATCH(C38+1,Commutation!$A:$A,0)),0)) -> 35319695 | G38: =IF(Inputs!$B$7+35-1>MAX(MORTALITY!$A:$A),"",IFERROR(INDEX(Commutation!$I:$I,MATCH(C38,Commutation!$A:$A,0)),0)) -> 1388279.1 | H38: =IF(Inputs!$B$7+35-1>MAX(MORTALITY!$A:$A),"",IFERROR(1000*INDEX(Commutation!$I:$I,MATCH(Inputs!$B$7,Commutation!$A:$A,0))/INDEX(Commutation!$H:$H,MATCH(Inputs!$B$7,Commutation!$A:$A,0)),0)) -> 11.090171 | I38: =IF(Inputs!$B$7+35-1>MAX(MORTALITY!$A:$A),"",IFERROR((1000*G38-H38*F38)/E38,0)) -> 432.17126
A39: =IF(Inputs!$B$7+36-1>MAX(MORTALITY!$A:$A),"",Inputs!$B$7) -> 16 | B39: =IF(Inputs!$B$7+36-1>MAX(MORTALITY!$A:$A),"",36) -> 36 | C39: =IF(Inputs!$B$7+36-1>MAX(MORTALITY!$A:$A),"",Inputs!$B$7+36-1) -> 51 | D39: =IF(C39="","",INDEX(Commutation!$K:$K,MATCH(C39,Commutation!$A:$A,0))) -> 0.61230923 | E39: =IF(Inputs!$B$7+36-1>MAX(MORTALITY!$A:$A),"",IFERROR(INDEX(Commutation!$F:$F,MATCH(C39,Commutation!$A:$A,0)),0)) -> 2222018.3 | F39: =IF(Inputs!$B$7+36-1>MAX(MORTALITY!$A:$A),"",IFERROR(INDEX(Commutation!$H:$H,MATCH(C39+1,Commutation!$A:$A,0)),0)) -> 33097677 | G39: =IF(Inputs!$B$7+36-1>MAX(MORTALITY!$A:$A),"",IFERROR(INDEX(Commutation!$I:$I,MATCH(C39,Commutation!$A:$A,0)),0)) -> 1360562.3 | H39: =IF(Inputs!$B$7+36-1>MAX(MORTALITY!$A:$A),"",IFERROR(1000*INDEX(Commutation!$I:$I,MATCH(Inputs!$B$7,Commutation!$A:$A,0))/INDEX(Commutation!$H:$H,MATCH(Inputs!$B$7,Commutation!$A:$A,0)),0)) -> 11.090171 | I39: =IF(Inputs!$B$7+36-1>MAX(MORTALITY!$A:$A),"",IFERROR((1000*G39-H39*F39)/E39,0)) -> 447.11757
A40: =IF(Inputs!$B$7+37-1>MAX(MORTALITY!$A:$A),"",Inputs!$B$7) -> 16 | B40: =IF(Inputs!$B$7+37-1>MAX(MORTALITY!$A:$A),"",37) -> 37 | C40: =IF(Inputs!$B$7+37-1>MAX(MORTALITY!$A:$A),"",Inputs!$B$7+37-1) -> 52 | D40: =IF(C40="","",INDEX(Commutation!$K:$K,MATCH(C40,Commutation!$A:$A,0))) -> 0.62260899 | E40: =IF(Inputs!$B$7+37-1>MAX(MORTALITY!$A:$A),"",IFERROR(INDEX(Commutation!$F:$F,MATCH(C40,Commutation!$A:$A,0)),0)) -> 2139055.7 | F40: =IF(Inputs!$B$7+37-1>MAX(MORTALITY!$A:$A),"",IFERROR(INDEX(Commutation!$H:$H,MATCH(C40+1,Commutation!$A:$A,0)),0)) -> 30958621 | G40: =IF(Inputs!$B$7+37-1>MAX(MORTALITY!$A:$A),"",IFERROR(INDEX(Commutation!$I:$I,MATCH(C40,Commutation!$A:$A,0)),0)) -> 1331795.3 | H40: =IF(Inputs!$B$7+37-1>MAX(MORTALITY!$A:$A),"",IFERROR(1000*INDEX(Commutation!$I:$I,MATCH(Inputs!$B$7,Commutation!$A:$A,0))/INDEX(Commutation!$H:$H,MATCH(Inputs!$B$7,Commutation!$A:$A,0)),0)) -> 11.090171 | I40: =IF(Inputs!$B$7+37-1>MAX(MORTALITY!$A:$A),"",IFERROR((1000*G40-H40*F40)/E40,0)) -> 462.10059
